Workbook
Name Actual: [12]Soportes!$M$2:$M$3
Name Mes: [21]Toggle!$G$2:$G$13
Name Mes: [22]Toggle!$G$2:$G$13
Name Mes: [23]Toggle!$D$3:$D$14
Name Meses: [21]Toggle!$A$1:$A$192
Name Meses: [22]Toggle!$A$1:$A$192
Name Meses: [23]Toggle!$G$3:$G$254
Name Start_12: '[24]Variables Relevantes'!#REF!
Name Start_12: '[25]Variables Relevantes'!#REF!
Name Start_13: '[24]EDE''s'!#REF!
Name Start_13: '[25]EDE''s'!#REF!
Name Start_14: [24]CDEEE!#REF!
Name Start_14: [25]CDEEE!#REF!
Name Start_15: [24]EGEHID!#REF!
Name Start_15: [25]EGEHID!#REF!
Name Start_16: [24]ETED!#REF!
Name Start_16: [25]ETED!#REF!
Name Start_17: '[24]Anexo Res Financieros'!#REF!
Name Start_17: #REF!
Name Start_18: '[26]Anexo Res Financieros'!#REF!
Name Start_3: #REF!
Name Start_62: #REF!
Name Start_63: #REF!
Name Status: [22]Toggle!$C$3:$C$4
Name Status: [21]Toggle!$C$3:$C$4
Name Toggle: [22]Toggle!$B$3:$B$4
Name Toggle: [21]Toggle!$B$3:$B$4

Sheet Variables Relevantes
B2: Ministerio de Energía y Minas
B3: Variables Relevantes
B4: Valores según indicación
L5: 2009 | M5: 2009 | N5: 2009 | O5: 2009 | P5: 2009 | Q5: 2009 | R5: 2009 | S5: 2009 | T5: 2009 | U5: 2009 | V5: 2009 | W5: 2009 | X5: 2010 | Y5: 2010 | Z5: 2010 | AA5: 2010 | AB5: 2010 | AC5: 2010 | AD5: 2010 | AE5: 2010 | AF5: 2010 | AG5: 2010 | AH5: 2010 | AI5: 2010 | AJ5: 2011 | AK5: 2011 | AL5: 2011 | AM5: 2011 | AN5: 2011 | AO5: 2011 | AP5: 2011 | AQ5: 2011 | AR5: 2011 | AS5: 2011 | AT5: 2011 | AU5: 2011 | AV5: 2012 | AW5: 2012 | AX5: 2012 | AY5: 2012 | AZ5: 2012 | BA5: 2012 | BB5: 2012 | BC5: 2012 | BD5: 2012 | BE5: 2012 | BF5: 2012 | BG5: 2012 | BH5: 2013 | BI5: 2013 | BJ5: 2013 | BK5: 2013 | BL5: 2013 | BM5: 2013 | BN5: 2013 | BO5: 2013 | BP5: 2013 | BQ5: 2013 | BR5: 2013 | BS5: 2013 | BT5: 2014 | BU5: 2014 | BV5: 2014 | BW5: 2014 | BX5: 2014 | BY5: 2014 | BZ5: 2014
C6: Ene21-Nov21 | D6: Ene20-Nov20 | E6: Comparación 2020 - 2021 | H6: Ene19-Nov19 | I6: Comparación 2019 - 2020 | FL6: Acumulado Año
E7: D | F7: D% | I7: D | J7: D% | L7: 39814 | M7: 39845 | N7: 39873 | O7: 39904 | P7: 39934 | Q7: 39965 | R7: 39995 | S7: 40026 | T7: 40057 | U7: 40087 | V7: 40118 | W7: 40148 | X7: 40179 | Y7: 40210 | Z7: 40238 | AA7: 40269 | AB7: 40299 | AC7: 40330 | AD7: 40360 | AE7: 40391 | AF7: 40422 | AG7: 40452 | AH7: 40483 | AI7: 40513 | AJ7: 40544 | AK7: 40575 | AL7: 40603 | AM7: 40634 | AN7: 40664 | AO7: 40695 | AP7: 40725 | AQ7: 40756 | AR7: 40787 | AS7: 40817 | AT7: 40848 | AU7: 40878 | AV7: 40909 | AW7: 40940 | AX7: 40969 | AY7: 41000 | AZ7: 41030 | BA7: 41061 | BB7: 41091 | BC7: 41122 | BD7: 41153 | BE7: 41183 | BF7: 41214 | BG7: 41244 | BH7: 41275 | BI7: 41306 | BJ7: 41334 | BK7: 41365 | BL7: 41395 | BM7: 41426 | BN7: 41456 | BO7: 41487 | BP7: 41518 | BQ7: 41548 | BR7: 41579 | BS7: 41609 | BT7: 41640 | BU7: 41671 | BV7: 41699 | BW7: 41730 | BX7: 41760 | BY7: 41791 | BZ7: 41821 | CA7: 41852 | CB7: 41883 | CC7: 41913 | CD7: 41944 | CE7: 41974 | CF7: 42005 | CG7: 42036 | CH7: 42064 | CI7: 42095 | CJ7: 42125 | CK7: 42156 | CL7: 42186 | CM7: 42217 | CN7: 42248 | CO7: 42278 | CP7: 42309 | CQ7: 42339 | CR7: 42370 | CS7: 42401 | CT7: 42430 | CU7: 42461 | CV7: 42491 | CW7: 42522 | CX7: 42552 | CY7: 42583 | CZ7: 42614 | DA7: 42644 | DB7: 42675 | DC7: 42705 | DD7: 42736 | DE7: 42767 | DF7: 42795 | DG7: 42826 | DH7: 42856 | DI7: 42887 | DJ7: 42917 | DK7: 42948 | DL7: 42979 | DM7: 43009 | DN7: 43040 | DO7: 43070 | DP7: 43101 | DQ7: 43132 | DR7: 43160 | DS7: 43191 | DT7: 43221 | DU7: 43252 | DV7: 43282 | DW7: 43313 | DX7: 43344 | DY7: 43374 | DZ7: 43405 | EA7: 43435 | EB7: 43466 | EC7: 43497 | ED7: 43525 | EE7: 43556 | EF7: 43586 | EG7: 43617 | EH7: 43647 | EI7: 43678 | EJ7: 43709 | EK7: 43739 | EL7: 43770 | EM7: 43800 | EN7: 43831 | EO7: 43862 | EP7: 43891 | EQ7: 43922 | ER7: 43952 | ES7: 43983 | ET7: 44013 | EU7: 44044 | EV7: 44075 | EW7: 44105 | EX7: 44136 | EY7: 44166 | EZ7: 44197 | FA7: 44228 | FB7: 44256 | FC7: 44287 | FD7: 44317 | FE7: 44348 | FF7: 44378 | FG7: 44409 | FH7: 44440 | FI7: 44470 | FJ7: 44501 | FL7: 2009 | FM7: 2010 | FN7: 2011 | FO7: 2012 | FP7: 2013 | FQ7: 2014 | FR7: 2015 | FS7: 2016 | FT7: 2017 | FU7: 2018 | FV7: 2019 | FW7: 2020 | FX7: 2021
B8: Precios Combustibles
A9: 8 | B9: Fuel Oil # 2 (US$/BBL) | C9: 76.219469 | D9: 46.044103 | E9: 30.175366 | F9: 0.6553579 | H9: 76.474631 | I9: -30.430528 | J9: -0.39791664 | L9: 58.9014 | M9: 51.7628 | N9: 51.7713 | O9: 55.9641 | P9: 61.4095 | Q9: 73.4096 | R9: 68.1985 | S9: 78.093 | T9: 72.565 | U9: 80.807141 | V9: 82.9503 | W9: 82.070386 | X9: 85.064147 | Y9: 82.077284 | Z9: 86.686996 | AA9: 92.3491 | AB9: 84.848925 | AC9: 84.548482 | AD9: 82.5055 | AE9: 84.976214 | AF9: 87.0492 | AG9: 93.3613 | AH9: 96.12645 | AI9: 101.67704 | AJ9: 107.68002 | AK9: 114.97611 | AL9: 126.29875 | AM9: 133.5949 | AN9: 123.5946 | AO9: 124.0428 | AP9: 128.10735 | AQ9: 122.63635 | AR9: 121.9579 | AS9: 123.1108 | AT9: 127.42275 | AU9: 119.7879 | AV9: 126.71946 | AW9: 132.7872 | AX9: 134.60045 | AY9: 132.29979 | AZ9: 122.38189 | BA9: 109.8258 | BB9: 116.9128 | BC9: 127.2463 | BD9: 131.65851 | BE9: 130.21881 | BF9: 123.90294 | BG9: 123.69168 | BH9: 126.9378 | BI9: 132.35593 | BJ9: 122.42076 | BK9: 115.14739 | BL9: 114.63575 | BM9: 116.43156 | BN9: 120.60796 | BO9: 124.39885 | BP9: 123.50583 | BQ9: 122.19553 | BR9: 119.06823 | BS9: 123.3216 | BT9: 120.7294 | BU9: 120.99979 | BV9: 119.7954 | BW9: 121.1192 | BX9: 120.0848 | BY9: 120.8904 | BZ9: 117.5979 | CA9: 116.3406 | CB9: 111.0988 | CC9: 101.83959 | CD9: 93.4794 | CE9: 72.6562 | CF9: 64.76022 | CG9: 73.518458 | CH9: 68.7939 | CI9: 72.086 | CJ9: 77.48013 | CK9: 72.4437 | CL9: 64.756745 | CM9: 57.9812 | CN9: 58.2938 | CO9: 58.242927 | CP9: 54.294063 | CQ9: 43.0395 | CR9: 38.148821 | CS9: 38.08245 | CT9: 41.849564 | CU9: 46.608 | CV9: 53.7636 | CW9: 57.644236 | CX9: 51.47835 | CY9: 53.399987 | CZ9: 54.6616 | DA9: 60.1302 | DB9: 54.87006 | DC9: 61.6612 | DD9: 63.222 | DE9: 63.899 | DF9: 59.364809 | DG9: 61.130337 | DH9: 57.995891 | DI9: 53.709409 | DJ9: 57.5484 | DK9: 67.1958 | DL9: 61.344835 | DM9: 67.689491 | DN9: 73.25304 | DO9: 74.64198 | DP9: 79.632 | DQ9: 73.779632 | DR9: 74.8776 | DS9: 82.238 | DT9: 87.423382 | DU9: 84.6566 | DV9: 84.647033 | DW9: 86.747713 | DX9: 90.847768 | DY9: 94.182261 | DZ9: 81.28449 | EA9: 69.015567 | EB9: 72.0832 | EC9: 77.708842 | ED9: 79.0566 | EE9: 81.5034 | EF9: 80.225536 | EG9: 73.06866 | EH9: 76.6082 | EI9: 72.879545 | EJ9: 77.56056 | EK9: 76.282774 | EL9: 74.243621 | EM9: 77.0518 | EN9: 72.8078 | EO9: 62.952916 | EP9: 43.115864 | EQ9: 27.4876 | ER9: 31.17072 | ES9: 41.835818 | ET9: 45.753273 | EU9: 46.4864 | EV9: 42.303 | EW9: 44.441727 | EX9: 48.130011 | EY9: 56.407527 | EZ9: 59.687084 | FA9: 67.236695 | FB9: 70.246643 | FC9: 68.4642 | FD9: 72.77382 | FE9: 76.967482 | FF9: 77.3088 | FG9: 75.104782 | FH9: 83.5382 | FI9: 96.42 | FJ9: 90.66645 | FL9: 68.158586 | FM9: 88.43922 | FN9: 122.76752 | FO9: 126.02047 | FP9: 121.75227 | FQ9: 111.38596 | FR9: 63.807554 | FS9: 51.024839 | FT9: 63.416249 | FU9: 82.444337 | FV9: 76.522728 | FW9: 46.907721 | FX9: =C9 -> 76.219469
A10: 12 | B10: Fuel Oil # 2 (US$/MMBTU) | C10: 13.853048 | D10: 8.3686119 | E10: 5.4844359 | F10: 0.6553579 | H10: 13.899424 | I10: -5.5308121 | J10: -0.39791664 | L10: 10.705453 | M10: 9.4079971 | N10: 9.409542 | O10: 10.171592 | P10: 11.161305 | Q10: 13.342348 | R10: 12.39522 | S10: 14.193566 | T10: 13.18884 | U10: 14.686867 | V10: 15.07639 | W10: 14.916464 | X10: 15.460587 | Y10: 14.917718 | Z10: 15.755543 | AA10: 16.784642 | AB10: 15.421469 | AC10: 15.366863 | AD10: 14.995547 | AE10: 15.444604 | AF10: 15.821374 | AG10: 16.968611 | AH10: 17.471183 | AI10: 18.480014 | AJ10: 19.571069 | AK10: 20.897147 | AL10: 22.955061 | AM10: 24.281152 | AN10: 22.463577 | AO10: 22.545038 | AP10: 23.283779 | AQ10: 22.289413 | AR10: 22.166103 | AS10: 22.375645 | AT10: 23.159351 | AU10: 21.771701 | AV10: 23.031527 | AW10: 24.134351 | AX10: 24.463914 | AY10: 24.045763 | AZ10: 22.243164 | BA10: 19.961069 | BB10: 21.249146 | BC10: 23.127282 | BD10: 23.929209 | BE10: 23.667541 | BF10: 22.519618 | BG10: 22.481221 | BH10: 23.07121 | BI10: 24.055966 | BJ10: 22.250229 | BK10: 20.928279 | BL10: 20.835288 | BM10: 21.161679 | BN10: 21.920749 | BO10: 22.60975 | BP10: 22.447443 | BQ10: 22.209293 | BR10: 21.6409 | BS10: 22.413959 | BT10: 21.942821 | BU10: 21.991965 | BV10: 21.773064 | BW10: 22.013668 | BX10: 21.825663 | BY10: 21.972083 | BZ10: 21.373664 | CA10: 21.145147 | CB10: 20.192439 | CC10: 18.509559 | CD10: 16.990076 | CE10: 13.205416 | CF10: 11.770305 | CG10: 13.362133 | CH10: 12.503435 | CI10: 13.101781 | CJ10: 14.082176 | CK10: 13.166794 | CL10: 11.769674 | CM10: 10.538204 | CN10: 10.59502 | CO10: 10.585774 | CP10: 9.8680595 | CQ10: 7.8225191 | CR10: 6.933628 | CS10: 6.9215649 | CT10: 7.6062457 | CU10: 8.4711014 | CV10: 9.7716467 | CW10: 10.47696 | CX10: 9.3562977 | CY10: 9.7055592 | CZ10: 9.9348601 | DA10: 10.92879 | DB10: 9.9727481 | DC10: 11.207052 | DD10: 11.490731 | DE10: 11.613777 | DF10: 10.789678 | DG10: 11.110566 | DH10: 10.540874 | DI10: 9.7617974 | DJ10: 10.459542 | DK10: 12.212977 | DL10: 11.149552 | DM10: 12.302706 | DN10: 13.313893 | DO10: 13.566336 | DP10: 14.473282 | DQ10: 13.409602 | DR10: 13.60916 | DS10: 14.946928 | DT10: 15.889382 | DU10: 15.386514 | DV10: 15.384775 | DW10: 15.766578 | DX10: 16.511772 | DY10: 17.117823 | DZ10: 14.773626 | EA10: 12.543723 | EB10: 13.101272 | EC10: 14.123744 | ED10: 14.368702 | EE10: 14.813413 | EF10: 14.581159 | EG10: 13.280382 | EH10: 13.9237 | EI10: 13.24601 | EJ10: 14.096794 | EK10: 13.864554 | EL10: 13.493933 | EM10: 14.004326 | EN10: 13.23297 | EO10: 11.441824 | EP10: 7.8363983 | EQ10: 4.9959288 | ER10: 5.6653435 | ES10: 7.6037474 | ET10: 8.3157529 | EU10: 8.4490004 | EV10: 7.6886587 | EW10: 8.0773768 | EX10: 8.74773 | EY10: 10.252186 | EZ10: 10.848252 | FA10: 12.22041 | FB10: 12.767474 | FC10: 12.443511 | FD10: 13.226794 | FE10: 13.989001 | FF10: 14.051036 | FG10: 13.650451 | FH10: 15.183242 | FI10: 17.524537 | FJ10: 16.478817 | FL10: 12.387965 | FM10: 16.074013 | FN10: 22.313253 | FO10: 22.904484 | FP10: 22.128729 | FQ10: 20.24463 | FR10: 11.597156 | FS10: 9.2738711 | FT10: 11.526036 | FU10: 14.984431 | FV10: 13.908166 | FW10: 8.5255764 | FX10: =C10 -> 13.853048
A11: 9 | B11: Fuel Oil # 6 (US$/BBL) | C11: 60.029948 | D11: 34.403853 | E11: 25.626095 | F11: 0.74486118 | H11: 54.717104 | I11: -20.31325 | J11: -0.37124133 | L11: 38.6775 | M11: 40.6289 | N11: 37.608 | O11: 42.8619 | P11: 52.2375 | Q11: 60.1477 | R11: 59.8432 | S11: 66.2107 | T11: 64.0917 | U11: 67.0841 | V11: 71.3105 | W11: 69.067 | X11: 71.4961 | Y11: 69.8368 | Z11: 69.7804 | AA11: 72.9071 | AB11: 66.705 | AC11: 66.0398 | AD11: 66.2548 | AE11: 66.6318 | AF11: 67.169 | AG11: 71.5119 | AH11: 72.4025 | AI11: 75.7114 | AJ11: 79.045 | AK11: 87.9276 | AL11: 95.5141 | AM11: 101.4613 | AN11: 95.4012 | AO11: 98.65 | AP11: 100.5588 | AQ11: 97.4228 | AR11: 97.630952 | AS11: 99.265476 | AT11: 100.31625 | AU11: 95.252381 | AV11: 102.89375 | AW11: 109.09125 | AX11: 111.62159 | AY11: 108.6 | AZ11: 98.593182 | BA11: 86.915476 | BB11: 91.579762 | BC11: 99.518478 | BD11: 100.90263 | BE11: 96.180435 | BF11: 92.93375 | BG11: 93.654 | BH11: 96.698333 | BI11: 98.950526 | BJ11: 95.7855 | BK11: 91.488636 | BL11: 91.141818 | BM11: 89.976 | BN11: 91.294545 | BO11: 93.104545 | BP11: 94.584 | BQ11: 92.10913 | BR11: 89.546316 | BS11: 91.892857 | BT11: 88.237619 | BU11: 90.344737 | BV11: 89.31381 | BW11: 90.735238 | BX11: 91.779524 | BY11: 93.101905 | BZ11: 88.975 | CA11: 87.641429 | CB11: 85.90619 | CC11: 73.147391 | CD11: 63.972222 | CE11: 48.875238 | CF11: 38.487 | CG11: 48.698421 | CH11: 45.855 | CI11: 48.552381 | CJ11: 52.36 | CK11: 51.861818 | CL11: 44.388182 | CM11: 35.175238 | CN11: 34.402381 | CO11: 34.603864 | CP11: 31.723684 | CQ11: 23.035909 | CR11: 19.054211 | CS11: 20.3665 | CT11: 23.640909 | CU11: 25.910476 | CV11: 31.819524 | CW11: 35.049091 | CX11: 33.8275 | CY11: 34.37 | CZ11: 36.410476 | DA11: 40.091905 | DB11: 38.1235 | DC11: 45.313333 | DD11: 46.648 | DE11: 46.948 | DF11: 43.35 | DG11: 44.524737 | DH11: 43.760455 | DI11: 41.572727 | DJ11: 44.596316 | DK11: 47.43 | DL11: 48.788 | DM11: 49.368636 | DN11: 55.234 | DO11: 54.2005 | DP11: 56.795714 | DQ11: 54.146316 | DR11: 54.357143 | DS11: 57.545238 | DT11: 64.940909 | DU11: 64.644762 | DV11: 67.159524 | DW11: 63.893478 | DX11: 66.354737 | DY11: 70.510435 | DZ11: 61.483 | EA11: 52.828333 | EB11: 55.820952 | EC11: 63.532105 | ED11: 63.990952 | EE11: 66.04619 | EF11: 61.661818 | EG11: 55.7805 | EH11: 58.92 | EI11: 45.339091 | EJ11: 50.4655 | EK11: 43.022609 | EL11: 37.308421 | EM11: 41.417143 | EN11: 43.393333 | EO11: 44.618421 | EP11: 24.928636 | EQ11: 17.28619 | ER11: 23.965 | ES11: 32.899545 | ET11: 37.432727 | EU11: 40.315714 | EV11: 36.125714 | EW11: 37.695 | EX11: 39.782105 | EY11: 44.087273 | EZ11: 48.4758 | FA11: 53.446842 | FB11: 55.751957 | FC11: 56.289762 | FD11: 57.82525 | FE11: 61.712727 | FF11: 61.661905 | FG11: 60.64 | FH11: 65.202381 | FI11: 72.97381 | FJ11: 66.349 | FL11: 55.814058 | FM11: 69.703883 | FN11: 95.703822 | FO11: 99.373692 | FP11: 93.047684 | FQ11: 82.669192 | FR11: 40.76199 | FS11: 31.998119 | FT11: 47.201781 | FU11: 61.221632 | FV11: 53.608774 | FW11: 35.210805 | FX11: =C11 -> 60.029948
A12: 13 | B12: Fuel Oil # 6 (US$/MMBTU) | C12: 10.136769 | D12: 5.8094991 | E12: 4.3272704 | F12: 0.74486118 | H12: 9.2396325 | I12: -3.4301334 | J12: -0.37124133 | L12: 6.531155 | M12: 6.8606721 | N12: 6.3505572 | O12: 7.2377406 | P12: 8.820922 | Q12: 10.156653 | R12: 10.105235 | S12: 11.180463 | T12: 10.822644 | U12: 11.327947 | V12: 12.041624 | W12: 11.662783 | X12: 12.072965 | Y12: 11.792773 | Z12: 11.783249 | AA12: 12.311229 | AB12: 11.263931 | AC12: 11.151604 | AD12: 11.187909 | AE12: 11.25157 | AF12: 11.342283 | AG12: 12.075633 | AH12: 12.226022 | AI12: 12.784769 | AJ12: 13.347687 | AK12: 14.847619 | AL12: 16.12869 | AM12: 17.132945 | AN12: 16.109625 | AO12: 16.658224 | AP12: 16.980547 | AQ12: 16.450996 | AR12: 16.486145 | AS12: 16.762154 | AT12: 16.93959 | AU12: 16.084495 | AV12: 17.374831 | AW12: 18.421353 | AX12: 18.848631 | AY12: 18.338399 | AZ12: 16.648629 | BA12: 14.67671 | BB12: 15.46433 | BC12: 16.804876 | BD12: 17.038607 | BE12: 16.241208 | BF12: 15.692967 | BG12: 15.81459 | BH12: 16.328661 | BI12: 16.708971 | BJ12: 16.174519 | BK12: 15.448942 | BL12: 15.390378 | BM12: 15.193516 | BN12: 15.416168 | BO12: 15.721808 | BP12: 15.971631 | BQ12: 15.55372 | BR12: 15.120958 | BS12: 15.5172 | BT12: 14.899969 | BU12: 15.255781 | BV12: 15.081697 | BW12: 15.321722 | BX12: 15.498062 | BY12: 15.721362 | BZ12: 15.024485 | CA12: 14.799296 | CB12: 14.50628 | CC12: 12.351805 | CD12: 10.802469 | CE12: 8.2531641 | CF12: 6.4989868 | CG12: 8.2233065 | CH12: 7.7431611 | CI12: 8.1986459 | CJ12: 8.8416076 | CK12: 8.7574837 | CL12: 7.4954714 | CM12: 5.9397565 | CN12: 5.8092504 | CO12: 5.8432732 | CP12: 5.3569207 | CQ12: 3.8898867 | CR12: 3.2175296 | CS12: 3.4391253 | CT12: 3.9920481 | CU12: 4.3752915 | CV12: 5.3731043 | CW12: 5.9184551 | CX12: 5.7121749 | CY12: 5.8037825 | CZ12: 6.1483411 | DA12: 6.769994 | DB12: 6.4376055 | DC12: 7.6516942 | DD12: 7.8770686 | DE12: 7.9277271 | DF12: 7.3201621 | DG12: 7.5185304 | DH12: 7.3894722 | DI12: 7.0200485 | DJ12: 7.5306173 | DK12: 8.0091185 | DL12: 8.238433 | DM12: 8.3364803 | DN12: 9.3269166 | DO12: 9.1523978 | DP12: 9.5906306 | DQ12: 9.1432482 | DR12: 9.1788488 | DS12: 9.7171966 | DT12: 10.966043 | DU12: 10.916035 | DV12: 11.340683 | DW12: 10.789172 | DX12: 11.204785 | DY12: 11.906524 | DZ12: 10.382134 | EA12: 8.9206912 | EB12: 9.4260305 | EC12: 10.72815 | ED12: 10.805632 | EE12: 11.152683 | EF12: 10.41233 | EG12: 9.4191996 | EH12: 9.9493414 | EI12: 7.6560437 | EJ12: 8.5216988 | EK12: 7.2648782 | EL12: 6.2999698 | EM12: 6.9937762 | EN12: 7.3274795 | EO12: 7.5343501 | EP12: 4.2094962 | EQ12: 2.9189785 | ER12: 4.0467747 | ES12: 5.5554788 | ET12: 6.3209604 | EU12: 6.8077869 | EV12: 6.1002557 | EW12: 6.3652482 | EX12: 6.7176807 | EY12: 7.4446594 | EZ12: 8.1857143 | FA12: 9.0251338 | FB12: 9.4143797 | FC12: 9.5051945 | FD12: 9.7644799 | FE12: 10.420927 | FF12: 10.412345 | FG12: 10.239784 | FH12: 11.010196 | FI12: 12.322494 | FJ12: 11.203816 | FL12: 9.4248663 | FM12: 11.770328 | FN12: 16.160726 | FO12: 16.780428 | FP12: 15.712206 | FQ12: 13.959674 | FR12: 6.8831459 | FS12: 5.4032622 | FT12: 7.970581 | FU12: 10.337999 | FV12: 9.0524778 | FW12: 5.9457624 | FX12: =C12 -> 10.136769
A13: 10 | B13: Gas Natural (US$/MMBTU) | C13: 3.4511999 | D13: 2.0353421 | E13: 1.4158578 | F13: 0.69563626 | H13: 2.6928762 | I13: -0.65753402 | J13: -0.24417537 | L13: 5.7933 | M13: 5.1954 | N13: 4.4096842 | O13: 4.0367 | P13: 3.5966 | Q13: 3.8816 | R13: 3.9373 | S13: 3.5682 | T13: 3.3675 | U13: 3.2839 | V13: 4.7618 | W13: 4.6042 | X13: 5.2869 | Y13: 5.6522 | Z13: 5.2503 | AA13: 4.3756 | AB13: 4.0809 | AC13: 4.1173 | AD13: 4.7597 | AE13: 4.562 | AF13: 4.3143 | AG13: 3.887 | AH13: 3.5951 | AI13: 3.9998 | AJ13: 4.2709 | AK13: 4.4882 | AL13: 4.0724 | AM13: 4.0387 | AN13: 4.2454 | AO13: 4.3402 | AP13: 4.5385 | AQ13: 4.3683 | AR13: 4.0021 | AS13: 3.8752 | AT13: 3.6028 | AU13: 3.5922 | AV13: 3.3019 | AW13: 2.7478 | AX13: 2.53 | AY13: 2.3347 | AZ13: 2.0384 | BA13: 2.4766 | BB13: 2.4646 | BC13: 2.9214 | BD13: 2.8455 | BE13: 2.8614 | BF13: 3.4663 | BG13: 3.6848 | BH13: 3.4636 | BI13: 3.3569 | BJ13: 3.3013 | BK13: 3.7144 | BL13: 4.132 | BM13: 4.1010455 | BN13: 3.8492 | BO13: 3.6535 | BP13: 3.3981 | BQ13: 3.6206 | BR13: 3.652 | BS13: 3.6074 | BT13: 4.2523 | BU13: 4.4908 | BV13: 5.2067 | BW13: 4.4984 | BX13: 4.5708 | BY13: 4.5616 | BZ13: 4.6048 | CA13: 4.0812 | CB13: 3.8764 | CC13: 3.9129 | CD13: 3.8261 | CE13: 4.1954 | CF13: 3.5699 | CG13: 3.0436 | CH13: 2.7512 | CI13: 2.7488 | CJ13: 2.5851 | CK13: 2.8564 | CL13: 2.7613 | CM13: 2.8147 | CN13: 2.7573 | CO13: 2.6529 | CP13: 2.4092 | CQ13: 2.2832 | CR13: 2.0388 | CS13: 2.2371 | CT13: 1.9784 | CU13: 1.7862 | CV13: 2.0000476 | CW13: 2.0738571 | CX13: 2.5633636 | CY13: 2.7633 | CZ13: 2.7238696 | DA13: 2.8957143 | DB13: 3.061619 | DC13: 2.8473333 | DD13: 3.543 | DE13: 3.35 | DF13: 2.9531579 | DG13: 2.9526957 | DH13: 3.2492273 | DI13: 2.9999091 | DJ13: 2.9999091 | DK13: 2.97225 | DL13: 2.8945652 | DM13: 3.00365 | DN13: 2.9199545 | DO13: 3.0425714 | DP13: 2.7986667 | DQ13: 3.1451905 | DR13: 2.7065789 | DS13: 2.6955238 | DT13: 2.7193333 | DU13: 2.8155455 | DV13: 2.9412381 | DW13: 2.8029048 | DX13: 2.898913 | DY13: 2.8815789 | DZ13: 3.1912609 | EA13: 3.9589524 | EB13: 4.1080526 | EC13: 3.1371 | ED13: 2.6855789 | EE13: 2.8159524 | EF13: 2.6129048 | EG13: 2.6 | EH13: 2.3488 | EI13: 2.3232857 | EJ13: 2.1644545 | EK13: 2.5119 | EL13: 2.3136087 | EM13: 2.65855 | EN13: 2.307619 | EO13: 2.0635238 | EP13: 1.8571053 | EQ13: 1.7511304 | ER13: 1.8059444 | ES13: 1.81625 | ET13: 1.7106818 | EU13: 1.7573182 | EV13: 2.2644762 | EW13: 2.2897143 | EX13: 2.765 | EY13: 2.91845 | EZ13: 2.619 | FA13: 2.6346842 | FB13: 2.9001579 | FC13: 2.6358261 | FD13: 2.656 | FE13: 2.9581111 | FF13: 3.2116818 | FG13: 3.7820476 | FH13: 4.0005 | FI13: 4.9880952 | FJ13: 5.5770952 | FL13: 4.2030154 | FM13: 4.4900917 | FN13: 4.119575 | FO13: 2.8061167 | FP13: 3.6541705 | FQ13: 4.3397833 | FR13: 2.7694667 | FS13: 2.4141337 | FT13: 3.0734075 | FU13: 2.9629739 | FV13: 2.6900156 | FW13: 2.1089345 | FX13: =C13 -> 3.4511999
B14: Gas Natural Conversion (US$/MMBTU) | C14: 9.46888 | D14: 8.1094962 | E14: 1.3593837 | F14: 0.16762863 | H14: 0 | I14: 8.1094962 | J14: 0 | L14: 0 | M14: 0 | N14: 0 | O14: 0 | P14: 0 | Q14: 0 | R14: 0 | S14: 0 | T14: 0 | U14: 0 | V14: 0 | W14: 0 | X14: 0 | Y14: 0 | Z14: 0 | AA14: 0 | AB14: 0 | AC14: 0 | AD14: 0 | AE14: 0 | AF14: 0 | AG14: 0 | AH14: 0 | AI14: 0 | AJ14: 0 | AK14: 0 | AL14: 0 | AM14: 0 | AN14: 0 | AO14: 0 | AP14: 0 | AQ14: 0 | AR14: 0 | AS14: 0 | AT14: 0 | AU14: 0 | AV14: 0 | AW14: 0 | AX14: 0 | AY14: 0 | AZ14: 0 | BA14: 0 | BB14: 0 | BC14: 0 | BD14: 0 | BE14: 0 | BF14: 0 | BG14: 0 | BH14: 0 | BI14: 0 | BJ14: 0 | BK14: 0 | BL14: 0 | BM14: 0 | BN14: 0 | BO14: 0 | BP14: 0 | BQ14: 0 | BR14: 0 | BS14: 0 | BT14: 0 | BU14: 0 | BV14: 0 | BW14: 0 | BX14: 0 | BY14: 0 | BZ14: 0 | CA14: 0 | CB14: 0 | CC14: 0 | CD14: 0 | CE14: 0 | CF14: 0 | CG14: 0 | CH14: 0 | CI14: 0 | CJ14: 0 | CK14: 0 | CL14: 0 | CM14: 0 | CN14: 0 | CO14: 0 | CP14: 0 | CQ14: 0 | CR14: 0 | CS14: 0 | CT14: 0 | CU14: 0 | CV14: 0 | CW14: 0 | CX14: 0 | CY14: 0 | CZ14: 0 | DA14: 0 | DB14: 0 | DC14: 0 | DD14: 0 | DE14: 0 | DF14: 0 | DG14: 0 | DH14: 0 | DI14: 0 | DJ14: 0 | DK14: 0 | DL14: 0 | DM14: 0 | DN14: 0 | DO14: 0 | DP14: 0 | DQ14: 0 | DR14: 0 | DS14: 0 | DT14: 0 | DU14: 0 | DV14: 0 | DW14: 0 | DX14: 0 | DY14: 0 | DZ14: 0 | EA14: 0 | EB14: 0 | EC14: 0 | ED14: 0 | EE14: 0 | EF14: 0 | EG14: 0 | EH14: 0 | EI14: 0 | EJ14: 0 | EK14: 0 | EL14: 0 | EM14: 0 | EN14: 0 | EO14: 0 | EP14: 0 | EQ14: 0 | ER14: 0 | ES14: 0 | ET14: 0 | EU14: 7.5209159 | EV14: 8.1041476 | EW14: 8.1331714 | EX14: 8.67975 | EY14: 8.8562175 | EZ14: 8.51185 | FA14: 8.5298868 | FB14: 8.8351816 | FC14: 8.5312 | FD14: 8.5544 | FE14: 8.9018278 | FF14: 9.1934341 | FG14: 9.8493548 | FH14: 10.100575 | FI14: 11.23631 | FJ14: 11.91366 | FL14: 0 | FM14: 0 | FN14: 0 | FO14: 0 | FP14: 0 | FQ14: 0 | FR14: 0 | FS14: 0 | FT14: 0 | FU14: 0 | FV14: 0 | FW14: 8.2588405 | FX14: =C14 -> 9.46888
A15: 11 | B15: Carbón Mineral (US$/Ton) | C15: 113.89773 | D15: 50.660303 | E15: 63.237424 | F15: 1.2482638 | H15: 57.625978 | I15: -6.9656749 | J15: -0.12087734 | L15: 77.1 | M15: 69.38 | N15: 56.63 | O15: 58.5 | P15: 54.9 | Q15: 56.31 | R15: 57.1 | S15: 57 | T15: 52.38 | U15: 55.25 | V15: 54.63 | W15: 57.15 | X15: 62.25 | Y15: 59.63 | Z15: 60.19 | AA15: 68.8 | AB15: 78.13 | AC15: 79.63 | AD15: 81.15 | AE15: 78.75 | AF15: 78.69 | AG15: 84.45 | AH15: 91.13 | AI15: 108.5 | AJ15: 114.88 | AK15: 111.13 | AL15: 116 | AM15: 119.3 | AN15: 114.5 | AO15: 113.8 | AP15: 114.33 | AQ15: 115 | AR15: 111.6625 | AS15: 103 | AT15: 101.125 | AU15: 97.8125 | AV15: 95.8 | AW15: 90.4167 | AX15: 88.3 | AY15: 88 | AZ15: 79.45 | BA15: 78.47 | BB15: 80.875 | BC15: 85.57 | BD15: 80.8125 | BE15: 77.0625 | BF15: 78.45 | BG15: 80.8 | BH15: 78.125 | BI15: 80.3 | BJ15: 78.28 | BK15: 74.65 | BL15: 73.03 | BM15: 66.4625 | BN15: 65.6875 | BO15: 66.53 | BP15: 65.5375 | BQ15: 69.2 | BR15: 72.95 | BS15: 70.5 | BT15: 72.69 | BU15: 69.3375 | BV15: 64.8625 | BW15: 68.0375 | BX15: 67.91 | BY15: 63.675 | BZ15: 66 | CA15: 68.65 | CB15: 66.5125 | CC15: 64.35 | CD15: 68.475 | CE15: 64.933333 | CF15: 55.38 | CG15: 60.045 | CH15: 57.7 | CI15: 55.5 | CJ15: 54.34 | CK15: 53.25 | CL15: 51.875 | CM15: 49.65 | CN15: 49.125 | CO15: 48.56 | CP15: 51.016667 | CQ15: 45 | CR15: 43.0125 | CS15: 41.375 | CT15: 43.8375 | CU15: 44 | CV15: 44.3875 | CW15: 46.775 | CX15: 54.23 | CY15: 57.85 | CZ15: 60.95 | DA15: 78.875 | DB15: 86.6875 | DC15: 89.8 | DD15: 83.75 | DE15: 79.5 | DF15: 68.5 | DG15: 67.95 | DH15: 67.95 | DI15: 73.98 | DJ15: 78.75 | DK15: 79.1875 | DL15: 82.74 | DM15: 84.0625 | DN15: 83.775 | DO15: 83.9 | DP15: 86.375 | DQ15: 81.5 | DR15: 75.8 | DS15: 77.9 | DT15: 83.4375 | DU15: 89.7 | DV15: 93.4375 | DW15: 90.1 | DX15: 91.25 | DY15: 93.3125 | DZ15: 84.3 | EA15: 81.75 | EB15: 79.375 | EC15: 73.25 | ED15: 67.68 | EE15: 55.916667 | EF15: 54.1 | EG15: 47.4 | EH15: 49.875 | EI15: 45.339091 | EJ15: 51.625 | EK15: 54.625 | EL15: 54.7 | EM15: 52.9375 | EN15: 50.38 | EO15: 49.875 | EP15: 48.8125 | EQ15: 47.333333 | ER15: 44.45 | ES15: 48.4375 | ET15: 52 | EU15: 52 | EV15: 53.5 | EW15: 55.1 | EX15: 55.375 | EY15: 61.1 | EZ15: 66.75 | FA15: 68.875 | FB15: 69.625 | FC15: 67.5 | FD15: 75.375 | FE15: 97.25 | FF15: 122.1 | FG15: 138.5 | FH15: 159.5 | FI15: 215.4 | FJ15: 172 | FL15: 58.860833 | FM15: 77.608333 | FN15: 111.045 | FO15: 83.667225 | FP15: 71.771042 | FQ15: 67.119444 | FR15: 52.620139 | FS15: 57.648333 | FT15: 77.837083 | FU15: 85.738542 | FV15: 57.235271 | FW15: 51.530278 | FX15: =C15 -> 113.89773
A16: 14 | B16: Carbón Mineral (US$/MMBTU) | C16: 4.5815659 | D16: 2.0378239 | E16: 2.5437419 | F16: 1.2482638 | H16: 2.31802 | I16: -0.2801961 | J16: -0.12087734 | L16: 3.1013677 | M16: 2.7908286 | N16: 2.2779566 | O16: 2.3531778 | P16: 2.2083669 | Q16: 2.2650845 | R16: 2.2968624 | S16: 2.2928399 | T16: 2.1069992 | U16: 2.2224457 | V16: 2.197506 | W16: 2.2988737 | X16: 2.5040225 | Y16: 2.3986323 | Z16: 2.4211585 | AA16: 2.767498 | AB16: 3.1427997 | AC16: 3.2031376 | AD16: 3.26428 | AE16: 3.1677393 | AF16: 3.1653258 | AG16: 3.3970233 | AH16: 3.6657281 | AI16: 4.3644409 | AJ16: 4.621078 | AK16: 4.4702333 | AL16: 4.6661303 | AM16: 4.7988737 | AN16: 4.6057924 | AO16: 4.5776348 | AP16: 4.5989541 | AQ16: 4.6259051 | AR16: 4.4916533 | AS16: 4.1432019 | AT16: 4.0677796 | AU16: 3.9345334 | AV16: 3.85358 | AW16: 3.6370354 | AX16: 3.5518906 | AY16: 3.539823 | AZ16: 3.195897 | BA16: 3.1564763 | BB16: 3.253218 | BC16: 3.4420756 | BD16: 3.2507039 | BE16: 3.0998592 | BF16: 3.1556718 | BG16: 3.2502011 | BH16: 3.1425986 | BI16: 3.2300885 | BJ16: 3.1488335 | BK16: 3.0028158 | BL16: 2.9376508 | BM16: 2.6734714 | BN16: 2.6422969 | BO16: 2.6761866 | BP16: 2.6362631 | BQ16: 2.7835881 | BR16: 2.9344328 | BS16: 2.8358809 | BT16: 2.9239743 | BU16: 2.7891191 | BV16: 2.609111 | BW16: 2.7368262 | BX16: 2.7316975 | BY16: 2.5613435 | BZ16: 2.6548673 | CA16: 2.7614642 | CB16: 2.6754827 | CC16: 2.5884956 | CD16: 2.7544248 | CE16: 2.6119603 | CF16: 2.227675 | CG16: 2.4153258 | CH16: 2.3209976 | CI16: 2.232502 | CJ16: 2.1858407 | CK16: 2.1419952 | CL16: 2.0866854 | CM16: 1.9971842 | CN16: 1.976066 | CO16: 1.9533387 | CP16: 2.0521588 | CQ16: 1.8101368 | CR16: 1.7301891 | CS16: 1.6643202 | CT16: 1.7633749 | CU16: 1.7699115 | CV16: 1.7854988 | CW16: 1.8815366 | CX16: 2.1814159 | CY16: 2.3270314 | CZ16: 2.4517297 | DA16: 3.1727675 | DB16: 3.4870274 | DC16: 3.6122285 | DD16: 3.3688656 | DE16: 3.1979083 | DF16: 2.7554304 | DG16: 2.7333065 | DH16: 2.7333065 | DI16: 2.9758648 | DJ16: 3.1677393 | DK16: 3.1853379 | DL16: 3.3282381 | DM16: 3.381436 | DN16: 3.3698713 | DO16: 3.3748994 | DP16: 3.474457 | DQ16: 3.2783588 | DR16: 3.0490748 | DS16: 3.1335479 | DT16: 3.3562953 | DU16: 3.608206 | DV16: 3.7585479 | DW16: 3.6242961 | DX16: 3.6705551 | DY16: 3.7535197 | DZ16: 3.3909895 | EA16: 3.2884151 | EB16: 3.1928801 | EC16: 2.9465004 | ED16: 2.7224457 | EE16: 2.2492625 | EF16: 2.1761866 | EG16: 1.9066774 | EH16: 2.0062349 | EI16: 1.8237768 | EJ16: 2.0766291 | EK16: 2.1973049 | EL16: 2.2003218 | EM16: 2.1294248 | EN16: 2.0265487 | EO16: 2.0062349 | EP16: 1.9634956 | EQ16: 1.9039957 | ER16: 1.7880129 | ES16: 1.9484111 | ET16: 2.0917136 | EU16: 2.0917136 | EV16: 2.1520515 | EW16: 2.2164119 | EX16: 2.2274739 | EY16: 2.4577635 | EZ16: 2.6850362 | FA16: 2.7705149 | FB16: 2.8006838 | FC16: 2.7152051 | FD16: 3.0319791 | FE16: 3.9119067 | FF16: 4.9115044 | FG16: 5.5711987 | FH16: 6.4159292 | FI16: 8.6645213 | FJ16: 6.918745 | FL16: 2.3676924 | FM16: 3.1218155 | FN16: 4.4668142 | FO16: 3.365536 | FP16: 2.8870089 | FQ16: 2.6998972 | FR16: 2.1166588 | FS16: 2.3189193 | FT16: 3.131017 | FU16: 3.4488553 | FV16: 2.3023038 | FW16: 2.0728189 | FX16: =C16 -> 4.5815659
B18: Generación de Energía por tipo de combustible
B19: Total Generación | C19: 17813.07 | D19: 16211.883 | E19: 1601.1876 | F19: 0.098766294 | H19: 15946.877 | I19: 265.00545 | J19: 0.016618015 | L19: 922.04842 | M19: 818.5513 | N19: 898.69257 | O19: 917.18353 | P19: 943.30873 | Q19: 982.41699 | R19: 1045.7514 | S19: 1040.5285 | T19: 1014.8929 | U19: 1064.5995 | V19: 973.9716 | W19: 1023.1697 | X19: 948.15589 | Y19: 891.79764 | Z19: 1021.3541 | AA19: 1013.6284 | AB19: 1084.5643 | AC19: 1042.3687 | AD19: 1084.7864 | AE19: 1117.3577 | AF19: 1049.5927 | AG19: 1081.8468 | AH19: 966.62602 | AI19: 969.55713 | AJ19: 963.30584 | AK19: 890.38935 | AL19: 998.47666 | AM19: 1002.0157 | AN19: 1060.2304 | AO19: 1070.0921 | AP19: 1094.807 | AQ19: 1115.2692 | AR19: 1093.6813 | AS19: 1127.1931 | AT19: 1046.0148 | AU19: 1016.834 | AV19: 980.675 | AW19: 948 | AX19: 1019.83 | AY19: 1030.543 | AZ19: 1181.68 | BA19: 1175.746 | BB19: 1211.903 | BC19: 1181.76 | BD19: 1175.886 | BE19: 1202.848 | BF19: 1146.739 | BG19: 1100.28 | BH19: 918.96586 | BI19: 814.9526 | BJ19: 911.30384 | BK19: 953.37083 | BL19: 1073.7916 | BM19: 981.71516 | BN19: 1150.5949 | BO19: 1188.1823 | BP19: 1133.8477 | BQ19: 1084.3878 | BR19: 995.92368 | BS19: 900.38185 | BT19: 1038.6562 | BU19: 950.3367 | BV19: 1099.9252 | BW19: 1090.918 | BX19: 1135.3995 | BY19: 1150.3523 | BZ19: 1216.798 | CA19: 1200.9025 | CB19: 1142.8577 | CC19: 1218.5596 | CD19: 1115.9196 | CE19: 1103.2836 | CF19: 1088.2508 | CG19: 996.01054 | CH19: 1133.9448 | CI19: 1136.6634 | CJ19: 1201.1855 | CK19: 1214.9412 | CL19: 1276.3813 | CM19: 1276.2716 | CN19: 1242.271 | CO19: 1286.8876 | CP19: 1148.8956 | CQ19: 1175.6812 | CR19: 1124.733 | CS19: 1089.2607 | CT19: 1196 | CU19: 1218.353 | CV19: 1313.6868 | CW19: 1271.6447 | CX19: 1344.0761 | CY19: 1337.6032 | CZ19: 1301.8436 | DA19: 1286.9115 | DB19: 1192.4198 | DC19: 1222.9171 | DD19: 1166.8597 | DE19: 1084.8635 | DF19: 1218.2465 | DG19: 1200.4853 | DH19: 1318.045 | DI19: 1306.7353 | DJ19: 1359.1451 | DK19: 1403.6907 | DL19: 1312.6597 | DM19: 1396.0976 | DN19: 1258.5423 | DO19: 1257.0779 | DP19: 1204.6836 | DQ19: 1069.0964 | DR19: 1246.691 | DS19: 1283.513 | DT19: 1335.0744 | DU19: 1360.984 | DV19: 1428.548 | DW19: 1419.2095 | DX19: 1331.2559 | DY19: 1360.2069 | DZ19: 1331.1317 | EA19: 1331.2889 | EB19: 1302.4387 | EC19: 1220.268 | ED19: 1372.7351 | EE19: 1373.6511 | EF19: 1492.2832 | EG19: 1482.4467 | EH19: 1577.4577 | EI19: 1584.2529 | EJ19: 1521.606 | EK19: 1564.2869 | EL19: 1455.451 | EM19: 1464.6197 | EN19: 1405.4504 | EO19: 1347.4261 | EP19: 1316.6857 | EQ19: 1293.3879 | ER19: 1446.7289 | ES19: 1558.1795 | ET19: 1619.0817 | EU19: 1602.3002 | EV19: 1571.5381 | EW19: 1607.3049 | EX19: 1443.7993 | EY19: 1451.372 | EZ19: 1398.4578 | FA19: 1365.4169 | FB19: 1542.4843 | FC19: 1539.2145 | FD19: 1667.1297 | FE19: 1627.7822 | FF19: 1736.1979 | FG19: 1728.9816 | FH19: 1764.7737 | FI19: 1764.2522 | FJ19: 1678.3796 | FL19: 11645.115 | FM19: 12271.636 | FN19: 12478.309 | FO19: 13355.89 | FP19: 12107.418 | FQ19: 13463.909 | FR19: 14177.385 | FS19: 14899.449 | FT19: 15282.449 | FU19: 15701.683 | FV19: 17411.497 | FW19: 17663.255 | FX19: =C19 -> 17813.07
B20: Carbón Mineral | C20: 5573.407 | D20: 6011.0596 | E20: -437.65264 | F20: -0.072807903 | H20: 3147.7599 | I20: 2863.2997 | J20: 0.90963091 | L20: 180.73189 | M20: 114.72025 | N20: 126.3082 | O20: 139.8629 | P20: 161.86797 | Q20: 136.65605 | R20: 168.8417 | S20: 159.2608 | T20: 172.1727 | U20: 188.2451 | V20: 184.9449 | W20: 193.7253 | X20: 181.0222 | Y20: 136.3036 | Z20: 195.1545 | AA20: 173.8431 | AB20: 178.3092 | AC20: 155.9941 | AD20: 96.33377 | AE20: 95.54638 | AF20: 129.1356 | AG20: 163.3322 | AH20: 169.0025 | AI20: 180.5036 | AJ20: 173.69175 | AK20: 141.27538 | AL20: 179.45588 | AM20: 166.36899 | AN20: 175.63835 | AO20: 158.47094 | AP20: 99.084291 | AQ20: 118.15267 | AR20: 169.1168 | AS20: 104.10654 | AT20: 179.25153 | AU20: 177.90639 | AV20: 193.341 | AW20: 167.277 | AX20: 166.029 | AY20: 155.405 | AZ20: 185.259 | BA20: 133.246 | BB20: 164.371 | BC20: 168.319 | BD20: 185.1 | BE20: 172.049 | BF20: 135.791 | BG20: 101.642 | BH20: 26.927598 | BI20: 25.473518 | BJ20: 28.649248 | BK20: 27.715653 | BL20: 29.287192 | BM20: 27.076533 | BN20: 189.90356 | BO20: 194.64735 | BP20: 160.94923 | BQ20: 176.45955 | BR20: 192.1552 | BS20: 111.24065 | BT20: 197.82194 | BU20: 124.96989 | BV20: 191.04104 | BW20: 153.52174 | BX20: 199.35918 | BY20: 193.93111 | BZ20: 195.70767 | CA20: 192.01894 | CB20: 180.54749 | CC20: 183.45777 | CD20: 185.42385 | CE20: 203.26735 | CF20: 198.80768 | CG20: 143.30717 | CH20: 153.22181 | CI20: 146.96281 | CJ20: 166.35303 | CK20: 169.03868 | CL20: 189.53084 | CM20: 184.48432 | CN20: 189.38363 | CO20: 191.65864 | CP20: 175.16277 | CQ20: 191.72707 | CR20: 200.53224 | CS20: 168.42402 | CT20: 127.2897 | CU20: 138.85773 | CV20: 175.44089 | CW20: 195.96862 | CX20: 192.52377 | CY20: 192.01358 | CZ20: 177.47579 | DA20: 199.23246 | DB20: 183.85229 | DC20: 189.02996 | DD20: 197.3957 | DE20: 117.34558 | DF20: 151.07638 | DG20: 165.51834 | DH20: 146.07355 | DI20: 183.23751 | DJ20: 192.99292 | DK20: 198.8427 | DL20: 193.03355 | DM20: 195.47929 | DN20: 170.59646 | DO20: 206.01394 | DP20: 195.89696 | DQ20: 173.03221 | DR20: 188.74981 | DS20: 181.02473 | DT20: 105.98117 | DU20: 124.45685 | DV20: 135.18714 | DW20: 180.33436 | DX20: 161.42698 | DY20: 194.61203 | DZ20: 190.54242 | EA20: 203.18825 | EB20: 199.46885 | EC20: 183.53188 | ED20: 176.76904 | EE20: 280.20021 | EF20: 295.39771 | EG20: 191.81828 | EH20: 339.78835 | EI20: 308.73641 | EJ20: 358.20952 | EK20: 420.86132 | EL20: 392.97833 | EM20: 476.09807 | EN20: 464.14452 | EO20: 485.29229 | EP20: 427.41664 | EQ20: 419.40655 | ER20: 640.9533 | ES20: 598.52948 | ET20: 654.73319 | EU20: 582.23064 | EV20: 629.06089 | EW20: 589.29095 | EX20: 520.00114 | EY20: 539.56558 | EZ20: 341.39298 | FA20: 295.90849 | FB20: 421.23452 | FC20: 509.15782 | FD20: 552.69216 | FE20: 556.25901 | FF20: 627.01397 | FG20: 588.47984 | FH20: 533.35606 | FI20: 619.75474 | FJ20: 528.15738 | FL20: 1927.3378 | FM20: 1854.4808 | FN20: 1842.5195 | FO20: 1927.829 | FP20: 1190.4853 | FQ20: 2201.068 | FR20: 2099.6384 | FS20: 2140.6411 | FT20: 2117.6059 | FU20: 2034.4329 | FV20: 3623.858 | FW20: 6550.6252 | FX20: =C20 -> 5573.407
B21: Gas Natural | C21: 7179.0384 | D21: 4676.7396 | E21: 2502.2988 | F21: 0.53505198 | H21: 4703.9527 | I21: -27.213084 | J21: -0.0057851525 | L21: 144.6669 | M21: 160.5582 | N21: 199.4615 | O21: 158.81113 | P21: 83.6026 | Q21: 206.98518 | R21: 212.6697 | S21: 232.42 | T21: 187.147 | U21: 217.4535 | V21: 199.6551 | W21: 225.656 | X21: 229.8596 | Y21: 237.0705 | Z21: 257.5413 | AA21: 283.7555 | AB21: 290.6041 | AC21: 246.2251 | AD21: 307.152 | AE21: 323.4835 | AF21: 288.944 | AG21: 319.2311 | AH21: 276.1185 | AI21: 283.3471 | AJ21: 345.39022 | AK21: 319.41372 | AL21: 260.5236 | AM21: 319.94904 | AN21: 312.11014 | AO21: 311.88686 | AP21: 353.80397 | AQ21: 333.91837 | AR21: 335.94337 | AS21: 353.65726 | AT21: 328.49034 | AU21: 329.00359 | AV21: 243.644 | AW21: 292.044 | AX21: 366.721 | AY21: 378.011 | AZ21: 420.798 | BA21: 409.969 | BB21: 396.513 | BC21: 423.473 | BD21: 421.208 | BE21: 418.412 | BF21: 417.075 | BG21: 440.053 | BH21: 276.96145 | BI21: 259.79393 | BJ21: 308.04544 | BK21: 354.23314 | BL21: 366.53013 | BM21: 335.99136 | BN21: 354.04918 | BO21: 324.95544 | BP21: 351.48273 | BQ21: 337.13847 | BR21: 279.86575 | BS21: 319.15781 | BT21: 369.22379 | BU21: 344.75892 | BV21: 414.86759 | BW21: 399.54863 | BX21: 393.38648 | BY21: 392.41552 | BZ21: 411.94705 | CA21: 409.3575 | CB21: 369.27979 | CC21: 391.30146 | CD21: 335.16256 | CE21: 365.98092 | CF21: 275.68358 | CG21: 191.06041 | CH21: 395.75322 | CI21: 396.31356 | CJ21: 386.51887 | CK21: 375.42223 | CL21: 391.19833 | CM21: 397.50918 | CN21: 374.68346 | CO21: 382.63516 | CP21: 387.63287 | CQ21: 422.68669 | CR21: 402.81022 | CS21: 328.08913 | CT21: 391.57077 | CU21: 414.42021 | CV21: 368.65667 | CW21: 337.20255 | CX21: 350.77204 | CY21: 373.64135 | CZ21: 363.51108 | DA21: 414.61844 | DB21: 388.98946 | DC21: 417.42149 | DD21: 267.03798 | DE21: 322.03828 | DF21: 370.33686 | DG21: 411.43175 | DH21: 460.58904 | DI21: 477.07466 | DJ21: 451.07465 | DK21: 528.04727 | DL21: 494.8645 | DM21: 526.5389 | DN21: 510.22875 | DO21: 520.92794 | DP21: 443.51702 | DQ21: 411.34766 | DR21: 410.90119 | DS21: 506.18152 | DT21: 520.55157 | DU21: 505.64908 | DV21: 518.69983 | DW21: 521.36768 | DX21: 324.86167 | DY21: 396.43984 | DZ21: 380.51423 | EA21: 403.76447 | EB21: 440.12589 | EC21: 351.64779 | ED21: 397.52649 | EE21: 338.11532 | EF21: 436.53967 | EG21: 452.2979 | EH21: 467.00366 | EI21: 494.84065 | EJ21: 388.21938 | EK21: 448.76015 | EL21: 488.87578 | EM21: 508.75982 | EN21: 478.13762 | EO21: 323.75213 | EP21: 350.10375 | EQ21: 351.53817 | ER21: 340.38609 | ES21: 360.88514 | ET21: 311.12601 | EU21: 532.41214 | EV21: 439.42093 | EW21: 606.02555 | EX21: 582.95206 | EY21: 622.29549 | EZ21: 628.06763 | FA21: 653.75473 | FB21: 695.1036 | FC21: 621.25565 | FD21: 684.06261 | FE21: 587.38463 | FF21: 622.71536 | FG21: 580.0734 | FH21: 705.69527 | FI21: 690.57803 | FJ21: 710.34747 | FL21: 2229.0868 | FM21: 3343.3323 | FN21: 3904.0905 | FO21: 4627.921 | FP21: 3868.2048 | FQ21: 4597.2302 | FR21: 4377.0976 | FS21: 4551.7034 | FT21: 5340.1906 | FU21: 5343.7958 | FV21: 5212.7125 | FW21: 5299.0351 | FX21: =C21 -> 7179.0384
B22: Fuel Oil No. 2 | C22: 36.727325 | D22: 144.96403 | E22: -108.2367 | F22: -0.74664525 | H22: 1105.1427 | I22: -960.17869 | J22: -0.86882777 | L22: 32.56563 | M22: 31.4068 | N22: 45.00641 | O22: 77.58731 | P22: 105.38252 | Q22: 73.999 | R22: 90.36366 | S22: 102.56099 | T22: 76.0039 | U22: 59.0232 | V22: 61.4323 | W22: 44.4491 | X22: 0.8075 | Y22: 0.6574 | Z22: 54.0537 | AA22: 46.8456 | AB22: 40.2445 | AC22: 29.4926 | AD22: 25.3445 | AE22: 28.2142 | AF22: 11.6574 | AG22: 3.7237 | AH22: 8.2578 | AI22: 10.9999 | AJ22: 17.834612 | AK22: 6.8083313 | AL22: 70.757402 | AM22: 54.928247 | AN22: 95.014113 | AO22: 70.089367 | AP22: 99.770045 | AQ22: 126.4215 | AR22: 82.648066 | AS22: 101.70014 | AT22: 58.972407 | AU22: 54.517903 | AV22: 95.994 | AW22: 61.835 | AX22: 46.946 | AY22: 49.154 | AZ22: 38.88 | BA22: 98.727 | BB22: 72.706 | BC22: 53.404 | BD22: 33.06 | BE22: 46.789 | BF22: 96.001 | BG22: 86.569 | BH22: 69.098393 | BI22: 51.786869 | BJ22: 39.980739 | BK22: 61.037643 | BL22: 98.821346 | BM22: 25.319085 | BN22: 14.71397 | BO22: 64.820541 | BP22: 48.369278 | BQ22: 10.709336 | BR22: 2.6964508 | BS22: 0.94560826 | BT22: 1.450941 | BU22: 12.362486 | BV22: 0.26298027 | BW22: 2.5164767 | BX22: 0.52124392 | BY22: 6.3247172 | BZ22: 23.850555 | CA22: 8.2042075 | CB22: 19.463012 | CC22: 16.855069 | CD22: 64.379245 | CE22: 10.681114 | CF22: 66.613439 | CG22: 125.60676 | CH22: 25.610016 | CI22: 42.263635 | CJ22: 97.338052 | CK22: 119.72252 | CL22: 118.36721 | CM22: 130.29496 | CN22: 133.30949 | CO22: 155.86831 | CP22: 76.252134 | CQ22: 47.607449 | CR22: 31.930188 | CS22: 92.568718 | CT22: 128.33317 | CU22: 120.62496 | CV22: 122.44918 | CW22: 114.00655 | CX22: 148.24334 | CY22: 146.84397 | CZ22: 129.79001 | DA22: 98.412729 | DB22: 32.017979 | DC22: 20.096722 | DD22: 25.920413 | DE22: 53.494506 | DF22: 55.58266 | DG22: 35.74106 | DH22: 17.184703 | DI22: 34.504817 | DJ22: 71.864085 | DK22: 53.418593 | DL22: 50.359962 | DM22: 60.530697 | DN22: 59.198726 | DO22: 1.7496273 | DP22: 22.719474 | DQ22: 0 | DR22: 46.305846 | DS22: 14.850049 | DT22: 54.277172 | DU22: 80.290643 | DV22: 106.26964 | DW22: 94.593983 | DX22: 154.09552 | DY22: 92.141328 | DZ22: 112.88657 | EA22: 86.307907 | EB22: 40.358736 | EC22: 87.636615 | ED22: 157.64367 | EE22: 119.26297 | EF22: 106.46999 | EG22: 106.30003 | EH22: 95.522076 | EI22: 84.834864 | EJ22: 153.93338 | EK22: 101.56017 | EL22: 51.620208 | EM22: 16.401874 | EN22: 8.4128991 | EO22: 20.018546 | EP22: 14.198453 | EQ22: 0.80405177 | ER22: 2.3181938 | ES22: 24.750912 | ET22: 56.770186 | EU22: 2.6962518 | EV22: 12.94265 | EW22: 1.3812055 | EX22: 0.67068113 | EY22: 0 | EZ22: 1.6206006 | FA22: 2.2481987 | FB22: 1.3343845 | FC22: 0 | FD22: 1.9054344 | FE22: 4.2073443 | FF22: 0.41693007 | FG22: 6.4790696 | FH22: 11.834727 | FI22: 0 | FJ22: 6.680636 | FL22: 799.78082 | FM22: 260.2988 | FN22: 839.46214 | FO22: 780.065 | FP22: 488.29926 | FQ22: 166.87205 | FR22: 1138.854 | FS22: 1185.3175 | FT22: 519.54985 | FU22: 864.73813 | FV22: 1121.5446 | FW22: 144.96403 | FX22: =C22 -> 36.727325
A23: 8 | B23: Fuel Oil No. 6 | C23: 1936.8033 | D23: 2748.304 | E23: -811.50068 | F23: -0.29527326 | H23: 4942.4406 | I23: -2194.1366 | J23: -0.44393787 | L23: 350.78359 | M23: 323.88028 | N23: 362.65062 | O23: 374.76572 | P23: 352.1515 | Q23: 341.73773 | R23: 353.40061 | S23: 343.9081 | T23: 413.05171 | U23: 429.94554 | V23: 411.56689 | W23: 379.67117 | X23: 363.74345 | Y23: 399.5711 | Z23: 410.69853 | AA23: 367.71556 | AB23: 388.8752 | AC23: 386.80594 | AD23: 379.64433 | AE23: 400.93661 | AF23: 403.33062 | AG23: 395.04206 | AH23: 333.20859 | AI23: 353.05326 | AJ23: 303.49867 | AK23: 265.22296 | AL23: 310.70943 | AM23: 308.57337 | AN23: 301.56957 | AO23: 298.63427 | AP23: 299.61291 | AQ23: 294.88911 | AR23: 271.16827 | AS23: 302.95638 | AT23: 254.18468 | AU23: 255.18441 | AV23: 344.212 | AW23: 322.851 | AX23: 325.654 | AY23: 282.18 | AZ23: 309.958 | BA23: 384.888 | BB23: 438.638 | BC23: 385.205 | BD23: 373.813 | BE23: 396.312 | BF23: 303.595 | BG23: 287.054 | BH23: 310.82061 | BI23: 302.92979 | BJ23: 336.94588 | BK23: 335.48859 | BL23: 363.84667 | BM23: 317.61157 | BN23: 321.3435 | BO23: 337.03599 | BP23: 359.42483 | BQ23: 392.49383 | BR23: 367.25154 | BS23: 292.54341 | BT23: 278.15223 | BU23: 292.37712 | BV23: 335.0994 | BW23: 385.52346 | BX23: 392.47756 | BY23: 425.58038 | BZ23: 460.92713 | CA23: 425.72665 | CB23: 413.72851 | CC23: 464.65458 | CD23: 429.75017 | CE23: 410.04205 | CF23: 451.96223 | CG23: 437.3327 | CH23: 441.55313 | CI23: 445.25532 | CJ23: 455.07104 | CK23: 444.42504 | CL23: 481.80263 | CM23: 484.22615 | CN23: 451.80125 | CO23: 466.08447 | CP23: 397.6536 | CQ23: 386.50684 | CR23: 392.42822 | CS23: 416.76768 | CT23: 450.4208 | CU23: 463.27923 | CV23: 431.78022 | CW23: 418.46669 | CX23: 489.34877 | CY23: 425.3752 | CZ23: 445.10568 | DA23: 386.17858 | DB23: 318.44668 | DC23: 322.45613 | DD23: 386.84401 | DE23: 370.56154 | DF23: 386.2109 | DG23: 335.94046 | DH23: 348.72008 | DI23: 384.64831 | DJ23: 409.31223 | DK23: 396.09492 | DL23: 327.4078 | DM23: 357.38169 | DN23: 309.33473 | DO23: 331.65987 | DP23: 303.93967 | DQ23: 178.75508 | DR23: 383.07798 | DS23: 365.77175 | DT23: 396.03797 | DU23: 447.47332 | DV23: 458.596 | DW23: 439.55966 | DX23: 495.40542 | DY23: 464.69064 | DZ23: 475.66392 | EA23: 440.99517 | EB23: 440.12665 | EC23: 432.65736 | ED23: 485.29601 | EE23: 465.78942 | EF23: 491.88904 | EG23: 499.97522 | EH23: 446.04783 | EI23: 464.75177 | EJ23: 426.84401 | EK23: 395.68583 | EL23: 393.37743 | EM23: 274.64937 | EN23: 209.19729 | EO23: 271.90376 | EP23: 253.07552 | EQ23: 307.47065 | ER23: 249.70765 | ES23: 334.92533 | ET23: 344.95673 | EU23: 242.12378 | EV23: 285.95504 | EW23: 154.71055 | EX23: 94.27769 | EY23: 63.810874 | EZ23: 190.33825 | FA23: 135.33866 | FB23: 129.04635 | FC23: 137.49087 | FD23: 136.79926 | FE23: 145.684 | FF23: 149.1743 | FG23: 210.3626 | FH23: 280.60627 | FI23: 208.98488 | FJ23: 212.97789 | FL23: 4437.5135 | FM23: 4582.6253 | FN23: 3466.204 | FO23: 4154.36 | FP23: 4037.7362 | FQ23: 4714.0392 | FR23: 5343.6744 | FS23: 4960.0539 | FT23: 4344.1165 | FU23: 4849.9666 | FV23: 5217.0899 | FW23: 2812.1149 | FX23: =C23 -> 1936.8033
A24: 2 | B24: Fuel Oil No. 2 y No. 6 | C24: 0 | D24: 0 | E24: 0 | F24: 0 | H24: 56.126183 | I24: -56.126183 | J24: -1 | L24: 83.0682 | M24: 50.0019 | N24: 49.1954 | O24: 49.8913 | P24: 68.6832 | Q24: 69.8186 | R24: 109.82223 | S24: 68.4282 | T24: 45.4605 | U24: 63.1767 | V24: 33.2797 | W24: 94.6292 | X24: 95.3245 | Y24: 62.544 | Z24: 51.028 | AA24: 70.643 | AB24: 91.4553 | AC24: 58.97048 | AD24: 102.41889 | AE24: 90.25118 | AF24: 92.5349 | AG24: 59.95863 | AH24: 10.4828 | AI24: 10.83424 | AJ24: 9.306468 | AK24: 68.804286 | AL24: 86.246476 | AM24: 78.170953 | AN24: 87.067728 | AO24: 77.597756 | AP24: 102.56818 | AQ24: 61.454001 | AR24: 70.907333 | AS24: 90.682832 | AT24: 85.066742 | AU24: 90.030096 | AV24: 0 | AW24: 0 | AX24: 0 | AY24: 0 | AZ24: 0 | BA24: 0 | BB24: 0 | BC24: 0 | BD24: 0 | BE24: 0 | BF24: 0 | BG24: 0 | BH24: 74.351966 | BI24: 40.003578 | BJ24: 76.374457 | BK24: 41.470119 | BL24: 39.576238 | BM24: 60.131153 | BN24: 49.890335 | BO24: 90.079164 | BP24: 43.844671 | BQ24: 0 | BR24: 0 | BS24: 3.3692434 | BT24: 21.241662 | BU24: 33.3214 | BV24: 25.972376 | BW24: 19.560898 | BX24: 3.1278106 | BY24: 0.99255569 | BZ24: 10.415251 | CA24: 52.756947 | CB24: 51.879535 | CC24: 66.283731 | CD24: 1.1990312 | CE24: 0 | CF24: 0 | CG24: 0 | CH24: 0 | CI24: 0 | CJ24: 0 | CK24: 0 | CL24: 0 | CM24: 0 | CN24: 0 | CO24: 0 | CP24: 0 | CQ24: 0 | CR24: 0 | CS24: 0 | CT24: 0 | CU24: 0 | CV24: 77.776426 | CW24: 35.66647 | CX24: 1.0340738 | CY24: 42.01041 | CZ24: 46.970788 | DA24: 16.911882 | DB24: 1.5018001 | DC24: 0 | DD24: 54.624969 | DE24: 55.170757 | DF24: 27.332137 | DG24: 3.6569148 | DH24: 8.7981806 | DI24: 17.007704 | DJ24: 9.1079808 | DK24: 4.9741239 | DL24: 9.0762404 | DM24: 8.0394426 | DN24: 10.897722 | DO24: 14.253539 | DP24: 0.71712712 | DQ24: 0 | DR24: 0.51210141 | DS24: 0 | DT24: 12.889012 | DU24: 9.2612037 | DV24: 9.6877081 | DW24: 3.4857809 | DX24: 23.260324 | DY24: 11.752284 | DZ24: 7.3505261 | EA24: 4.0603683 | EB24: 0 | EC24: 0 | ED24: 0 | EE24: 0 | EF24: 0 | EG24: 0 | EH24: 0 | EI24: 19.7984 | EJ24: 28.794464 | EK24: 6.817097 | EL24: 0.71622178 | EM24: 0 | EN24: 0 | EO24: 0 | EP24: 0 | EQ24: 0 | ER24: 0 | ES24: 0 | ET24: 0 | EU24: 0 | EV24: 0 | EW24: 0 | EX24: 0 | EY24: 0 | EZ24: 0 | FA24: 0 | FB24: 0 | FC24: 0 | FD24: 0 | FE24: 0 | FF24: 0 | FG24: 0 | FH24: 0 | FI24: 0 | FJ24: 0 | FL24: 785.45513 | FM24: 796.44592 | FN24: 907.90285 | FO24: 0 | FP24: 519.09093 | FQ24: 286.7512 | FR24: 0 | FS24: 221.87185 | FT24: 222.93971 | FU24: 82.976435 | FV24: 56.126183 | FW24: 0 | FX24: =C24 -> 0
A25: 3 | B25: Hidráulica | C25: 1360.9457 | D25: 1131.3957 | E25: 229.54996 | F25: 0.20289096 | H25: 951.38075 | I25: 180.01496 | J25: 0.18921442 | L25: 130.23221 | M25: 137.98387 | N25: 116.07044 | O25: 116.26517 | P25: 171.62094 | Q25: 153.22043 | R25: 110.65353 | S25: 133.95041 | T25: 121.05712 | U25: 106.75549 | V25: 83.09271 | W25: 85.03893 | X25: 77.39864 | Y25: 55.65104 | Z25: 52.87805 | AA25: 70.82568 | AB25: 95.07596 | AC25: 164.88049 | AD25: 173.8929 | AE25: 178.92579 | AF25: 123.99023 | AG25: 140.55911 | AH25: 169.55583 | AI25: 130.81903 | AJ25: 113.58413 | AK25: 88.86467 | AL25: 90.783889 | AM25: 74.025069 | AN25: 88.830467 | AO25: 153.4129 | AP25: 139.96757 | AQ25: 180.43355 | AR25: 163.602 | AS25: 170.6778 | AT25: 137.12559 | AU25: 103.07729 | AV25: 94.589 | AW25: 96.259 | AX25: 103.254 | AY25: 159.661 | AZ25: 218.773 | BA25: 140.244 | BB25: 127.082 | BC25: 142.113 | BD25: 158.866 | BE25: 165.587 | BF25: 191.521 | BG25: 173.632 | BH25: 134.0028 | BI25: 116.82077 | BJ25: 106.69588 | BK25: 110.8429 | BL25: 156.42082 | BM25: 188.37387 | BN25: 195.7858 | BO25: 152.54863 | BP25: 160.96753 | BQ25: 157.42438 | BR25: 140.93053 | BS25: 144.20138 | BT25: 141.6006 | BU25: 120.66734 | BV25: 117.3149 | BW25: 108.37085 | BX25: 127.36011 | BY25: 108.44908 | BZ25: 87.912204 | CA25: 91.594893 | CB25: 90.423149 | CC25: 89.405636 | CD25: 83.529873 | CE25: 92.542198 | CF25: 74.691174 | CG25: 80.648703 | CH25: 89.910697 | CI25: 81.945284 | CJ25: 68.794167 | CK25: 76.685451 | CL25: 64.150156 | CM25: 56.118765 | CN25: 79.870163 | CO25: 80.107912 | CP25: 89.928052 | CQ25: 91.583602 | CR25: 83.921165 | CS25: 71.554544 | CT25: 74.51204 | CU25: 70.894115 | CV25: 114.33526 | CW25: 134.23568 | CX25: 106.67368 | CY25: 111.18645 | CZ25: 106.15618 | DA25: 154.38719 | DB25: 250.63329 | DC25: 225.33145 | DD25: 200.95106 | DE25: 138.42852 | DF25: 181.76724 | DG25: 196.31608 | DH25: 280.08923 | DI25: 143.96606 | DJ25: 168.54435 | DK25: 162.5926 | DL25: 202.99936 | DM25: 201.77986 | DN25: 171.11175 | DO25: 127.28276 | DP25: 174.98016 | DQ25: 232.53817 | DR25: 166.8644 | DS25: 164.42573 | DT25: 178.23922 | DU25: 131.51928 | DV25: 128.6618 | DW25: 107.90352 | DX25: 108.98038 | DY25: 151.11585 | DZ25: 117.40662 | EA25: 98.661815 | EB25: 100.4857 | EC25: 80.776559 | ED25: 75.718697 | EE25: 68.585453 | EF25: 72.08614 | EG25: 103.1428 | EH25: 90.469519 | EI25: 89.648297 | EJ25: 94.367416 | EK25: 105.20085 | EL25: 70.899323 | EM25: 73.726707 | EN25: 102.53122 | EO25: 88.945251 | EP25: 136.07831 | EQ25: 93.249553 | ER25: 88.270199 | ES25: 86.964837 | ET25: 89.815669 | EU25: 105.96167 | EV25: 103.24492 | EW25: 111.4205 | EX25: 124.91358 | EY25: 113.24503 | EZ25: 107.8539 | FA25: 98.398546 | FB25: 132.37785 | FC25: 126.59792 | FD25: 121.46901 | FE25: 150.54212 | FF25: 134.81536 | FG25: 157.28518 | FH25: 105.40834 | FI25: 125.39299 | FJ25: 100.80446 | FL25: 1465.9413 | FM25: 1434.4527 | FN25: 1504.3849 | FO25: 1771.581 | FP25: 1765.0153 | FQ25: 1259.1708 | FR25: 934.43413 | FS25: 1503.821 | FT25: 2175.8289 | FU25: 1761.297 | FV25: 1025.1075 | FW25: 1244.6407 | FX25: =C25 -> 1360.9457
A26: 4 | B26: Eòlica | C26: 1102.2548 | D26: 1068.7121 | E26: 33.542628 | F26: 0.031386027 | H26: 709.51264 | I26: 359.19951 | J26: 0.50626232 | L26: 0 | M26: 0 | N26: 0 | O26: 0 | P26: 0 | Q26: 0 | R26: 0 | S26: 0 | T26: 0 | U26: 0 | V26: 0 | W26: 0 | X26: 0 | Y26: 0 | Z26: 0 | AA26: 0 | AB26: 0 | AC26: 0 | AD26: 0 | AE26: 0 | AF26: 0 | AG26: 0 | AH26: 0 | AI26: 0 | AJ26: 0 | AK26: 0 | AL26: 0 | AM26: 0 | AN26: 0 | AO26: 0 | AP26: 0 | AQ26: 0 | AR26: 0.29546457 | AS26: 3.4121442 | AT26: 2.923479 | AU26: 7.114331 | AV26: 8.895 | AW26: 7.734 | AX26: 11.226 | AY26: 6.132 | AZ26: 8.012 | BA26: 8.672 | BB26: 12.593 | BC26: 9.246 | BD26: 3.839 | BE26: 3.699 | BF26: 2.756 | BG26: 11.33 | BH26: 26.803041 | BI26: 18.144141 | BJ26: 14.612194 | BK26: 22.582782 | BL26: 19.309188 | BM26: 27.211582 | BN26: 24.908539 | BO26: 24.095206 | BP26: 8.8094064 | BQ26: 10.16221 | BR26: 13.024204 | BS26: 28.923755 | BT26: 29.164996 | BU26: 21.879548 | BV26: 15.366891 | BW26: 21.875993 | BX26: 19.167157 | BY26: 22.658939 | BZ26: 26.038107 | CA26: 21.243358 | CB26: 17.536231 | CC26: 6.6013368 | CD26: 16.47489 | CE26: 20.769954 | CF26: 20.492698 | CG26: 18.054796 | CH26: 27.895966 | CI26: 23.922806 | CJ26: 27.11038 | CK26: 29.647274 | CL26: 31.332084 | CM26: 23.638174 | CN26: 13.223016 | CO26: 10.533108 | CP26: 22.266187 | CQ26: 35.56955 | CR26: 13.110925 | CS26: 11.856603 | CT26: 23.873474 | CU26: 10.276707 | CV26: 23.248139 | CW26: 35.209494 | CX26: 51.16454 | CY26: 43.894802 | CZ26: 28.404466 | DA26: 13.194676 | DB26: 13.658519 | DC26: 44.700189 | DD26: 29.70239 | DE26: 23.49532 | DF26: 35.729444 | DG26: 34.665914 | DH26: 37.906679 | DI26: 46.38996 | DJ26: 42.313924 | DK26: 37.905582 | DL26: 14.439804 | DM26: 23.160141 | DN26: 18.474134 | DO26: 33.721683 | DP26: 43.537386 | DQ26: 52.461899 | DR26: 26.602419 | DS26: 28.808699 | DT26: 44.34002 | DU26: 39.627595 | DV26: 48.120897 | DW26: 47.515106 | DX26: 32.36587 | DY26: 21.520419 | DZ26: 33.351196 | EA26: 62.952055 | EB26: 50.274032 | EC26: 54.755651 | ED26: 46.370656 | EE26: 68.700644 | EF26: 62.250771 | EG26: 96.270253 | EH26: 104.97026 | EI26: 88.016458 | EJ26: 39.923458 | EK26: 52.243149 | EL26: 45.737307 | EM26: 79.462324 | EN26: 98.930214 | EO26: 122.93762 | EP26: 102.80052 | EQ26: 79.151087 | ER26: 83.86773 | ES26: 111.74959 | ET26: 121.47784 | EU26: 107.97561 | EV26: 60.334241 | EW26: 98.959183 | EX26: 80.528503 | EY26: 70.41316 | EZ26: 87.373533 | FA26: 137.59281 | FB26: 112.68462 | FC26: 90.568051 | FD26: 114.72891 | FE26: 131.39207 | FF26: 141.38366 | FG26: 112.62105 | FH26: 54.247033 | FI26: 57.245839 | FJ26: 62.417195 | FL26: 0 | FM26: 0 | FN26: 13.745419 | FO26: 94.134 | FP26: 238.58625 | FQ26: 238.7774 | FR26: 283.68604 | FS26: 312.59254 | FT26: 377.90497 | FU26: 481.20356 | FV26: 788.97496 | FW26: 1139.1253 | FX26: =C26 -> 1102.2548
A27: 5 | B27: Solar Fotovoltaica | C27: 436.27951 | D27: 282.15362 | E27: 154.12589 | F27: 0.54624813 | H27: 142.4369 | I27: 139.71672 | J27: 0.98090258 | L27: 0 | M27: 0 | N27: 0 | O27: 0 | P27: 0 | Q27: 0 | R27: 0 | S27: 0 | T27: 0 | U27: 0 | V27: 0 | W27: 0 | X27: 0 | Y27: 0 | Z27: 0 | AA27: 0 | AB27: 0 | AC27: 0 | AD27: 0 | AE27: 0 | AF27: 0 | AG27: 0 | AH27: 0 | AI27: 0 | AJ27: 0 | AK27: 0 | AL27: 0 | AM27: 0 | AN27: 0 | AO27: 0 | AP27: 0 | AQ27: 0 | AR27: 0 | AS27: 0 | AT27: 0 | AU27: 0 | AV27: 0 | AW27: 0 | AX27: 0 | AY27: 0 | AZ27: 0 | BA27: 0 | BB27: 0 | BC27: 0 | BD27: 0 | BE27: 0 | BF27: 0 | BG27: 0 | BH27: 0 | BI27: 0 | BJ27: 0 | BK27: 0 | BL27: 0 | BM27: 0 | BN27: 0 | BO27: 0 | BP27: 0 | BQ27: 0 | BR27: 0 | BS27: 0 | BT27: 0 | BU27: 0 | BV27: 0 | BW27: 0 | BX27: 0 | BY27: 0 | BZ27: 0 | CA27: 0 | CB27: 0 | CC27: 0 | CD27: 0 | CE27: 0 | CF27: 0 | CG27: 0 | CH27: 0 | CI27: 0 | CJ27: 0 | CK27: 0 | CL27: 0 | CM27: 0 | CN27: 0 | CO27: 0 | CP27: 0 | CQ27: 0 | CR27: 0 | CS27: 0 | CT27: 0 | CU27: 0 | CV27: 0 | CW27: 0.8886039 | CX27: 4.3159442 | CY27: 2.6374192 | CZ27: 4.4295869 | DA27: 3.9755566 | DB27: 3.3197459 | DC27: 3.8811678 | DD27: 4.3831554 | DE27: 3.8484085 | DF27: 4.6030536 | DG27: 3.9416782 | DH27: 4.359607 | DI27: 4.3676131 | DJ27: 2.3715978 | DK27: 4.5455884 | DL27: 4.0803576 | DM27: 3.7246003 | DN27: 3.191524 | DO27: 3.8486661 | DP27: 3.5109256 | DQ27: 4.0134723 | DR27: 4.8624644 | DS27: 4.3311473 | DT27: 4.003458 | DU27: 4.0092632 | DV27: 4.3923577 | DW27: 4.8940347 | DX27: 12.062164 | DY27: 12.098354 | DZ27: 11.264137 | EA27: 12.137123 | EB27: 12.207238 | EC27: 11.548647 | ED27: 13.754283 | EE27: 14.052738 | EF27: 13.29842 | EG27: 13.7018 | EH27: 14.078239 | EI27: 13.837808 | EJ27: 11.903919 | EK27: 12.807407 | EL27: 11.246401 | EM27: 17.121318 | EN27: 24.387507 | EO27: 24.621369 | EP27: 26.883936 | EQ27: 28.635536 | ER27: 27.275679 | ES27: 26.657298 | ET27: 26.021732 | EU27: 26.566674 | EV27: 24.948968 | EW27: 25.389778 | EX27: 20.765147 | EY27: 22.93504 | EZ27: 24.060011 | FA27: 24.784503 | FB27: 31.4 | FC27: 34.656031 | FD27: 35.527131 | FE27: 33.370676 | FF27: 41.957794 | FG27: 54.125785 | FH27: 56.91724 | FI27: 48.964299 | FJ27: 50.516042 | FL27: 0 | FM27: 0 | FN27: 0 | FO27: 0 | FP27: 0 | FQ27: 0 | FR27: 0 | FS27: 23.448025 | FT27: 47.26585 | FU27: 81.5789 | FV27: 159.55822 | FW27: 305.08866 | FX27: =C27 -> 436.27951
A28: 6 | B28: Biomasa | C28: 187.61447 | D28: 148.55412 | E28: 39.060357 | F28: 0.26293688 | H28: 188.12505 | I28: -39.570936 | J28: -0.21034378 | L28: 0 | M28: 0 | N28: 0 | O28: 0 | P28: 0 | Q28: 0 | R28: 0 | S28: 0 | T28: 0 | U28: 0 | V28: 0 | W28: 0 | X28: 0 | Y28: 0 | Z28: 0 | AA28: 0 | AB28: 0 | AC28: 0 | AD28: 0 | AE28: 0 | AF28: 0 | AG28: 0 | AH28: 0 | AI28: 0 | AJ28: 0 | AK28: 0 | AL28: 0 | AM28: 0 | AN28: 0 | AO28: 0 | AP28: 0 | AQ28: 0 | AR28: 0 | AS28: 0 | AT28: 0 | AU28: 0 | AV28: 0 | AW28: 0 | AX28: 0 | AY28: 0 | AZ28: 0 | BA28: 0 | BB28: 0 | BC28: 0 | BD28: 0 | BE28: 0 | BF28: 0 | BG28: 0 | BH28: 0 | BI28: 0 | BJ28: 0 | BK28: 0 | BL28: 0 | BM28: 0 | BN28: 0 | BO28: 0 | BP28: 0 | BQ28: 0 | BR28: 0 | BS28: 0 | BT28: 0 | BU28: 0 | BV28: 0 | BW28: 0 | BX28: 0 | BY28: 0 | BZ28: 0 | CA28: 0 | CB28: 0 | CC28: 0 | CD28: 0 | CE28: 0 | CF28: 0 | CG28: 0 | CH28: 0 | CI28: 0 | CJ28: 0 | CK28: 0 | CL28: 0 | CM28: 0 | CN28: 0 | CO28: 0 | CP28: 0 | CQ28: 0 | CR28: 0 | CS28: 0 | CT28: 0 | CU28: 0 | CV28: 0 | CW28: 0 | CX28: 0 | CY28: 0 | CZ28: 0 | DA28: 0 | DB28: 0 | DC28: 0 | DD28: 0 | DE28: 0.48064488 | DF28: 5.6078697 | DG28: 13.273094 | DH28: 14.323914 | DI28: 15.538634 | DJ28: 11.563382 | DK28: 17.269348 | DL28: 16.398167 | DM28: 19.462928 | DN28: 5.508479 | DO28: 17.619839 | DP28: 15.864917 | DQ28: 16.9479 | DR28: 18.814807 | DS28: 18.119347 | DT28: 18.75478 | DU28: 18.696759 | DV28: 18.932663 | DW28: 19.555351 | DX28: 18.797597 | DY28: 15.836182 | DZ28: 2.1520464 | EA28: 19.221745 | EB28: 19.391589 | EC28: 17.713523 | ED28: 19.656218 | EE28: 18.944397 | EF28: 14.351487 | EG28: 18.940445 | EH28: 19.577746 | EI28: 19.788247 | EJ28: 19.410469 | EK28: 20.350932 | EL28: 0 | EM28: 18.400172 | EN28: 19.709148 | EO28: 9.955167 | EP28: 6.1285904 | EQ28: 13.132301 | ER28: 13.950061 | ES28: 13.71693 | ET28: 14.180315 | EU28: 2.3334588 | EV28: 15.630411 | EW28: 20.127182 | EX28: 19.690554 | EY28: 19.1068 | EZ28: 17.750912 | FA28: 17.390953 | FB28: 19.302962 | FC28: 19.488174 | FD28: 19.945185 | FE28: 18.942358 | FF28: 18.720552 | FG28: 19.554684 | FH28: 16.708736 | FI28: 13.33142 | FJ28: 6.4785384 | FL28: 0 | FM28: 0 | FN28: 0 | FO28: 0 | FP28: 0 | FQ28: 0 | FR28: 0 | FS28: 0 | FT28: 137.0463 | FU28: 201.6941 | FV28: 206.52523 | FW28: 167.66092 | FX28: =C28 -> 187.61447
A29: 7 | B29: Total Renovable No Convencional | C29: 1726.1488 | D29: 1499.4199 | E29: 226.72887 | F29: 0.15121106 | H29: 1040.0746 | I29: 459.3453 | J29: 0.4416465 | L29: 0 | M29: 0 | N29: 0 | O29: 0 | P29: 0 | Q29: 0 | R29: 0 | S29: 0 | T29: 0 | U29: 0 | V29: 0 | W29: 0 | X29: 0 | Y29: 0 | Z29: 0 | AA29: 0 | AB29: 0 | AC29: 0 | AD29: 0 | AE29: 0 | AF29: 0 | AG29: 0 | AH29: 0 | AI29: 0 | AJ29: 0 | AK29: 0 | AL29: 0 | AM29: 0 | AN29: 0 | AO29: 0 | AP29: 0 | AQ29: 0 | AR29: 0.29546457 | AS29: 3.4121442 | AT29: 2.923479 | AU29: 7.114331 | AV29: 8.895 | AW29: 7.734 | AX29: 11.226 | AY29: 6.132 | AZ29: 8.012 | BA29: 8.672 | BB29: 12.593 | BC29: 9.246 | BD29: 3.839 | BE29: 3.699 | BF29: 2.756 | BG29: 11.33 | BH29: 26.803041 | BI29: 18.144141 | BJ29: 14.612194 | BK29: 22.582782 | BL29: 19.309188 | BM29: 27.211582 | BN29: 24.908539 | BO29: 24.095206 | BP29: 8.8094064 | BQ29: 10.16221 | BR29: 13.024204 | BS29: 28.923755 | BT29: 29.164996 | BU29: 21.879548 | BV29: 15.366891 | BW29: 21.875993 | BX29: 19.167157 | BY29: 22.658939 | BZ29: 26.038107 | CA29: 21.243358 | CB29: 17.536231 | CC29: 6.6013368 | CD29: 16.47489 | CE29: 20.769954 | CF29: 20.492698 | CG29: 18.054796 | CH29: 27.895966 | CI29: 23.922806 | CJ29: 27.11038 | CK29: 29.647274 | CL29: 31.332084 | CM29: 23.638174 | CN29: 13.223016 | CO29: 10.533108 | CP29: 22.266187 | CQ29: 35.56955 | CR29: 13.110925 | CS29: 11.856603 | CT29: 23.873474 | CU29: 10.276707 | CV29: 23.248139 | CW29: 36.098098 | CX29: 55.480485 | CY29: 46.532222 | CZ29: 32.834053 | DA29: 17.170232 | DB29: 16.978265 | DC29: 48.581357 | DD29: 34.085545 | DE29: 27.824373 | DF29: 45.940367 | DG29: 51.880686 | DH29: 56.5902 | DI29: 66.296207 | DJ29: 56.248903 | DK29: 59.720518 | DL29: 34.918329 | DM29: 46.347669 | DN29: 27.174137 | DO29: 55.190188 | DP29: 62.913229 | DQ29: 73.423271 | DR29: 50.27969 | DS29: 51.259193 | DT29: 67.098259 | DU29: 62.333617 | DV29: 71.445918 | DW29: 71.964491 | DX29: 63.225631 | DY29: 49.454955 | DZ29: 46.767379 | EA29: 94.310923 | EB29: 81.87286 | EC29: 84.017821 | ED29: 79.781157 | EE29: 101.69778 | EF29: 89.900678 | EG29: 128.9125 | EH29: 138.62624 | EI29: 121.64251 | EJ29: 71.237845 | EK29: 85.401488 | EL29: 56.983708 | EM29: 114.98381 | EN29: 143.02687 | EO29: 157.51416 | EP29: 135.81305 | EQ29: 120.91892 | ER29: 125.09347 | ES29: 152.12382 | ET29: 161.67989 | EU29: 136.87574 | EV29: 100.91362 | EW29: 144.47614 | EX29: 120.9842 | EY29: 112.455 | EZ29: 129.18446 | FA29: 179.76827 | FB29: 163.38758 | FC29: 144.71226 | FD29: 170.20123 | FE29: 183.70511 | FF29: 202.06201 | FG29: 186.30152 | FH29: 127.87301 | FI29: 119.54156 | FJ29: 119.41178 | FL29: 0 | FM29: 0 | FN29: 13.745419 | FO29: 94.134 | FP29: 238.58625 | FQ29: 238.7774 | FR29: 283.68604 | FS29: 336.04056 | FT29: 562.21712 | FU29: 764.47656 | FV29: 1155.0584 | FW29: 1611.8749 | FX29: =C29 -> 1726.1488
B31: Composición Generación de Energía por tipo de Combustible | E31: PP | I31: PP
B32: Carbón Mineral | C32: 0.312883 | D32: 0.37078109 | E32: -5.7898088 | F32: 0 | H32: 0.19739036 | I32: 17.339073 | L32: 0.19601128 | M32: 0.14015035 | N32: 0.14054662 | O32: 0.15249173 | P32: 0.17159596 | Q32: 0.13910188 | R32: 0.16145491 | S32: 0.1530576 | T32: 0.16964617 | U32: 0.17682245 | V32: 0.18988736 | W32: 0.18933839 | X32: 0.19092029 | Y32: 0.1528414 | Z32: 0.19107428 | AA32: 0.17150574 | AB32: 0.1644063 | AC32: 0.14965348 | AD32: 0.088804368 | AE32: 0.085511008 | AF32: 0.12303401 | AG32: 0.15097535 | AH32: 0.17483752 | AI32: 0.18617119 | AJ32: 0.180308 | AK32: 0.15866697 | AL32: 0.17972966 | AM32: 0.16603432 | AN32: 0.16566055 | AO32: 0.14809093 | AP32: 0.090503891 | AQ32: 0.10594094 | AR32: 0.15463078 | AS32: 0.092359098 | AT32: 0.17136616 | AU32: 0.17496109 | AV32: 0.19715094 | AW32: 0.17645253 | AX32: 0.16280066 | AY32: 0.15079914 | AZ32: 0.15677595 | BA32: 0.1133289 | BB32: 0.13563049 | BC32: 0.14243078 | BD32: 0.15741322 | BE32: 0.1430347 | BF32: 0.11841491 | BG32: 0.092378304 | BH32: 0.029302065 | BI32: 0.031257669 | BJ32: 0.031437646 | BK32: 0.02907122 | BL32: 0.027274559 | BM32: 0.027580845 | BN32: 0.16504815 | BO32: 0.16381943 | BP32: 0.14194961 | BQ32: 0.16272735 | BR32: 0.1929417 | BS32: 0.1235483 | BT32: 0.19045951 | BU32: 0.13150065 | BV32: 0.17368549 | BW32: 0.1407271 | BX32: 0.17558505 | BY32: 0.16858411 | BZ32: 0.16083826 | CA32: 0.15989553 | CB32: 0.15797897 | CC32: 0.15055297 | CD32: 0.16616237 | CE32: 0.18423854 | CF32: 0.18268554 | CG32: 0.14388118 | CH32: 0.13512281 | CI32: 0.12929316 | CJ32: 0.1384907 | CK32: 0.13913322 | CL32: 0.14849078 | CM32: 0.14454943 | CN32: 0.15244953 | CO32: 0.14893192 | CP32: 0.15246186 | CQ32: 0.16307743 | CR32: 0.1782932 | CS32: 0.15462232 | CT32: 0.10642952 | CU32: 0.11397168 | CV32: 0.13354849 | CW32: 0.15410643 | CX32: 0.14323874 | CY32: 0.14355048 | CZ32: 0.13632651 | DA32: 0.15481442 | DB32: 0.1541842 | DC32: 0.154573 | DD32: 0.16916833 | DE32: 0.10816621 | DF32: 0.12401133 | DG32: 0.13787619 | DH32: 0.11082592 | DI32: 0.14022542 | DJ32: 0.14199581 | DK32: 0.14165706 | DL32: 0.14705528 | DM32: 0.14001836 | DN32: 0.13555084 | DO32: 0.1638832 | DP32: 0.16261278 | DQ32: 0.16184903 | DR32: 0.15140063 | DS32: 0.14103849 | DT32: 0.079382223 | DU32: 0.091446224 | DV32: 0.09463255 | DW32: 0.12706677 | DX32: 0.12125916 | DY32: 0.14307531 | DZ32: 0.14314318 | EA32: 0.15262521 | EB32: 0.15315028 | EC32: 0.15040292 | ED32: 0.12877142 | EE32: 0.20398207 | EF32: 0.19795016 | EG32: 0.12939303 | EH32: 0.21540252 | EI32: 0.19487824 | EJ32: 0.23541542 | EK32: 0.26904356 | EL32: 0.27000451 | EM32: 0.32506601 | EN32: 0.3302461 | EO32: 0.36016244 | EP32: 0.32461554 | EQ32: 0.32426973 | ER32: 0.44303622 | ES32: 0.384121 | ET32: 0.40438552 | EU32: 0.36337175 | EV32: 0.40028359 | EW32: 0.36663296 | EX32: 0.36016164 | EY32: 0.37176244 | EZ32: 0.24412104 | FA32: 0.21671658 | FB32: 0.27308837 | FC32: 0.33079068 | FD32: 0.33152319 | FE32: 0.34172815 | FF32: 0.36114199 | FG32: 0.34036212 | FH32: 0.30222349 | FI32: 0.35128466 | FJ32: 0.31468291 | FL32: 0.16550611 | FM32: 0.15111928 | FN32: 0.14765778 | FO32: 0.14434298 | FP32: 0.098326933 | FQ32: 0.16347912 | FR32: 0.14809773 | FS32: 0.1436725 | FT32: 0.13856457 | FU32: 0.12956782 | FV32: 0.20813018 | FW32: 0.37086173 | FX32: =C32 -> 0.312883
B33: Gas Natural | C33: 0.40302083 | D33: 0.28847603 | E33: 11.45448 | F33: 0 | H33: 0.29497641 | I33: -0.65003826 | L33: 0.15689729 | M33: 0.19614922 | N33: 0.22194631 | O33: 0.17315087 | P33: 0.088626976 | Q33: 0.21068974 | R33: 0.20336544 | S33: 0.22336726 | T33: 0.18440073 | U33: 0.2042585 | V33: 0.20499068 | W33: 0.22054601 | X33: 0.24242807 | Y33: 0.26583441 | Z33: 0.25215672 | AA33: 0.27994035 | AB33: 0.26794549 | AC33: 0.2362169 | AD33: 0.28314515 | AE33: 0.28950757 | AF33: 0.27529154 | AG33: 0.29507976 | AH33: 0.28565184 | AI33: 0.29224384 | AJ33: 0.35854679 | AK33: 0.35873489 | AL33: 0.26092107 | AM33: 0.31930543 | AN33: 0.29437955 | AO33: 0.29145796 | AP33: 0.32316562 | AQ33: 0.29940607 | AR33: 0.30716752 | AS33: 0.31375038 | AT33: 0.31403987 | AU33: 0.32355683 | AV33: 0.2484452 | AW33: 0.30806329 | AX33: 0.35959032 | AY33: 0.3668076 | AZ33: 0.35610148 | BA33: 0.34868841 | BB33: 0.32718213 | BC33: 0.35834095 | BD33: 0.35820479 | BE33: 0.3478511 | BF33: 0.36370525 | BG33: 0.39994638 | BH33: 0.30138383 | BI33: 0.3187841 | BJ33: 0.33802715 | BK33: 0.37155861 | BL33: 0.34134197 | BM33: 0.34224933 | BN33: 0.30770967 | BO33: 0.27348954 | BP33: 0.30999114 | BQ33: 0.31090213 | BR33: 0.28101124 | BS33: 0.35446939 | BT33: 0.35548222 | BU33: 0.36277555 | BV33: 0.37717801 | BW33: 0.36624991 | BX33: 0.34647405 | BY33: 0.34112638 | BZ33: 0.33855008 | CA33: 0.34087488 | CB33: 0.32311966 | CC33: 0.32111803 | CD33: 0.30034651 | CE33: 0.33171972 | CF33: 0.25332724 | CG33: 0.19182569 | CH33: 0.34900571 | CI33: 0.34866396 | CJ33: 0.32178116 | CK33: 0.30900445 | CL33: 0.30649019 | CM33: 0.31146128 | CN33: 0.30161169 | CO33: 0.29733379 | CP33: 0.33739608 | CQ33: 0.35952492 | CR33: 0.35813854 | CS33: 0.3012035 | CT33: 0.32740032 | CU33: 0.34014791 | CV33: 0.28062753 | CW33: 0.26517042 | CX33: 0.26097631 | CY33: 0.27933647 | CZ33: 0.27922793 | DA33: 0.322181 | DB33: 0.32621856 | DC33: 0.34133261 | DD33: 0.22885184 | DE33: 0.2968468 | DF33: 0.30399172 | DG33: 0.34272119 | DH33: 0.34944865 | DI33: 0.36508899 | DJ33: 0.33188115 | DK33: 0.37618491 | DL33: 0.37699374 | DM33: 0.37715051 | DN33: 0.40541248 | DO33: 0.41439592 | DP33: 0.36816058 | DQ33: 0.38476199 | DR33: 0.32959345 | DS33: 0.39437195 | DT33: 0.38990455 | DU33: 0.37153198 | DV33: 0.36309583 | DW33: 0.36736485 | DX33: 0.24402646 | DY33: 0.29145554 | DZ33: 0.2858577 | EA33: 0.30328839 | EB33: 0.33792446 | EC33: 0.28817258 | ED33: 0.28958719 | EE33: 0.24614351 | EF33: 0.29253138 | EG33: 0.3051023 | EH33: 0.2960483 | EI33: 0.31234953 | EJ33: 0.25513791 | EK33: 0.28687842 | EL33: 0.33589298 | EM33: 0.34736651 | EN33: 0.34020241 | EO33: 0.24027449 | EP33: 0.26589773 | EQ33: 0.27179639 | ER33: 0.2352798 | ES33: 0.23160691 | ET33: 0.19216202 | EU33: 0.33227989 | EV33: 0.27961202 | EW33: 0.37704455 | EX33: 0.40376252 | EY33: 0.42876361 | EZ33: 0.44911446 | FA33: 0.47879497 | FB33: 0.45063901 | FC33: 0.40361863 | FD33: 0.41032357 | FE33: 0.36084965 | FF33: 0.35866611 | FG33: 0.33550004 | FH33: 0.39987863 | FI33: 0.39142818 | FJ33: 0.42323409 | FL33: 0.19141818 | FM33: 0.2724439 | FN33: 0.31287015 | FO33: 0.34650787 | FP33: 0.31949048 | FQ33: 0.3414484 | FR33: 0.30873802 | FS33: 0.30549474 | FT33: 0.34943292 | FU33: 0.34033267 | FV33: 0.29938336 | FW33: 0.30000332 | FX33: =C33 -> 0.40302083
B34: Fuel Oil No. 2 | C34: 0.0020618189 | D34: 0.008941838 | E34: -0.6880019 | F34: 0 | H34: 0.069301512 | I34: -6.0359674 | L34: 0.035318785 | M34: 0.038368762 | N34: 0.050079873 | O34: 0.084593004 | P34: 0.11171583 | Q34: 0.075323412 | R34: 0.086410267 | S34: 0.098566248 | T34: 0.074888589 | U34: 0.055441693 | V34: 0.063074016 | W34: 0.043442549 | X34: 0.0008516532 | Y34: 0.00073716275 | Z34: 0.052923566 | AA34: 0.046215751 | AB34: 0.037106607 | AC34: 0.028293827 | AD34: 0.023363586 | AE34: 0.025250823 | AF34: 0.011106594 | AG34: 0.0034419846 | AH34: 0.008542911 | AI34: 0.011345283 | AJ34: 0.018513967 | AK34: 0.0076464654 | AL34: 0.070865354 | AM34: 0.054817752 | AN34: 0.089616479 | AO34: 0.065498445 | AP34: 0.091130261 | AQ34: 0.11335515 | AR34: 0.075568692 | AS34: 0.090224237 | AT34: 0.056378178 | AU34: 0.053615342 | AV34: 0.09788564 | AW34: 0.065226793 | AX34: 0.046033162 | AY34: 0.047697185 | AZ34: 0.032902309 | BA34: 0.083969667 | BB34: 0.05999325 | BC34: 0.045190225 | BD34: 0.02811497 | BE34: 0.038898514 | BF34: 0.083716521 | BG34: 0.078679064 | BH34: 0.075191469 | BI34: 0.063545867 | BJ34: 0.043872018 | BK34: 0.064022981 | BL34: 0.092030286 | BM34: 0.025790663 | BN34: 0.012788142 | BO34: 0.054554373 | BP34: 0.042659414 | BQ34: 0.0098759281 | BR34: 0.0027074874 | BS34: 0.0010502303 | BT34: 0.0013969406 | BU34: 0.013008533 | BV34: 0.00023908924 | BW34: 0.0023067514 | BX34: 0.00045908414 | BY34: 0.0054980697 | BZ34: 0.01960108 | CA34: 0.0068317016 | CB34: 0.017030127 | CC34: 0.013831962 | CD34: 0.057691651 | CE34: 0.0096812047 | CF34: 0.061211477 | CG34: 0.12610987 | CH34: 0.022584887 | CI34: 0.03718219 | CJ34: 0.081034985 | CK34: 0.098541822 | CL34: 0.092736561 | CM34: 0.10209031 | CN34: 0.10731112 | CO34: 0.12112038 | CP34: 0.066369941 | CQ34: 0.040493502 | CR34: 0.028389128 | CS34: 0.084983071 | CT34: 0.10730199 | CU34: 0.099006579 | CV34: 0.093210333 | CW34: 0.089652835 | CX34: 0.11029385 | CY34: 0.10978142 | CZ34: 0.099697083 | DA34: 0.076472025 | DB34: 0.026851265 | DC34: 0.01643343 | DD34: 0.022213822 | DE34: 0.049309893 | DF34: 0.045625133 | DG34: 0.029772177 | DH34: 0.013038024 | DI34: 0.026405361 | DJ34: 0.052874475 | DK34: 0.038055814 | DL34: 0.038364825 | DM34: 0.043357068 | DN34: 0.047037535 | DO34: 0.0013918209 | DP34: 0.018859287 | DQ34: 0 | DR34: 0.037143001 | DS34: 0.011569848 | DT34: 0.040654793 | DU34: 0.058994553 | DV34: 0.074389963 | DW34: 0.066652587 | DX34: 0.11575199 | DY34: 0.06774067 | DZ34: 0.084804963 | EA34: 0.064830336 | EB34: 0.030987053 | EC34: 0.071817514 | ED34: 0.11483911 | EE34: 0.086821879 | EF34: 0.071347042 | EG34: 0.0717058 | EH34: 0.060554446 | EI34: 0.053548813 | EJ34: 0.10116507 | EK34: 0.064924261 | EL34: 0.035466812 | EM34: 0.011198726 | EN34: 0.0059859095 | EO34: 0.014856878 | EP34: 0.010783479 | EQ34: 0.00062166328 | ER34: 0.0016023691 | ES34: 0.015884506 | ET34: 0.0350632 | EU34: 0.0016827382 | EV34: 0.0082356581 | EW34: 0.00085933013 | EX34: 0.00046452516 | EY34: 0 | EZ34: 0.0011588484 | FA34: 0.0016465291 | FB34: 0.00086508792 | FC34: 0 | FD34: 0.0011429431 | FE34: 0.0025847096 | FF34: 0.00024013971 | FG34: 0.0037473329 | FH34: 0.0067060878 | FI34: 0 | FJ34: 0.0039804082 | FL34: 0.068679511 | FM34: 0.021211418 | FN34: 0.067273708 | FO34: 0.058406067 | FP34: 0.040330585 | FQ34: 0.012394027 | FR34: 0.080328919 | FS34: 0.079554451 | FT34: 0.033996506 | FU34: 0.055072957 | FV34: 0.064414024 | FW34: 0.0082070961 | FX34: =C34 -> 0.0020618189
B35: Fuel Oil No. 6 | C35: 0.10872934 | D35: 0.16952405 | E35: -6.0794712 | F35: 0 | H35: 0.30993156 | I35: -14.040751 | L35: 0.38043945 | M35: 0.39567499 | N35: 0.40353134 | O35: 0.40860494 | P35: 0.37331521 | Q35: 0.34785405 | R35: 0.3379394 | S35: 0.33051291 | T35: 0.40699043 | U35: 0.40385659 | V35: 0.4225656 | W35: 0.37107351 | X35: 0.38363254 | Y35: 0.44805131 | Z35: 0.4021118 | AA35: 0.36277155 | AB35: 0.35855432 | AC35: 0.37108361 | AD35: 0.34997151 | AE35: 0.35882567 | AF35: 0.38427344 | AG35: 0.36515527 | AH35: 0.34471303 | AI35: 0.36413869 | AJ35: 0.31505951 | AK35: 0.29787301 | AL35: 0.31118346 | AM35: 0.30795264 | AN35: 0.28443778 | AO35: 0.27907343 | AP35: 0.27366734 | AQ35: 0.2644107 | AR35: 0.24794085 | AS35: 0.26877061 | AT35: 0.24300296 | AU35: 0.25095975 | AV35: 0.35099498 | AW35: 0.34056013 | AX35: 0.31932185 | AY35: 0.27381681 | AZ35: 0.26230282 | BA35: 0.32735642 | BB35: 0.36194151 | BC35: 0.32595874 | BD35: 0.31789901 | BE35: 0.32947804 | BF35: 0.26474638 | BG35: 0.26089177 | BH35: 0.33822868 | BI35: 0.37171461 | BJ35: 0.36974044 | BK35: 0.35189726 | BL35: 0.33884292 | BM35: 0.32352722 | BN35: 0.27928466 | BO35: 0.2836568 | BP35: 0.31699569 | BQ35: 0.3619497 | BR35: 0.3687547 | BS35: 0.32491038 | BT35: 0.2678001 | BU35: 0.30765635 | BV35: 0.30465654 | BW35: 0.35339361 | BX35: 0.34567352 | BY35: 0.36995656 | BZ35: 0.37880333 | CA35: 0.35450559 | CB35: 0.36201226 | CC35: 0.38131462 | CD35: 0.38510854 | CE35: 0.37165607 | CF35: 0.41531073 | CG35: 0.43908441 | CH35: 0.3893956 | CI35: 0.39172134 | CJ35: 0.37885158 | CK35: 0.36579963 | CL35: 0.37747548 | CM35: 0.37940684 | CN35: 0.36368976 | CO35: 0.36217962 | CP35: 0.34611813 | CQ35: 0.3287514 | CR35: 0.3489079 | CS35: 0.38261518 | CT35: 0.37660604 | CU35: 0.38025043 | CV35: 0.32867821 | CW35: 0.32907517 | CX35: 0.36407816 | CY35: 0.318013 | CZ35: 0.34190412 | DA35: 0.30008169 | DB35: 0.26705921 | DC35: 0.26367783 | DD35: 0.33152573 | DE35: 0.34157433 | DF35: 0.31702195 | DG35: 0.27983721 | DH35: 0.26457374 | DI35: 0.29435825 | DJ35: 0.30115418 | DK35: 0.28218105 | DL35: 0.24942321 | DM35: 0.25598619 | DN35: 0.24578812 | DO35: 0.26383399 | DP35: 0.25229833 | DQ35: 0.16720202 | DR35: 0.3072758 | DS35: 0.28497706 | DT35: 0.29664113 | DU35: 0.32878661 | DV35: 0.32102246 | DW35: 0.30972148 | DX35: 0.37213387 | DY35: 0.34163231 | DZ35: 0.357338 | EA35: 0.3312543 | EB35: 0.33792505 | EC35: 0.35455929 | ED35: 0.35352489 | EE35: 0.33908858 | EF35: 0.32962177 | EG35: 0.33726353 | EH35: 0.28276374 | EI35: 0.29335706 | EJ35: 0.28052203 | EK35: 0.25294965 | EL35: 0.27027872 | EM35: 0.18752266 | EN35: 0.14884715 | EO35: 0.20179493 | EP35: 0.19220647 | EQ35: 0.23772501 | ER35: 0.17260155 | ES35: 0.21494656 | ET35: 0.21305703 | EU35: 0.15111012 | EV35: 0.18195871 | EW35: 0.096254636 | EX35: 0.065298332 | EY35: 0.043965899 | EZ35: 0.13610582 | FA35: 0.09911893 | FB35: 0.083661368 | FC35: 0.089325347 | FD35: 0.082056758 | FE35: 0.08949846 | FF35: 0.085920101 | FG35: 0.1216685 | FH35: 0.15900411 | FI35: 0.11845522 | FJ35: 0.12689495 | FL35: 0.38106222 | FM35: 0.37343231 | FN35: 0.27777834 | FO35: 0.31105078 | FP35: 0.33349276 | FQ35: 0.35012412 | FR35: 0.37691539 | FS35: 0.33290183 | FT35: 0.28425527 | FU35: 0.30888195 | FV35: 0.29963477 | FW35: 0.15920706 | FX35: =C35 -> 0.10872934
B36: Fuel Oil No. 2 y No. 6 | C36: 0 | D36: 0 | E36: 0 | F36: 0 | H36: 0.003519572 | I36: -0.3519572 | L36: 0.09009093 | M36: 0.061085848 | N36: 0.054741078 | O36: 0.054396201 | P36: 0.072810945 | Q36: 0.071068193 | R36: 0.10501753 | S36: 0.065762927 | T36: 0.044793395 | U36: 0.05934316 | V36: 0.034169066 | W36: 0.09248632 | X36: 0.10053674 | Y36: 0.070132502 | Z36: 0.049961126 | AA36: 0.06969319 | AB36: 0.084324464 | AC36: 0.056573532 | AD36: 0.094413878 | AE36: 0.080771971 | AF36: 0.088162671 | AG36: 0.055422477 | AH36: 0.010844732 | AI36: 0.011174421 | AJ36: 0.0096609692 | AK36: 0.077274382 | AL36: 0.086378059 | AM36: 0.078013703 | AN36: 0.082121519 | AO36: 0.072515027 | AP36: 0.093686085 | AQ36: 0.055102392 | AR36: 0.064833633 | AS36: 0.080450131 | AT36: 0.081324609 | AU36: 0.088539619 | AV36: 0 | AW36: 0 | AX36: 0 | AY36: 0 | AZ36: 0 | BA36: 0 | BB36: 0 | BC36: 0 | BD36: 0 | BE36: 0 | BF36: 0 | BG36: 0 | BH36: 0.080908301 | BI36: 0.049087 | BJ36: 0.083807896 | BK36: 0.043498414 | BL36: 0.036856535 | BM36: 0.061251121 | BN36: 0.04336047 | BO36: 0.075812578 | BP36: 0.038668926 | BQ36: 0 | BR36: 0 | BS36: 0.0037420161 | BT36: 0.020451101 | BU36: 0.035062731 | BV36: 0.023612857 | BW36: 0.017930676 | BX36: 0.0027548106 | BY36: 0.00086282758 | BZ36: 0.0085595569 | CA36: 0.043931083 | CB36: 0.04539457 | CC36: 0.05439515 | CD36: 0.0010744781 | CE36: 0 | CF36: 0 | CG36: 0 | CH36: 0 | CI36: 0 | CJ36: 0 | CK36: 0 | CL36: 0 | CM36: 0 | CN36: 0 | CO36: 0 | CP36: 0 | CQ36: 0 | CR36: 0 | CS36: 0 | CT36: 0 | CU36: 0 | CV36: 0.059204696 | CW36: 0.028047513 | CX36: 0.00076935653 | CY36: 0.031407229 | CZ36: 0.036080209 | DA36: 0.013141449 | DB36: 0.0012594559 | DC36: 0 | DD36: 0.046813657 | DE36: 0.050855019 | DF36: 0.022435637 | DG36: 0.0030461971 | DH36: 0.0066751748 | DI36: 0.013015417 | DJ36: 0.006701257 | DK36: 0.0035436038 | DL36: 0.0069143892 | DM36: 0.0057585107 | DN36: 0.008659004 | DO36: 0.011338629 | DP36: 0.00059528252 | DQ36: 0 | DR36: 0.00041076851 | DS36: 0 | DT36: 0.0096541532 | DU36: 0.0068047851 | DV36: 0.0067815067 | DW36: 0.0024561426 | DX36: 0.017472466 | DY36: 0.0086400704 | DZ36: 0.0055220128 | EA36: 0.0030499528 | EB36: 0 | EC36: 0 | ED36: 0 | EE36: 0 | EF36: 0 | EG36: 0 | EH36: 0 | EI36: 0.012496994 | EJ36: 0.018923732 | EK36: 0.0043579582 | EL36: 0.00049209611 | EM36: 0 | EN36: 0 | EO36: 0 | EP36: 0 | EQ36: 0 | ER36: 0 | ES36: 0 | ET36: 0 | EU36: 0 | EV36: 0 | EW36: 0 | EX36: 0 | EY36: 0 | EZ36: 0 | FA36: 0 | FB36: 0 | FC36: 0 | FD36: 0 | FE36: 0 | FF36: 0 | FG36: 0 | FH36: 0 | FI36: 0 | FJ36: 0 | FL36: 0.067449322 | FM36: 0.064901366 | FN36: 0.072758483 | FO36: 0 | FP36: 0.042873792 | FQ36: 0.021297767 | FR36: 0 | FS36: 0.014891279 | FT36: 0.014587958 | FU36: 0.0052845567 | FV36: 0.0032235128 | FW36: 0 | FX36: =C36 -> 0
B37: Hidráulica | C37: 0.076401521 | D37: 0.069788052 | E37: 0.66134695 | F37: 0 | H37: 0.059659376 | I37: 1.0128676 | L37: 0.14124227 | M37: 0.16857083 | N37: 0.12915478 | O37: 0.12676326 | P37: 0.18193507 | Q37: 0.15596272 | R37: 0.10581246 | S37: 0.12873305 | T37: 0.11928068 | U37: 0.1002776 | V37: 0.085313278 | W37: 0.083113222 | X37: 0.081630711 | Y37: 0.062403215 | Z37: 0.051772496 | AA37: 0.069873414 | AB37: 0.087662819 | AC37: 0.15817866 | AD37: 0.16030151 | AE37: 0.16013296 | AF37: 0.11813175 | AG37: 0.12992515 | AH37: 0.17540996 | AI37: 0.13492658 | AJ37: 0.11791077 | AK37: 0.099804283 | AL37: 0.090922395 | AM37: 0.07387616 | AN37: 0.083784119 | AO37: 0.1433642 | AP37: 0.1278468 | AQ37: 0.16178475 | AR37: 0.14958837 | AS37: 0.15141842 | AT37: 0.13109336 | AU37: 0.10137081 | AV37: 0.096452953 | AW37: 0.10153903 | AX37: 0.10124629 | AY37: 0.154929 | AZ37: 0.18513726 | BA37: 0.11928087 | BB37: 0.10486153 | BC37: 0.12025538 | BD37: 0.13510323 | BE37: 0.13766245 | BF37: 0.16701359 | BG37: 0.1578071 | BH37: 0.14581913 | BI37: 0.14334671 | BJ37: 0.11708046 | BK37: 0.11626421 | BL37: 0.14567149 | BM37: 0.19188241 | BN37: 0.1701605 | BO37: 0.12838823 | BP37: 0.14196575 | BQ37: 0.14517351 | BR37: 0.14150736 | BS37: 0.16015581 | BT37: 0.13633058 | BU37: 0.12697325 | BV37: 0.10665717 | BW37: 0.099339126 | BX37: 0.11217206 | BY37: 0.094274666 | BZ37: 0.072248809 | CA37: 0.076271715 | CB37: 0.079120215 | CC37: 0.073369934 | CD37: 0.074852948 | CE37: 0.083878885 | CF37: 0.068634155 | CG37: 0.080971737 | CH37: 0.079290186 | CI37: 0.072092832 | CJ37: 0.057271891 | CK37: 0.063118652 | CL37: 0.0502594 | CM37: 0.043970866 | CN37: 0.064293671 | CO37: 0.062249346 | CP37: 0.078273475 | CQ37: 0.07789833 | CR37: 0.074614303 | CS37: 0.065690927 | CT37: 0.062301039 | CU37: 0.058188487 | CV37: 0.087033878 | CW37: 0.10556068 | CX37: 0.079365798 | CY37: 0.083123644 | CZ37: 0.081542959 | DA37: 0.11996721 | DB37: 0.21018881 | DC37: 0.18425733 | DD37: 0.17221527 | DE37: 0.12759993 | DF37: 0.14920399 | DG37: 0.1635306 | DH37: 0.21250354 | DI37: 0.11017232 | DJ37: 0.12400762 | DK37: 0.11583221 | DL37: 0.15464736 | DM37: 0.14453135 | DN37: 0.13596027 | DO37: 0.10125289 | DP37: 0.14524989 | DQ37: 0.21750908 | DR37: 0.13384584 | DS37: 0.12810601 | DT37: 0.13350509 | DU37: 0.096635436 | DV37: 0.090064732 | DW37: 0.076030723 | DX37: 0.081862834 | DY37: 0.11109769 | DZ37: 0.088200604 | EA37: 0.074109996 | EB37: 0.077151961 | EC37: 0.066195752 | ED37: 0.055159003 | EE37: 0.049929309 | EF37: 0.048305937 | EG37: 0.069576062 | EH37: 0.057351471 | EI37: 0.056587112 | EJ37: 0.062018299 | EK37: 0.067251632 | EL37: 0.048712958 | EM37: 0.050338466 | EN37: 0.072952573 | EO37: 0.066011226 | EP37: 0.10334912 | EQ37: 0.072097128 | ER37: 0.061013642 | ES37: 0.055811821 | ET37: 0.055473217 | EU37: 0.066130972 | EV37: 0.065696738 | EW37: 0.069321319 | EX37: 0.086517268 | EY37: 0.078026194 | EZ37: 0.077123459 | FA37: 0.072064837 | FB37: 0.0858212 | FC37: 0.082248392 | FD37: 0.072861164 | FE37: 0.09248296 | FF37: 0.077649764 | FG37: 0.090969842 | FH37: 0.059729096 | FI37: 0.071074299 | FJ37: 0.060060585 | FL37: 0.12588465 | FM37: 0.11689173 | FN37: 0.12056 | FO37: 0.13264417 | FP37: 0.14577966 | FQ37: 0.093521936 | FR37: 0.065910191 | FS37: 0.10093132 | FT37: 0.14237436 | FU37: 0.11217249 | FV37: 0.05887532 | FW37: 0.070464972 | FX37: =C37 -> 0.076401521
B38: Eòlica | C38: 0.061878988 | D38: 0.065921532 | E38: -0.40425434 | F38: 0 | H38: 0.044492261 | I38: 2.142927 | L38: 0 | M38: 0 | N38: 0 | O38: 0 | P38: 0 | Q38: 0 | R38: 0 | S38: 0 | T38: 0 | U38: 0 | V38: 0 | W38: 0 | X38: 0 | Y38: 0 | Z38: 0 | AA38: 0 | AB38: 0 | AC38: 0 | AD38: 0 | AE38: 0 | AF38: 0 | AG38: 0 | AH38: 0 | AI38: 0 | AJ38: 0 | AK38: 0 | AL38: 0 | AM38: 0 | AN38: 0 | AO38: 0 | AP38: 0 | AQ38: 0 | AR38: 0.000270156 | AS38: 0.0030271159 | AT38: 0.0027948735 | AU38: 0.006996551 | AV38: 0.0090702832 | AW38: 0.0081582278 | AX38: 0.011007717 | AY38: 0.0059502612 | AZ38: 0.0067801774 | BA38: 0.0073757427 | BB38: 0.010391096 | BC38: 0.0078239236 | BD38: 0.0032647723 | BE38: 0.0030752015 | BF38: 0.0024033368 | BG38: 0.010297379 | BH38: 0.029166526 | BI38: 0.022264044 | BJ38: 0.016034382 | BK38: 0.023687301 | BL38: 0.01798225 | BM38: 0.027718409 | BN38: 0.021648401 | BO38: 0.020279048 | BP38: 0.0077694796 | BQ38: 0.0093713803 | BR38: 0.013077512 | BS38: 0.032123876 | BT38: 0.028079549 | BU38: 0.023022943 | BV38: 0.013970852 | BW38: 0.020052829 | BX38: 0.01688142 | BY38: 0.019697391 | BZ38: 0.021398875 | CA38: 0.017689494 | CB38: 0.015344194 | CC38: 0.0054173279 | CD38: 0.01476351 | CE38: 0.01882558 | CF38: 0.01883086 | CG38: 0.018127113 | CH38: 0.024600814 | CI38: 0.021046517 | CJ38: 0.022569686 | CK38: 0.02440223 | CL38: 0.02454759 | CM38: 0.018521273 | CN38: 0.010644228 | CO38: 0.0081849477 | CP38: 0.019380513 | CQ38: 0.030254417 | CR38: 0.011656923 | CS38: 0.010885 | CT38: 0.019961099 | CU38: 0.008434918 | CV38: 0.017696866 | CW38: 0.027688155 | CX38: 0.038066698 | CY38: 0.032816012 | CZ38: 0.021818647 | DA38: 0.010252978 | DB38: 0.011454455 | DC38: 0.036552101 | DD38: 0.02545498 | DE38: 0.021657396 | DF38: 0.029328582 | DG38: 0.028876584 | DH38: 0.028759776 | DI38: 0.035500657 | DJ38: 0.031132749 | DK38: 0.027004226 | DL38: 0.011000416 | DM38: 0.0165892 | DN38: 0.014678993 | DO38: 0.026825453 | DP38: 0.036140099 | DQ38: 0.049071252 | DR38: 0.021338422 | DS38: 0.022445195 | DT38: 0.033211648 | DU38: 0.029116871 | DV38: 0.033685179 | DW38: 0.03347998 | DX38: 0.024312283 | DY38: 0.01582143 | DZ38: 0.025054769 | EA38: 0.047286547 | EB38: 0.038599922 | EC38: 0.044871824 | ED38: 0.033779756 | EE38: 0.050013167 | EF38: 0.041715118 | EG38: 0.06494011 | EH38: 0.066543945 | EI38: 0.055557075 | EJ38: 0.02623771 | EK38: 0.033397422 | EL38: 0.031424835 | EM38: 0.05425458 | EN38: 0.070390398 | EO38: 0.09123886 | EP38: 0.078075213 | EQ38: 0.061196712 | ER38: 0.057970591 | ES38: 0.071718046 | ET38: 0.075028854 | EU38: 0.067387877 | EV38: 0.038391842 | EW38: 0.061568395 | EX38: 0.055775411 | EY38: 0.048514896 | EZ38: 0.06247849 | FA38: 0.10076982 | FB38: 0.073053983 | FC38: 0.058840435 | FD38: 0.068818228 | FE38: 0.080718461 | FF38: 0.081432915 | FG38: 0.065137215 | FH38: 0.030738804 | FI38: 0.032447651 | FJ38: 0.037188962 | FL38: 0 | FM38: 0 | FN38: 0.001101545 | FO38: 0.0070481263 | FP38: 0.019705791 | FQ38: 0.017734627 | FR38: 0.020009758 | FS38: 0.02098014 | FT38: 0.024728038 | FU38: 0.030646622 | FV38: 0.045313448 | FW38: 0.064491246 | FX38: =C38 -> 0.061878988
B39: Solar Fotovoltaica | C39: 0.024492101 | D39: 0.017404124 | E39: 0.70879763 | F39: 0 | H39: 0.0089319618 | I39: 0.84721624 | L39: 0 | M39: 0 | N39: 0 | O39: 0 | P39: 0 | Q39: 0 | R39: 0 | S39: 0 | T39: 0 | U39: 0 | V39: 0 | W39: 0 | X39: 0 | Y39: 0 | Z39: 0 | AA39: 0 | AB39: 0 | AC39: 0 | AD39: 0 | AE39: 0 | AF39: 0 | AG39: 0 | AH39: 0 | AI39: 0 | AJ39: 0 | AK39: 0 | AL39: 0 | AM39: 0 | AN39: 0 | AO39: 0 | AP39: 0 | AQ39: 0 | AR39: 0 | AS39: 0 | AT39: 0 | AU39: 0 | AV39: 0 | AW39: 0 | AX39: 0 | AY39: 0 | AZ39: 0 | BA39: 0 | BB39: 0 | BC39: 0 | BD39: 0 | BE39: 0 | BF39: 0 | BG39: 0 | BH39: 0 | BI39: 0 | BJ39: 0 | BK39: 0 | BL39: 0 | BM39: 0 | BN39: 0 | BO39: 0 | BP39: 0 | BQ39: 0 | BR39: 0 | BS39: 0 | BT39: 0 | BU39: 0 | BV39: 0 | BW39: 0 | BX39: 0 | BY39: 0 | BZ39: 0 | CA39: 0 | CB39: 0 | CC39: 0 | CD39: 0 | CE39: 0 | CF39: 0 | CG39: 0 | CH39: 0 | CI39: 0 | CJ39: 0 | CK39: 0 | CL39: 0 | CM39: 0 | CN39: 0 | CO39: 0 | CP39: 0 | CQ39: 0 | CR39: 0 | CS39: 0 | CT39: 0 | CU39: 0 | CV39: 0 | CW39: 0.00069878318 | CX39: 0.0032110861 | CY39: 0.0019717501 | CZ39: 0.0034025492 | DA39: 0.003089223 | DB39: 0.0027840413 | DC39: 0.0031736965 | DD39: 0.0037563689 | DE39: 0.0035473664 | DF39: 0.0037784253 | DG39: 0.003283404 | DH39: 0.0033076315 | DI39: 0.0033423856 | DJ39: 0.0017449187 | DK39: 0.0032383119 | DL39: 0.0031084656 | DM39: 0.0026678653 | DN39: 0.0025358894 | DO39: 0.0030615972 | DP39: 0.0029143963 | DQ39: 0.003754079 | DR39: 0.0039002963 | DS39: 0.0033744476 | DT39: 0.0029986779 | DU39: 0.0029458562 | DV39: 0.0030747008 | DW39: 0.0034484231 | DX39: 0.00906074 | DY39: 0.0088944952 | DZ39: 0.0084620754 | EA39: 0.0091168212 | EB39: 0.0093726009 | EC39: 0.0094640252 | ED39: 0.01001962 | EE39: 0.010230209 | EF39: 0.0089114586 | EG39: 0.0092426934 | EH39: 0.008924638 | EI39: 0.0087345953 | EJ39: 0.0078232595 | EK39: 0.008187377 | EL39: 0.0077270901 | EM39: 0.011689941 | EN39: 0.017352093 | EO39: 0.01827289 | EP39: 0.020417884 | EQ39: 0.022139944 | ER39: 0.018853345 | ES39: 0.017107976 | ET39: 0.016071908 | EU39: 0.016580335 | EV39: 0.01587551 | EW39: 0.015796491 | EX39: 0.014382294 | EY39: 0.015802317 | EZ39: 0.017204674 | FA39: 0.018151601 | FB39: 0.020356771 | FC39: 0.0225154 | FD39: 0.021310358 | FE39: 0.020500701 | FF39: 0.024166481 | FG39: 0.031305009 | FH39: 0.032251864 | FI39: 0.027753571 | FJ39: 0.030098103 | FL39: 0 | FM39: 0 | FN39: 0 | FO39: 0 | FP39: 0 | FQ39: 0 | FR39: 0 | FS39: 0.0015737511 | FT39: 0.0030928192 | FU39: 0.0051955512 | FV39: 0.0091639575 | FW39: 0.017272505 | FX39: =C39 -> 0.024492101
B40: Biomasa | C40: 0.010532405 | D40: 0.0091632859 | E40: 0.13691192 | F40: 0 | H40: 0.011796984 | I40: -0.26336978 | L40: 0 | M40: 0 | N40: 0 | O40: 0 | P40: 0 | Q40: 0 | R40: 0 | S40: 0 | T40: 0 | U40: 0 | V40: 0 | W40: 0 | X40: 0 | Y40: 0 | Z40: 0 | AA40: 0 | AB40: 0 | AC40: 0 | AD40: 0 | AE40: 0 | AF40: 0 | AG40: 0 | AH40: 0 | AI40: 0 | AJ40: 0 | AK40: 0 | AL40: 0 | AM40: 0 | AN40: 0 | AO40: 0 | AP40: 0 | AQ40: 0 | AR40: 0 | AS40: 0 | AT40: 0 | AU40: 0 | AV40: 0 | AW40: 0 | AX40: 0 | AY40: 0 | AZ40: 0 | BA40: 0 | BB40: 0 | BC40: 0 | BD40: 0 | BE40: 0 | BF40: 0 | BG40: 0 | BH40: 0 | BI40: 0 | BJ40: 0 | BK40: 0 | BL40: 0 | BM40: 0 | BN40: 0 | BO40: 0 | BP40: 0 | BQ40: 0 | BR40: 0 | BS40: 0 | BT40: 0 | BU40: 0 | BV40: 0 | BW40: 0 | BX40: 0 | BY40: 0 | BZ40: 0 | CA40: 0 | CB40: 0 | CC40: 0 | CD40: 0 | CE40: 0 | CF40: 0 | CG40: 0 | CH40: 0 | CI40: 0 | CJ40: 0 | CK40: 0 | CL40: 0 | CM40: 0 | CN40: 0 | CO40: 0 | CP40: 0 | CQ40: 0 | CR40: 0 | CS40: 0 | CT40: 0 | CU40: 0 | CV40: 0 | CW40: 0 | CX40: 0 | CY40: 0 | CZ40: 0 | DA40: 0 | DB40: 0 | DC40: 0 | DD40: 0 | DE40: 0.0004430464 | DF40: 0.0046032305 | DG40: 0.01105644 | DH40: 0.010867546 | DI40: 0.011891187 | DJ40: 0.0085078343 | DK40: 0.012302815 | DL40: 0.012492321 | DM40: 0.013940951 | DN40: 0.0043768725 | DO40: 0.014016506 | DP40: 0.013169364 | DQ40: 0.015852546 | DR40: 0.015091796 | DS40: 0.014116996 | DT40: 0.014047742 | DU40: 0.013737677 | DV40: 0.013253081 | DW40: 0.013779045 | DX40: 0.014120198 | DY40: 0.01164248 | DZ40: 0.0016167044 | EA40: 0.014438448 | EB40: 0.014888677 | EC40: 0.014516092 | ED40: 0.014319018 | EE40: 0.013791272 | EF40: 0.0096171335 | EG40: 0.012776476 | EH40: 0.012410949 | EI40: 0.012490586 | EJ40: 0.012756567 | EK40: 0.013009718 | EL40: 0 | EM40: 0.012563106 | EN40: 0.014023367 | EO40: 0.007388284 | EP40: 0.0046545582 | EQ40: 0.010153413 | ER40: 0.0096424843 | ES40: 0.0088031768 | ET40: 0.0087582458 | EU40: 0.0014563181 | EV40: 0.0099459319 | EW40: 0.012522317 | EX40: 0.013638013 | EY40: 0.013164647 | EZ40: 0.012693205 | FA40: 0.012736735 | FB40: 0.012514203 | FC40: 0.012661116 | FD40: 0.011963787 | FE40: 0.011636912 | FF40: 0.010782499 | FG40: 0.011309943 | FH40: 0.0094679201 | FI40: 0.0075564142 | FJ40: 0.0038599959 | FL40: 0 | FM40: 0 | FN40: 0 | FO40: 0 | FP40: 0 | FQ40: 0 | FR40: 0 | FS40: 0 | FT40: 0.0089675616 | FU40: 0.01284538 | FV40: 0.011861428 | FW40: 0.0094920738 | FX40: =C40 -> 0.010532405
B41: Total Renovable No Convencional | C41: 0.096903494 | D41: 0.092488942 | E41: 0.44145522 | F41: 0 | H41: 0.065221207 | I41: 2.7267735 | L41: 0 | M41: 0 | N41: 0 | O41: 0 | P41: 0 | Q41: 0 | R41: 0 | S41: 0 | T41: 0 | U41: 0 | V41: 0 | W41: 0 | X41: 0 | Y41: 0 | Z41: 0 | AA41: 0 | AB41: 0 | AC41: 0 | AD41: 0 | AE41: 0 | AF41: 0 | AG41: 0 | AH41: 0 | AI41: 0 | AJ41: 0 | AK41: 0 | AL41: 0 | AM41: 0 | AN41: 0 | AO41: 0 | AP41: 0 | AQ41: 0 | AR41: 0.000270156 | AS41: 0.0030271159 | AT41: 0.0027948735 | AU41: 0.006996551 | AV41: 0.0090702832 | AW41: 0.0081582278 | AX41: 0.011007717 | AY41: 0.0059502612 | AZ41: 0.0067801774 | BA41: 0.0073757427 | BB41: 0.010391096 | BC41: 0.0078239236 | BD41: 0.0032647723 | BE41: 0.0030752015 | BF41: 0.0024033368 | BG41: 0.010297379 | BH41: 0.029166526 | BI41: 0.022264044 | BJ41: 0.016034382 | BK41: 0.023687301 | BL41: 0.01798225 | BM41: 0.027718409 | BN41: 0.021648401 | BO41: 0.020279048 | BP41: 0.0077694796 | BQ41: 0.0093713803 | BR41: 0.013077512 | BS41: 0.032123876 | BT41: 0.028079549 | BU41: 0.023022943 | BV41: 0.013970852 | BW41: 0.020052829 | BX41: 0.01688142 | BY41: 0.019697391 | BZ41: 0.021398875 | CA41: 0.017689494 | CB41: 0.015344194 | CC41: 0.0054173279 | CD41: 0.01476351 | CE41: 0.01882558 | CF41: 0.01883086 | CG41: 0.018127113 | CH41: 0.024600814 | CI41: 0.021046517 | CJ41: 0.022569686 | CK41: 0.02440223 | CL41: 0.02454759 | CM41: 0.018521273 | CN41: 0.010644228 | CO41: 0.0081849477 | CP41: 0.019380513 | CQ41: 0.030254417 | CR41: 0.011656923 | CS41: 0.010885 | CT41: 0.019961099 | CU41: 0.008434918 | CV41: 0.017696866 | CW41: 0.028386938 | CX41: 0.041277784 | CY41: 0.034787763 | CZ41: 0.025221197 | DA41: 0.013342201 | DB41: 0.014238496 | DC41: 0.039725797 | DD41: 0.029211349 | DE41: 0.025647809 | DF41: 0.037710238 | DG41: 0.043216428 | DH41: 0.042934953 | DI41: 0.05073423 | DJ41: 0.041385502 | DK41: 0.042545353 | DL41: 0.026601203 | DM41: 0.033198016 | DN41: 0.021591755 | DO41: 0.043903556 | DP41: 0.05222386 | DQ41: 0.068677877 | DR41: 0.040330514 | DS41: 0.039936638 | DT41: 0.050258068 | DU41: 0.045800404 | DV41: 0.050012961 | DW41: 0.050707448 | DX41: 0.04749322 | DY41: 0.036358406 | DZ41: 0.035133548 | EA41: 0.070841816 | EB41: 0.062861201 | EC41: 0.068851941 | ED41: 0.058118394 | EE41: 0.074034648 | EF41: 0.06024371 | EG41: 0.086959279 | EH41: 0.087879532 | EI41: 0.076782256 | EJ41: 0.046817537 | EK41: 0.054594517 | EL41: 0.039151925 | EM41: 0.078507627 | EN41: 0.10176586 | EO41: 0.11690003 | EP41: 0.10314766 | EQ41: 0.093490069 | ER41: 0.08646642 | ES41: 0.097629199 | ET41: 0.099859008 | EU41: 0.085424529 | EV41: 0.064213284 | EW41: 0.089887204 | EX41: 0.083795718 | EY41: 0.07748186 | EZ41: 0.092376369 | FA41: 0.13165815 | FB41: 0.10592496 | FC41: 0.094016951 | FD41: 0.10209237 | FE41: 0.11285607 | FF41: 0.1163819 | FG41: 0.10775217 | FH41: 0.072458588 | FI41: 0.067757636 | FJ41: 0.07114706 | FL41: 0 | FM41: 0 | FN41: 0.001101545 | FO41: 0.0070481263 | FP41: 0.019705791 | FQ41: 0.017734627 | FR41: 0.020009758 | FS41: 0.022553891 | FT41: 0.036788419 | FU41: 0.048687554 | FV41: 0.066338833 | FW41: 0.091255825 | FX41: =C41 -> 0.096903494
B43: Precios del Mercado Eléctrico Mayorista (MEM)
A44: 15 | B44: Costos Marginal de Energía (USCents$/KWh) | C44: 9.0633405 | D44: 7.0346239 | E44: 2.0287166 | F44: 0.2883902 | H44: 12.509377 | I44: -5.4747533 | J44: -0.43765195 | L44: 7.9245495 | M44: 8.6266106 | N44: 8.6378394 | O44: 8.8904297 | P44: 9.906276 | Q44: 10.949903 | R44: 13.177938 | S44: 13.09247 | T44: 14.600774 | U44: 14.429834 | V44: 14.973757 | W44: 13.844561 | X44: 13.174537 | Y44: 15.449075 | Z44: 14.883535 | AA44: 13.699424 | AB44: 14.45171 | AC44: 13.372964 | AD44: 12.976667 | AE44: 13.997889 | AF44: 14.318403 | AG44: 13.466344 | AH44: 12.222222 | AI44: 12.577739 | AJ44: 14.003714 | AK44: 14.773475 | AL44: 17.949337 | AM44: 19.576941 | AN44: 21.067168 | AO44: 19.847934 | AP44: 20.679638 | AQ44: 20.127082 | AR44: 18.573206 | AS44: 19.932755 | AT44: 18.832264 | AU44: 17.926375 | AV44: 17.975452 | AW44: 19.309404 | AX44: 20.3684 | AY44: 19.459919 | AZ44: 19.793537 | BA44: 20.300364 | BB44: 18.747265 | BC44: 18.371773 | BD44: 20.474183 | BE44: 20.651811 | BF44: 19.916763 | BG44: 18.466076 | BH44: 20.03405 | BI44: 20.541655 | BJ44: 20.996154 | BK44: 21.013036 | BL44: 19.868672 | BM44: 18.092015 | BN44: 18.124001 | BO44: 20.079411 | BP44: 19.474028 | BQ44: 16.407948 | BR44: 15.806024 | BS44: 13.828953 | BT44: 13.563038 | BU44: 14.759674 | BV44: 14.845532 | BW44: 16.487608 | BX44: 15.671862 | BY44: 17.125315 | BZ44: 18.839467 | CA44: 17.179941 | CB44: 17.080219 | CC44: 17.215195 | CD44: 14.600243 | CE44: 10.791554 | CF44: 10.653611 | CG44: 9.6048813 | CH44: 10.052844 | CI44: 9.981478 | CJ44: 10.821933 | CK44: 11.267917 | CL44: 11.29677 | CM44: 10.011077 | CN44: 8.54424 | CO44: 8.7250029 | CP44: 7.4365255 | CQ44: 6.5499557 | CR44: 5.0884589 | CS44: 5.4846771 | CT44: 6.053258 | CU44: 7.0185032 | CV44: 6.4710663 | CW44: 7.7205344 | CX44: 9.1673803 | CY44: 7.6505277 | CZ44: 8.169673 | DA44: 7.6868668 | DB44: 7.413196 | DC44: 7.3360228 | DD44: 9.1541279 | DE44: 9.8500004 | DF44: 9.3752588 | DG44: 8.4297268 | DH44: 8.4481026 | DI44: 9.0821085 | DJ44: 8.9445783 | DK44: 8.9375247 | DL44: 8.8482693 | DM44: 9.3811869 | DN44: 9.387404 | DO44: 10.360223 | DP44: 9.6041706 | DQ44: 8.9896452 | DR44: 10.835728 | DS44: 11.259784 | DT44: 12.040638 | DU44: 13.64675 | DV44: 13.819051 | DW44: 13.3 | DX44: 14.527209 | DY44: 14.34043 | DZ44: 15.430476 | EA44: 12.792712 | EB44: 11.113099 | EC44: 12.613269 | ED44: 14.561553 | EE44: 13.46601 | EF44: 14.293399 | EG44: 14.187234 | EH44: 12.199562 | EI44: 12.502071 | EJ44: 11.536687 | EK44: 10.869611 | EL44: 10.260655 | EM44: 7.7434655 | EN44: 7.306201 | EO44: 8.116842 | EP44: 7.4382885 | EQ44: 7.0563907 | ER44: 3.9458448 | ES44: 5.6951275 | ET44: 7.6090742 | EU44: 8.9852521 | EV44: 10.481442 | EW44: 6.062 | EX44: 4.6844 | EY44: 4.2617339 | EZ44: 7.7426358 | FA44: 7.9947396 | FB44: 7.3814439 | FC44: 7.9190528 | FD44: 7.8730672 | FE44: 7.7139861 | FF44: 8.2592984 | FG44: 9.0990605 | FH44: 12.694 | FI44: 11.546461 | FJ44: 11.473 | FL44: 11.587912 | FM44: 13.715876 | FN44: 18.607491 | FO44: 19.486246 | FP44: 18.688829 | FQ44: 15.679971 | FR44: 9.578853 | FS44: 7.1050137 | FT44: 9.1832092 | FU44: 12.548883 | FV44: 12.112218 | FW44: 6.8035497 | FX44: =C44 -> 9.0633405
A45: 16 | B45: Costos Marginal de Potencia (US$/kW-Mes) | C45: 9.5654141 | D45: 9.3485111 | E45: 0.216903 | F45: 0.023201876 | H45: 9.2304123 | I45: 0.11809878 | J45: 0.01279453 | L45: 7.7440878 | M45: 7.752381 | N45: 7.8172404 | O45: 7.8345424 | P45: 7.8542072 | Q45: 7.8765569 | R45: 7.9448448 | S45: 7.9327243 | T45: 7.9505115 | U45: 7.9549724 | V45: 7.9629834 | W45: 7.9679735 | X45: 7.9549848 | Y45: 7.980679 | Z45: 7.9829295 | AA45: 8.0156464 | AB45: 8.0303694 | AC45: 8.0369164 | AD45: 8.0281843 | AE45: 8.0308525 | AF45: 8.0420939 | AG45: 8.0465805 | AH45: 8.0551539 | AI45: 8.0605411 | AJ45: 8.0108753 | AK45: 8.0798408 | AL45: 8.1527851 | AM45: 8.2208135 | AN45: 8.221519 | AO45: 8.2211108 | AP45: 8.2206499 | AQ45: 8.2210581 | AR45: 8.2197486 | AS45: 8.2203035 | AT45: 8.2207128 | AU45: 8.2206786 | AV45: 8.2003365 | AW45: 8.236623 | AX45: 8.2727005 | AY45: 8.3356138 | AZ45: 8.3612656 | BA45: 8.358254 | BB45: 8.3386698 | BC45: 8.2700248 | BD45: 8.3713525 | BE45: 8.3851401 | BF45: 8.3773936 | BG45: 8.3659821 | BH45: 8.3396576 | BI45: 8.3623317 | BJ45: 8.436037 | BK45: 8.4567619 | BL45: 8.4517964 | BM45: 8.4670043 | BN45: 8.4703345 | BO45: 8.4884434 | BP45: 8.4954902 | BQ45: 8.519351 | BR45: 8.5066821 | BS45: 8.4780917 | BT45: 8.4631036 | BU45: 8.4921305 | BV45: 8.5262778 | BW45: 8.5946974 | BX45: 8.619859 | BY45: 8.6420038 | BZ45: 8.6352743 | CA45: 8.6361144 | CB45: 8.6396553 | CC45: 8.629009 | CD45: 8.618952 | CE45: 8.5761382 | CF45: 8.519986 | CG45: 8.467199 | CH45: 8.5282287 | CI45: 8.5911836 | CJ45: 8.6025276 | CK45: 8.6422699 | CL45: 8.6716521 | CM45: 8.6648705 | CN45: 8.657533 | CO45: 8.641211 | CP45: 8.6340294 | CQ45: 8.621585 | CR45: 8.5910781 | CS45: 8.6018327 | CT45: 8.6106547 | CU45: 8.650979 | CV45: 8.6929595 | CW45: 8.7294705 | CX45: 8.7584919 | CY45: 8.749481 | CZ45: 8.7589575 | DA45: 8.7648661 | DB45: 8.7832749 | DC45: 8.7783524 | DD45: 8.7823107 | DE45: 8.83572 | DF45: 8.8449399 | DG45: 8.8552546 | DH45: 8.8831523 | DI45: 8.8905192 | DJ45: 8.8967799 | DK45: 8.8915385 | DL45: 8.9107019 | DM45: 8.9277574 | DN45: 8.9272983 | DO45: 8.9306214 | DP45: 8.9175253 | DQ45: 8.9709442 | DR45: 9.0254516 | DS45: 9.0751323 | DT45: 9.0977756 | DU45: 9.1358824 | DV45: 9.1436134 | DW45: 9.15 | DX45: 9.134947 | DY45: 9.1403051 | DZ45: 9.1368568 | EA45: 9.1366669 | EB45: 9.0951449 | EC45: 9.1123979 | ED45: 9.1509133 | EE45: 9.2025836 | EF45: 9.2513798 | EG45: 9.2711158 | EH45: 9.2729081 | EI45: 9.2883494 | EJ45: 9.287813 | EK45: 9.2951368 | EL45: 9.3067927 | EM45: 9.3066549 | EN45: 9.2982171 | EO45: 9.3342967 | EP45: 9.3598374 | EQ45: 9.3395222 | ER45: 9.2770954 | ES45: 9.2771247 | ET45: 9.3279468 | EU45: 9.375194 | EV45: 9.4047583 | EW45: 9.4178633 | EX45: 9.421766 | EY45: 9.4158814 | EZ45: 9.4247155 | FA45: 9.4648519 | FB45: 9.5165758 | FC45: 9.5840864 | FD45: 9.6042103 | FE45: 9.6042238 | FF45: 9.6041773 | FG45: 9.6041477 | FH45: 9.6042341 | FI45: 9.6041586 | FJ45: 9.6041735 | FL45: 7.8827521 | FM45: 8.0220776 | FN45: 8.1858413 | FO45: 8.3227797 | FP45: 8.4559985 | FQ45: 8.5894346 | FR45: 8.603523 | FS45: 8.7058665 | FT45: 8.8813829 | FU45: 9.0887584 | FV45: 9.2367658 | FW45: 9.3541253 | FX45: =C45 -> 9.5654141
A46: 17 | B46: Peaje de Transmisión (USCents$/KWh) | C46: 0.69175292 | D46: 0.70880306 | E46: -0.017050138 | F46: -0.024054831 | H46: 0.69173735 | I46: 0.017065707 | J46: 0.024670791 | L46: 0.67582598 | M46: 0.67308151 | N46: 0.67123667 | O46: 0.66834124 | P46: 0.69217948 | Q46: 0.69425738 | R46: 0.69241528 | S46: 0.69202428 | T46: 0.69208559 | U46: 0.69125698 | V46: 0.69171601 | W46: 0.69123978 | X46: 0.69007189 | Y46: 0.68838048 | Z46: 0.68738209 | AA46: 0.68524087 | AB46: 0.67911834 | AC46: 0.70618267 | AD46: 0.70518765 | AE46: 0.70324734 | AF46: 0.70153519 | AG46: 0.69504946 | AH46: 0.69683538 | AI46: 0.69540255 | AJ46: 0.71705943 | AK46: 0.71905484 | AL46: 0.71615055 | AM46: 0.71223644 | AN46: 0.71198894 | AO46: 0.7106657 | AP46: 0.70767624 | AQ46: 0.70690878 | AR46: 0.70722531 | AS46: 0.70625412 | AT46: 0.70347359 | AU46: 0.72671825 | AV46: 0.84476209 | AW46: 0.88017076 | AX46: 0.82030411 | AY46: 0.81749346 | AZ46: 0.71794788 | BA46: 0.72665061 | BB46: 0.6954576 | BC46: 0.71532633 | BD46: 0.72179884 | BE46: 0.70818483 | BF46: 0.74723921 | BG46: 0.76091845 | BH46: 0.84922006 | BI46: 0.92422309 | BJ46: 0.83154135 | BK46: 0.83261034 | BL46: 0.77360194 | BM46: 0.7985269 | BN46: 0.76952693 | BO46: 0.74945743 | BP46: 0.79229677 | BQ46: 0.81512465 | BR46: 0.88195058 | BS46: 0.8919699 | BT46: 0.92094315 | BU46: 1.1067256 | BV46: 0.87453025 | BW46: 0.88747141 | BX46: 0.85537714 | BY46: 0.83068816 | BZ46: 0.80095729 | CA46: 0.81144485 | CB46: 0.85083119 | CC46: 0.79787346 | CD46: 0.72743141 | CE46: 0.87613965 | CF46: 0.95782575 | CG46: 1.0382717 | CH46: 0.92028371 | CI46: 0.92279528 | CJ46: 0.87656854 | CK46: 0.87154424 | CL46: 0.83154777 | CM46: 0.83218374 | CN46: 0.85344689 | CO46: 0.82330213 | CP46: 0.91936018 | CQ46: 0.89886015 | CR46: 0.77815083 | CS46: 0.80400251 | CT46: 0.73526895 | CU46: 0.72584427 | CV46: 0.67568967 | CW46: 0.70025971 | CX46: 0.66707932 | CY46: 0.66744032 | CZ46: 0.68559311 | DA46: 0.69336994 | DB46: 0.74547169 | DC46: 0.72780407 | DD46: 0.75845652 | DE46: 0.81959469 | DF46: 0.73176241 | DG46: 0.74469748 | DH46: 0.6817962 | DI46: 0.68761258 | DJ46: 0.66200825 | DK46: 0.64020756 | DL46: 0.68445315 | DM46: 0.64613408 | DN46: 0.71743467 | DO46: 0.71848683 | DP46: 0.74911924 | DQ46: 0.85192097 | DR46: 0.73028943 | DS46: 0.84497863 | DT46: 0.68753784 | DU46: 0.67701679 | DV46: 0.64586077 | DW46: 0.672 | DX46: 0.71255525 | DY46: 0.6974855 | DZ46: 0.71301437 | EA46: 0.71388564 | EB46: 0.77007411 | EC46: 0.82477955 | ED46: 0.73027409 | EE46: 0.73278447 | EF46: 0.67219354 | EG46: 0.67684811 | EH46: 0.63192593 | EI46: 0.62561581 | EJ46: 0.64599969 | EK46: 0.62791432 | EL46: 0.67070127 | EM46: 0.66007339 | EN46: 0.75272822 | EO46: 0.78712905 | EP46: 0.80036143 | EQ46: 0.8116995 | ER46: 0.71722408 | ES46: 0.65566834 | ET46: 0.62382414 | EU46: 0.63529078 | EV46: 0.67312313 | EW46: 0.63808623 | EX46: 0.70169876 | EY46: 0.71717069 | EZ46: 0.78008801 | FA46: 0.81986016 | FB46: 0.72568111 | FC46: 0.72687822 | FD46: 0.6707501 | FE46: 0.68675451 | FF46: 0.63213662 | FG46: 0.64683068 | FH46: 0.63317561 | FI46: 0.6220847 | FJ46: 0.66504243 | FL46: 0.68547168 | FM46: 0.69446949 | FN46: 0.71211768 | FO46: 0.76302118 | FP46: 0.82583749 | FQ46: 0.86170113 | FR46: 0.89549917 | FS46: 0.71716453 | FT46: 0.70772037 | FU46: 0.7246387 | FV46: 0.68909869 | FW46: 0.70950036 | FX46: =C46 -> 0.69175292
A47: 18 | B47: Derecho de Conexión Unitario (US$/kW-mes) | C47: 3.006274 | D47: 3.3587284 | E47: -0.35245437 | F47: -0.10493685 | H47: 3.1148155 | I47: 0.2439129 | J47: 0.078307333 | L47: 3.1393581 | M47: 2.7420168 | N47: 3.1376994 | O47: 3.2619978 | P47: 3.163288 | Q47: 3.5386106 | R47: 3.5365854 | S47: 3.3067553 | T47: 3.5529444 | U47: 3.1259669 | V47: 2.8867403 | W47: 3.2178355 | X47: 2.7931511 | Y47: 2.6168921 | Z47: 3.1919053 | AA47: 3.1899533 | AB47: 3.4870041 | AC47: 3.5399023 | AD47: 3.6105691 | AE47: 3.9177267 | AF47: 3.5272531 | AG47: 3.6012386 | AH47: 3.3247421 | AI47: 3.0287152 | AJ47: 2.4657799 | AK47: 2.464167 | AL47: 3.135809 | AM47: 3.0530351 | AN47: 2.8111814 | AO47: 3.1287181 | AP47: 2.567086 | AQ47: 2.8085385 | AR47: 3.1760084 | AS47: 3.1318835 | AT47: 3.0835411 | AU47: 3.1729933 | AV47: 3.9230363 | AW47: 3.2363845 | AX47: 1.3505031 | AY47: 1.7497597 | AZ47: 3.7308944 | BA47: 4.1074934 | BB47: 3.280995 | BC47: 3.0787869 | BD47: 2.9353558 | BE47: 2.1714927 | BF47: 0.46825751 | BG47: 2.5283925 | BH47: 3.0027965 | BI47: 3.3510745 | BJ47: 3.8313058 | BK47: 3.7878914 | BL47: 4.3050648 | BM47: 4.3409609 | BN47: 4.2623592 | BO47: 4.341184 | BP47: 4.4118166 | BQ47: 4.400726 | BR47: 4.1021965 | BS47: 4.1964916 | BT47: 4.2220992 | BU47: 4.4615568 | BV47: 4.5234044 | BW47: 4.0560437 | BX47: 3.946848 | BY47: 3.9819681 | BZ47: 3.9862918 | CA47: 3.7767667 | CB47: 3.6699133 | CC47: 3.7228209 | CD47: 3.8041488 | CE47: 4.0854119 | CF47: 4.5346811 | CG47: 4.5027245 | CH47: 4.3660982 | CI47: 4.1996712 | CJ47: 4.1422159 | CK47: 4.1459166 | CL47: 4.0482756 | CM47: 4.1305607 | CN47: 4.2699747 | CO47: 4.2285259 | CP47: 4.3860316 | CQ47: 4.5658497 | CR47: 3.5620155 | CS47: 3.5782398 | CT47: 3.5076859 | CU47: 3.4759188 | CV47: 3.6033364 | CW47: 3.3880223 | CX47: 3.1982026 | CY47: 3.3196326 | CZ47: 3.3329269 | DA47: 3.2991047 | DB47: 3.2199272 | DC47: 3.267516 | DD47: 3.3281936 | DE47: 3.245283 | DF47: 3.2211602 | DG47: 3.2733639 | DH47: 3.2093219 | DI47: 3.2654436 | DJ47: 3.1757837 | DK47: 3.2262419 | DL47: 3.2599981 | DM47: 3.1728858 | DN47: 3.1299671 | DO47: 3.1047063 | DP47: 3.1561354 | DQ47: 3.0724298 | DR47: 3.0719919 | DS47: 3.0796915 | DT47: 2.8750169 | DU47: 2.8685809 | DV47: 2.7132026 | DW47: 3.06 | DX47: 3.4022768 | DY47: 3.3339724 | DZ47: 3.1863297 | EA47: 3.1613956 | EB47: 3.4575625 | EC47: 3.2657093 | ED47: 3.1038197 | EE47: 3.4050944 | EF47: 3.403643 | EG47: 3.0501327 | EH47: 2.9560787 | EI47: 2.9317203 | EJ47: 3.349252 | EK47: 2.4198135 | EL47: 2.9201447 | EM47: 3.2730831 | EN47: 3.5245121 | EO47: 3.5871588 | EP47: 3.6572767 | EQ47: 3.6377948 | ER47: 2.9146275 | ES47: 3.2030716 | ET47: 3.281148 | EU47: 3.1908713 | EV47: 3.1165504 | EW47: 3.3570249 | EX47: 3.4759765 | EY47: 3.5925038 | EZ47: 3.3820559 | FA47: 3.3227876 | FB47: 3.3496733 | FC47: 3.325082 | FD47: 3.2768395 | FE47: 3.388348 | FF47: 3.138955 | FG47: 1.6752149 | FH47: 2.6760858 | FI47: 2.7991079 | FJ47: 2.7348646 | FL47: 3.2174832 | FM47: 3.3190877 | FN47: 2.9165618 | FO47: 2.713446 | FP47: 4.0278223 | FQ47: 4.0197728 | FR47: 4.2933771 | FS47: 3.3960441 | FT47: 3.2176958 | FU47: 3.081752 | FV47: 3.1280045 | FW47: 3.3782097 | FX47: =C47 -> 3.006274
A49: 2 | B49: Tasa de Cambio (RD$/US$) | C49: 57.226664 | D49: 56.361727 | E49: 0.8649368 | F49: 0.015346173 | H49: 51.148009 | I49: 5.2137182 | J49: 0.10193394 | L49: 35.5121 | M49: 35.6569 | N49: 35.7549 | O49: 35.9098 | P49: 36.1178 | Q49: 36.0097 | R49: 36.1055 | S49: 36.1259 | T49: 36.1227 | U49: 36.166 | V49: 36.142 | W49: 36.1669 | X49: 36.216 | Y49: 36.3128 | Z49: 36.3661 | AA49: 36.5518 | AB49: 36.8053 | AC49: 36.8148 | AD49: 36.868 | AE49: 36.9695 | AF49: 37.0484 | AG49: 37.4186 | AH49: 37.3091 | AI49: 37.3869 | AJ49: 37.5429 | AK49: 37.8866 | AL49: 37.8665 | AM49: 37.9069 | AN49: 37.9739 | AO49: 38.1212 | AP49: 38.1106 | AQ49: 38.132 | AR49: 38.2137 | AS49: 38.3697 | AT49: 38.5145 | AU49: 38.6275 | AV49: 38.9468 | AW49: 39.0235 | AX49: 39.0686 | AY49: 39.0844 | AZ49: 39.0942 | BA49: 39.1366 | BB49: 39.1507 | BC49: 39.1785 | BD49: 39.2913 | BE49: 39.5269 | BF49: 40.0477 | BG49: 40.2946 | BH49: 40.7133 | BI49: 40.848474 | BJ49: 41.095358 | BK49: 41.1457 | BL49: 41.1834 | BM49: 41.5959 | BN49: 42.0115 | BO49: 42.4939 | BP49: 42.706 | BQ49: 42.5153 | BR49: 42.5256 | BS49: 42.6996 | BT49: 42.9692 | BU49: 43.1817 | BV49: 43.2189 | BW49: 43.2036 | BX49: 43.283305 | BY49: 43.4811 | BZ49: 43.5749 | CA49: 43.6016 | CB49: 43.765167 | CC49: 43.9085 | CD49: 44.1474 | CE49: 44.260732 | CF49: 44.607922 | CG49: 44.8817 | CH49: 44.7524 | CI49: 44.797124 | CJ49: 44.865095 | CK49: 44.9149 | CL49: 45.0605 | CM49: 45.1433 | CN49: 45.2282 | CO49: 45.3339 | CP49: 45.4333 | CQ49: 45.5277 | CR49: 45.6154 | CS49: 45.7642 | CT49: 45.8094 | CU49: 45.8535 | CV49: 45.901 | CW49: 45.954127 | CX49: 45.9945 | CY49: 46.0061 | CZ49: 46.1746 | DA49: 46.4371 | DB49: 46.5893 | DC49: 46.6741 | DD49: 46.7828 | DE49: 47.1285 | DF49: 47.3172 | DG49: 47.396111 | DH49: 47.4402 | DI49: 47.5046 | DJ49: 47.5375 | DK49: 47.581205 | DL49: 47.7206 | DM49: 47.8314 | DN49: 47.973524 | DO49: 48.19887 | DP49: 48.4247 | DQ49: 48.8367 | DR49: 49.202914 | DS49: 49.3807 | DT49: 49.4018 | DU49: 49.4161 | DV49: 49.5841 | DW49: 49.7276 | DX49: 49.8208 | DY49: 49.977 | DZ49: 50.1375 | EA49: 50.21 | EB49: 50.3761 | EC49: 50.4897 | ED49: 50.5432 | EE49: 50.5524 | EF49: 50.5647 | EG49: 50.7277 | EH49: 50.9213 | EI49: 51.1756 | EJ49: 51.6597 | EK49: 52.7486 | EL49: 52.8691 | EM49: 52.9102 | EN49: 53.1086 | EO49: 53.3702 | EP49: 53.7389 | EQ49: 54.2019 | ER49: 55.3914 | ES49: 57.9353 | ET49: 58.3452 | EU49: 58.4827 | EV49: 58.4714 | EW49: 58.4858 | EX49: 58.4476 | EY49: 58.3154 | EZ49: 58.3065 | FA49: 58.0968 | FB49: 57.4518 | FC49: 57.0965 | FD49: 57.040229 | FE49: 57.1258 | FF49: 57.1956 | FG49: 57.185376 | FH49: 56.759 | FI49: 56.5141 | FJ49: 56.7216 | FL49: 35.982517 | FM49: 36.838942 | FN49: 38.1055 | FO49: 39.320317 | FP49: 41.794503 | FQ49: 43.549675 | FR49: 45.045503 | FS49: 46.064444 | FT49: 47.534376 | FU49: 49.509993 | FV49: 51.294858 | FW49: 56.524533 | FX49: =C49 -> 57.226664

Sheet EDE's
B2: Ministerio de Energía y Minas
B3: Variables Relevantes
B4: Valores según indicación
C6: Ene21-Nov21 | D6: Ene20-Nov20 | E6: Comparación 2020 - 2021 | H6: Ene19-Nov19 | I6: Comparación 2019 - 2020 | K6: 0 | FL6: Acumulado Año
E7: D | F7: D% | I7: D | J7: D% | K7: 0 | L7: 39814 | M7: 39845 | N7: 39873 | O7: 39904 | P7: 39934 | Q7: 39965 | R7: 39995 | S7: 40026 | T7: 40057 | U7: 40087 | V7: 40118 | W7: 40148 | X7: 40179 | Y7: 40210 | Z7: 40238 | AA7: 40269 | AB7: 40299 | AC7: 40330 | AD7: 40360 | AE7: 40391 | AF7: 40422 | AG7: 40452 | AH7: 40483 | AI7: 40513 | AJ7: 40544 | AK7: 40575 | AL7: 40603 | AM7: 40634 | AN7: 40664 | AO7: 40695 | AP7: 40725 | AQ7: 40756 | AR7: 40787 | AS7: 40817 | AT7: 40848 | AU7: 40878 | AV7: 40909 | AW7: 40940 | AX7: 40969 | AY7: 41000 | AZ7: 41030 | BA7: 41061 | BB7: 41091 | BC7: 41122 | BD7: 41153 | BE7: 41183 | BF7: 41214 | BG7: 41244 | BH7: 41275 | BI7: 41306 | BJ7: 41334 | BK7: 41365 | BL7: 41395 | BM7: 41426 | BN7: 41456 | BO7: 41487 | BP7: 41518 | BQ7: 41548 | BR7: 41579 | BS7: 41609 | BT7: 41640 | BU7: 41671 | BV7: 41699 | BW7: 41730 | BX7: 41760 | BY7: 41791 | BZ7: 41821 | CA7: 41852 | CB7: 41883 | CC7: 41913 | CD7: 41944 | CE7: 41974 | CF7: 42005 | CG7: 42036 | CH7: 42064 | CI7: 42095 | CJ7: 42125 | CK7: 42156 | CL7: 42186 | CM7: 42217 | CN7: 42248 | CO7: 42278 | CP7: 42309 | CQ7: 42339 | CR7: 42370 | CS7: 42401 | CT7: 42430 | CU7: 42461 | CV7: 42491 | CW7: 42522 | CX7: 42552 | CY7: 42583 | CZ7: 42614 | DA7: 42644 | DB7: 42675 | DC7: 42705 | DD7: 42736 | DE7: 42767 | DF7: 42795 | DG7: 42826 | DH7: 42856 | DI7: 42887 | DJ7: 42917 | DK7: 42948 | DL7: 42979 | DM7: 43009 | DN7: 43040 | DO7: 43070 | DP7: 43101 | DQ7: 43132 | DR7: 43160 | DS7: 43191 | DT7: 43221 | DU7: 43252 | DV7: 43282 | DW7: 43313 | DX7: 43344 | DY7: 43374 | DZ7: 43405 | EA7: 43435 | EB7: 43466 | EC7: 43497 | ED7: 43525 | EE7: 43556 | EF7: 43586 | EG7: 43617 | EH7: 43647 | EI7: 43678 | EJ7: 43709 | EK7: 43739 | EL7: 43770 | EM7: 43800 | EN7: 43831 | EO7: 43862 | EP7: 43891 | EQ7: 43922 | ER7: 43952 | ES7: 43983 | ET7: 44013 | EU7: 44044 | EV7: 44075 | EW7: 44105 | EX7: 44136 | EY7: 44166 | EZ7: 44197 | FA7: 44228 | FB7: 44256 | FC7: 44287 | FD7: 44317 | FE7: 44348 | FF7: 44378 | FG7: 44409 | FH7: 44440 | FI7: 44470 | FJ7: 44501 | FL7: 2009 | FM7: 2010 | FN7: 2011 | FO7: 2012 | FP7: 2013 | FQ7: 2014 | FR7: 2015 | FS7: 2016 | FT7: 2017 | FU7: 2018 | FV7: 2019 | FW7: 2020 | FX7: 2021
B8: Compra de Energía (GWh) | C8: 15248.795 | D8: 14394.332 | E8: 854.46361 | F8: 0.059361116 | H8: 13916.914 | I8: 477.41772 | J8: 0.034304855 | K8: 0 | L8: 813.6184 | M8: 718.4309 | N8: 782.3334 | O8: 804.42306 | P8: 824.32473 | Q8: 862.31327 | R8: 915.31752 | S8: 915.03675 | T8: 879.43775 | U8: 934.2931 | V8: 860.01969 | W8: 916.21936 | X8: 851.67804 | Y8: 789.28446 | Z8: 907.26565 | AA8: 908.04466 | AB8: 976.49324 | AC8: 932.02198 | AD8: 993.41448 | AE8: 1019.8664 | AF8: 955.59047 | AG8: 990.73878 | AH8: 877.43408 | AI8: 889.91158 | AJ8: 885.54911 | AK8: 812.2319 | AL8: 905.26379 | AM8: 888.63663 | AN8: 941.93879 | AO8: 957.98535 | AP8: 978.25126 | AQ8: 987.55255 | AR8: 969.05726 | AS8: 990.71267 | AT8: 913.12603 | AU8: 892.43749 | AV8: 862.17354 | AW8: 826.66425 | AX8: 887.70501 | AY8: 901.67513 | AZ8: 1038.6988 | BA8: 1023.9082 | BB8: 1056.4329 | BC8: 1018.8305 | BD8: 1018.5314 | BE8: 1014.6423 | BF8: 955.31138 | BG8: 943.56299 | BH8: 925.82343 | BI8: 854.96249 | BJ8: 951.53986 | BK8: 956.83117 | BL8: 1015.7876 | BM8: 998.44833 | BN8: 1045.0327 | BO8: 1076.0451 | BP8: 1054.9716 | BQ8: 1077.0579 | BR8: 1000.7603 | BS8: 992.72217 | BT8: 963.29343 | BU8: 878.3467 | BV8: 1021.8083 | BW8: 1012.2906 | BX8: 1052.4454 | BY8: 1068.6895 | BZ8: 1122.6442 | CA8: 1101.7673 | CB8: 1047.0778 | CC8: 1118.9937 | CD8: 1022.7042 | CE8: 1017.9316 | CF8: 1005.9643 | CG8: 918.76728 | CH8: 1039.1093 | CI8: 1048.8547 | CJ8: 1107.2267 | CK8: 1121.0647 | CL8: 1180.7876 | CM8: 1178.6717 | CN8: 1148.127 | CO8: 1186.0396 | CP8: 1057.8317 | CQ8: 1085.2536 | CR8: 1044.5518 | CS8: 1002.0041 | CT8: 1097.5885 | CU8: 1114.7064 | CV8: 1196.0718 | CW8: 1157.3178 | CX8: 1213.2143 | CY8: 1204.9507 | CZ8: 1185.7198 | DA8: 1169.3347 | DB8: 1064.3608 | DC8: 1095.8116 | DD8: 1017.0488 | DE8: 966.62696 | DF8: 1091.3105 | DG8: 1074.7002 | DH8: 1181.8402 | DI8: 1194.5464 | DJ8: 1244.0969 | DK8: 1282.3836 | DL8: 1188.6316 | DM8: 1227.8168 | DN8: 1133.8748 | DO8: 1145.6407 | DP8: 1092.7074 | DQ8: 963.09965 | DR8: 1133.5896 | DS8: 1172.5103 | DT8: 1219.6311 | DU8: 1243.9196 | DV8: 1304.7974 | DW8: 1297.2034 | DX8: 1211.1842 | DY8: 1237.0658 | DZ8: 1215.1143 | EA8: 1212.6758 | EB8: 1184.8441 | EC8: 1097.8735 | ED8: 1190.1194 | EE8: 1179.707 | EF8: 1287.2689 | EG8: 1291.422 | EH8: 1367.9217 | EI8: 1388.6371 | EJ8: 1341.5493 | EK8: 1349.9966 | EL8: 1237.5745 | EM8: 1233.2515 | EN8: 1183.4041 | EO8: 1147.7128 | EP8: 1170.9938 | EQ8: 1198.8587 | ER8: 1327.7419 | ES8: 1399.4136 | ET8: 1463.7112 | EU8: 1425.7586 | EV8: 1392.8751 | EW8: 1427.8614 | EX8: 1256.0007 | EY8: 1283.0376 | EZ8: 1231.5055 | FA8: 1162.8159 | FB8: 1294.2581 | FC8: 1297.6897 | FD8: 1435.0528 | FE8: 1388.0156 | FF8: 1500.4978 | FG8: 1496.5522 | FH8: 1527.8898 | FI8: 1490.681 | FJ8: 1423.8372 | FL8: 10225.768 | FM8: 11091.744 | FN8: 11122.743 | FO8: 11548.136 | FP8: 11949.983 | FQ8: 12427.993 | FR8: 13077.698 | FS8: 13545.632 | FT8: 13748.517 | FU8: 14303.499 | FV8: 15150.166 | FW8: 15677.369 | FX8: ='EDE''s'!C8 -> 15248.795
B9: Edenorte | C9: 4584.0478 | D9: 4264.9126 | E9: 319.13516 | F9: 0.074828064 | H9: 4074.0772 | I9: 190.83538 | J9: 0.046841375 | K9: 0 | L9: 255.27 | M9: 224.04 | N9: 243.44 | O9: 254.23315 | P9: 259.335 | Q9: 268.48378 | R9: 291.383 | S9: 289.679 | T9: 277.07642 | U9: 296.70463 | V9: 265.31993 | W9: 278.135 | X9: 260.0712 | Y9: 241.65768 | Z9: 273.42556 | AA9: 271.53912 | AB9: 292.55084 | AC9: 287.69953 | AD9: 309.50188 | AE9: 313.26548 | AF9: 295.35423 | AG9: 306.95871 | AH9: 262.91327 | AI9: 273.22174 | AJ9: 271.53928 | AK9: 249.37535 | AL9: 275.65613 | AM9: 273.01633 | AN9: 286.36758 | AO9: 298.02177 | AP9: 309.38498 | AQ9: 309.43379 | AR9: 296.57661 | AS9: 303.14338 | AT9: 277.65941 | AU9: 268.91463 | AV9: 259.39429 | AW9: 248.73462 | AX9: 270.00205 | AY9: 273.02206 | AZ9: 316.46337 | BA9: 310.21297 | BB9: 325.95455 | BC9: 319.44844 | BD9: 315.46409 | BE9: 320.1231 | BF9: 292.53265 | BG9: 291.46524 | BH9: 285.68851 | BI9: 263.25707 | BJ9: 291.34109 | BK9: 294.81881 | BL9: 311.63305 | BM9: 308.85941 | BN9: 323.21701 | BO9: 336.92088 | BP9: 322.94346 | BQ9: 334.09695 | BR9: 314.03168 | BS9: 305.78787 | BT9: 291.54494 | BU9: 265.4057 | BV9: 309.01 | BW9: 308.83548 | BX9: 317.0415 | BY9: 325.32571 | BZ9: 347.64987 | CA9: 346.69529 | CB9: 322.67236 | CC9: 338.71832 | CD9: 309.74793 | CE9: 306.62232 | CF9: 304.19752 | CG9: 275.4296 | CH9: 312.6 | CI9: 326.59696 | CJ9: 341.28 | CK9: 336.42192 | CL9: 357.49346 | CM9: 359.93307 | CN9: 347.62953 | CO9: 356.48215 | CP9: 321.11442 | CQ9: 325.07587 | CR9: 314.28978 | CS9: 296.35618 | CT9: 327.86826 | CU9: 333.1 | CV9: 358.96278 | CW9: 350.41828 | CX9: 371.80657 | CY9: 369.26301 | CZ9: 358.45105 | DA9: 353.34983 | DB9: 311.03879 | DC9: 325.04767 | DD9: 302.25394 | DE9: 290.15321 | DF9: 317.30911 | DG9: 318.32706 | DH9: 346.9328 | DI9: 354.86207 | DJ9: 372.35844 | DK9: 380.74418 | DL9: 353.51388 | DM9: 366.34735 | DN9: 334.94889 | DO9: 336.46658 | DP9: 320.40367 | DQ9: 277.89411 | DR9: 328.74045 | DS9: 343.02013 | DT9: 360.26 | DU9: 369.63676 | DV9: 392.15061 | DW9: 392.86846 | DX9: 367.81643 | DY9: 368.07918 | DZ9: 358.12705 | EA9: 351.90631 | EB9: 336.47368 | EC9: 307.76637 | ED9: 352.68431 | EE9: 352.38305 | EF9: 379.74832 | EG9: 379.09582 | EH9: 408.72406 | EI9: 412.37 | EJ9: 389.50654 | EK9: 393.38605 | EL9: 361.93903 | EM9: 358.55247 | EN9: 344.41882 | EO9: 332.68159 | EP9: 336.26605 | EQ9: 356.08974 | ER9: 393.37115 | ES9: 410.04441 | ET9: 435.60142 | EU9: 433.27814 | EV9: 416.43352 | EW9: 427.88183 | EX9: 378.84595 | EY9: 375.60393 | EZ9: 366.3823 | FA9: 339.15916 | FB9: 382.98426 | FC9: 391.49011 | FD9: 431.08496 | FE9: 421.49508 | FF9: 457.60808 | FG9: 464.06672 | FH9: 458.30983 | FI9: 447.39718 | FJ9: 424.0701 | FL9: 3203.0999 | FM9: 3388.1592 | FN9: 3419.0892 | FO9: 3542.8174 | FP9: 3692.5958 | FQ9: 3789.2694 | FR9: 3964.2545 | FS9: 4069.9522 | FT9: 4074.2175 | FU9: 4230.9031 | FV9: 4432.6297 | FW9: 4640.5165 | FX9: ='EDE''s'!C9 -> 4584.0478
B10: Edesur | C10: 5338.0474 | D10: 5096.2994 | E10: 241.748 | F10: 0.047435989 | H10: 5005.6652 | I10: 90.634191 | J10: 0.018106323 | K10: 0 | L10: 316.7084 | M10: 281.5109 | N10: 302.7334 | O10: 309.843 | P10: 316.094 | Q10: 329.22295 | R10: 345.628 | S10: 345.524 | T10: 336.436 | U10: 353.57933 | V10: 323.49604 | W10: 341.15 | X10: 317.63 | Y10: 298.906 | Z10: 338.231 | AA10: 340.293 | AB10: 365.512 | AC10: 341.318 | AD10: 366.655 | AE10: 374.929 | AF10: 355.029 | AG10: 367.61 | AH10: 332.464 | AI10: 330.91 | AJ10: 328.54981 | AK10: 307.81779 | AL10: 340.30771 | AM10: 330.44124 | AN10: 348.93491 | AO10: 354.22123 | AP10: 360.68389 | AQ10: 363.17098 | AR10: 361.60016 | AS10: 373.98987 | AT10: 347.74329 | AU10: 338.35163 | AV10: 323.07806 | AW10: 314.04277 | AX10: 334.50399 | AY10: 333.68861 | AZ10: 383.02861 | BA10: 374.42175 | BB10: 387.92089 | BC10: 372.26841 | BD10: 374.74776 | BE10: 371.38505 | BF10: 351.92343 | BG10: 343.61184 | BH10: 337.8827 | BI10: 312.13226 | BJ10: 352.56099 | BK10: 352.57913 | BL10: 374.48365 | BM10: 366.54898 | BN10: 382.36985 | BO10: 390.80054 | BP10: 387.43542 | BQ10: 395.88791 | BR10: 364.27009 | BS10: 363.1077 | BT10: 355.41344 | BU10: 326.14088 | BV10: 373.32002 | BW10: 370.17014 | BX10: 386.4969 | BY10: 391.3279 | BZ10: 402.40868 | CA10: 391.56204 | CB10: 377.34784 | CC10: 405.7793 | CD10: 367.88979 | CE10: 366.66828 | CF10: 357.88598 | CG10: 331.23838 | CH10: 375.86391 | CI10: 371.4126 | CJ10: 392.92467 | CK10: 403.75986 | CL10: 423.55285 | CM10: 422.16484 | CN10: 413.97181 | CO10: 430.04002 | CP10: 379.05676 | CQ10: 389.31845 | CR10: 377.13294 | CS10: 366.2944 | CT10: 396.47918 | CU10: 399.28974 | CV10: 439.08157 | CW10: 430.87874 | CX10: 443.01825 | CY10: 440.34258 | CZ10: 440.36378 | DA10: 433.74815 | DB10: 401.25249 | DC10: 406.97865 | DD10: 372.86486 | DE10: 354.08026 | DF10: 398.57727 | DG10: 385.05748 | DH10: 426.30242 | DI10: 433.78461 | DJ10: 454.42237 | DK10: 471.82004 | DL10: 441.01755 | DM10: 449.52402 | DN10: 409.47583 | DO10: 409.58123 | DP10: 391.2107 | DQ10: 343.19465 | DR10: 404.00167 | DS10: 415.22621 | DT10: 431.08793 | DU10: 440.80662 | DV10: 460.37033 | DW10: 459.08273 | DX10: 425.46703 | DY10: 439.93926 | DZ10: 422.8548 | EA10: 419.98358 | EB10: 405.20628 | EC10: 382.80026 | ED10: 429.70944 | EE10: 419.96159 | EF10: 460.26284 | EG10: 467.81819 | EH10: 498.83506 | EI10: 504.24632 | EJ10: 482.05533 | EK10: 496.2485 | EL10: 458.52143 | EM10: 450.72144 | EN10: 430.88297 | EO10: 420.65779 | EP10: 426.15325 | EQ10: 420.36636 | ER10: 464.63698 | ES10: 495.35018 | ET10: 516.85507 | EU10: 497.75285 | EV10: 487.30087 | EW10: 497.75459 | EX10: 438.58852 | EY10: 452.21545 | EZ10: 426.56404 | FA10: 410.97924 | FB10: 455.15799 | FC10: 451.49493 | FD10: 502.52744 | FE10: 485.9205 | FF10: 521.12573 | FG10: 521.08592 | FH10: 537.50306 | FI10: 522.14685 | FJ10: 503.54173 | FL10: 3901.926 | FM10: 4129.487 | FN10: 4155.8125 | FO10: 4264.6212 | FP10: 4380.0592 | FQ10: 4514.5252 | FR10: 4691.1901 | FS10: 4974.8605 | FT10: 5006.5079 | FU10: 5053.2255 | FV10: 5456.3867 | FW10: 5548.5149 | FX10: ='EDE''s'!C10 -> 5338.0474
B11: Edeeste | C11: 5326.7003 | D11: 5033.1198 | E11: 293.58045 | F11: 0.058329716 | H11: 4837.1717 | I11: 195.94814 | J11: 0.040508826 | K11: 0 | L11: 241.64 | M11: 212.88 | N11: 236.16 | O11: 240.3469 | P11: 248.89573 | Q11: 264.60654 | R11: 278.30652 | S11: 279.83375 | T11: 265.92533 | U11: 284.00914 | V11: 271.20372 | W11: 296.93436 | X11: 273.97684 | Y11: 248.72078 | Z11: 295.60909 | AA11: 296.21254 | AB11: 318.4304 | AC11: 303.00445 | AD11: 317.2576 | AE11: 331.67191 | AF11: 305.20724 | AG11: 316.17007 | AH11: 282.05682 | AI11: 285.77984 | AJ11: 285.46002 | AK11: 255.03877 | AL11: 289.29995 | AM11: 285.17906 | AN11: 306.6363 | AO11: 305.74236 | AP11: 308.18239 | AQ11: 314.94777 | AR11: 310.88049 | AS11: 313.57942 | AT11: 287.72332 | AU11: 285.17123 | AV11: 279.70119 | AW11: 263.88686 | AX11: 283.19896 | AY11: 294.96446 | AZ11: 339.20682 | BA11: 339.27349 | BB11: 342.5575 | BC11: 327.11367 | BD11: 328.31951 | BE11: 323.13418 | BF11: 310.85529 | BG11: 308.4859 | BH11: 302.25223 | BI11: 279.57317 | BJ11: 307.63778 | BK11: 309.43323 | BL11: 329.67087 | BM11: 323.03994 | BN11: 339.44583 | BO11: 348.32367 | BP11: 344.59276 | BQ11: 347.07302 | BR11: 322.45855 | BS11: 323.8266 | BT11: 316.33506 | BU11: 286.80012 | BV11: 339.47824 | BW11: 333.285 | BX11: 348.90696 | BY11: 352.03591 | BZ11: 372.58561 | CA11: 363.50992 | CB11: 347.05761 | CC11: 374.49612 | CD11: 345.0665 | CE11: 344.64101 | CF11: 343.88085 | CG11: 312.0993 | CH11: 350.64541 | CI11: 350.84511 | CJ11: 373.02207 | CK11: 380.88294 | CL11: 399.74132 | CM11: 396.57375 | CN11: 386.52561 | CO11: 399.51748 | CP11: 357.66056 | CQ11: 370.85931 | CR11: 353.12909 | CS11: 339.35352 | CT11: 373.24103 | CU11: 382.31664 | CV11: 398.02748 | CW11: 376.02074 | CX11: 398.38951 | CY11: 395.34514 | CZ11: 386.90496 | DA11: 382.23675 | DB11: 352.06951 | DC11: 363.78526 | DD11: 341.92999 | DE11: 322.39348 | DF11: 375.42417 | DG11: 371.31566 | DH11: 408.60498 | DI11: 405.89968 | DJ11: 417.31607 | DK11: 429.81938 | DL11: 394.10021 | DM11: 411.94541 | DN11: 389.45007 | DO11: 399.59292 | DP11: 381.09301 | DQ11: 342.01089 | DR11: 400.84748 | DS11: 414.26397 | DT11: 428.28313 | DU11: 433.47618 | DV11: 452.27645 | DW11: 445.25225 | DX11: 417.90078 | DY11: 429.0474 | DZ11: 434.1325 | EA11: 440.78588 | EB11: 443.16412 | EC11: 407.3069 | ED11: 407.7257 | EE11: 407.36231 | EF11: 447.25777 | EG11: 444.508 | EH11: 460.36259 | EI11: 472.02076 | EJ11: 469.98747 | EK11: 460.36203 | EL11: 417.11404 | EM11: 423.97758 | EN11: 408.10228 | EO11: 394.37337 | EP11: 408.57452 | EQ11: 422.40265 | ER11: 469.73377 | ES11: 494.01896 | ET11: 511.25476 | EU11: 494.72763 | EV11: 489.14073 | EW11: 502.22495 | EX11: 438.5662 | EY11: 455.21819 | EZ11: 438.55914 | FA11: 412.67748 | FB11: 456.11587 | FC11: 454.70467 | FD11: 501.44043 | FE11: 480.6 | FF11: 521.76398 | FG11: 511.39953 | FH11: 532.07691 | FI11: 521.13692 | FJ11: 496.22533 | FL11: 3120.742 | FM11: 3574.0976 | FN11: 3547.8411 | FO11: 3740.6978 | FP11: 3877.3276 | FQ11: 4124.1981 | FR11: 4422.2537 | FS11: 4500.8196 | FT11: 4667.792 | FU11: 5019.3699 | FV11: 5261.1493 | FW11: 5488.338 | FX11: ='EDE''s'!C11 -> 5326.7003
B13: Precio Medio de Compra de Energía (USCents/kWh) | C13: 12.400565 | D13: 10.868991 | E13: 1.5315733 | F13: 0.14091218 | H13: 13.057747 | I13: -2.1887561 | J13: -0.16762126 | K13: 0 | L13: 13.180205 | M13: 12.757373 | N13: 11.325232 | O13: 11.60305 | P13: 11.289497 | Q13: 11.921498 | R13: 12.408819 | S13: 13.270596 | T13: 13.649989 | U13: 13.357094 | V13: 15.073853 | W13: 13.57786 | X13: 14.593761 | Y13: 15.297829 | Z13: 14.592946 | AA13: 14.091344 | AB13: 14.161289 | AC13: 14.180911 | AD13: 14.099071 | AE13: 14.378274 | AF13: 13.904998 | AG13: 13.74227 | AH13: 14.2266 | AI13: 14.373685 | AJ13: 15.250231 | AK13: 15.950725 | AL13: 17.245153 | AM13: 17.89486 | AN13: 18.644309 | AO13: 18.334718 | AP13: 18.954283 | AQ13: 19.090342 | AR13: 18.530853 | AS13: 18.515668 | AT13: 18.246215 | AU13: 18.101649 | AV13: 18.25801 | AW13: 18.544924 | AX13: 18.563297 | AY13: 18.672551 | AZ13: 18.463073 | BA13: 18.193979 | BB13: 16.589108 | BC13: 16.300449 | BD13: 17.425894 | BE13: 17.452062 | BF13: 17.253923 | BG13: 17.071149 | BH13: 17.086907 | BI13: 17.896414 | BJ13: 18.151675 | BK13: 17.582711 | BL13: 16.530776 | BM13: 15.668568 | BN13: 15.429751 | BO13: 16.232516 | BP13: 16.281883 | BQ13: 16.047667 | BR13: 16.026728 | BS13: 15.50819 | BT13: 16.328329 | BU13: 16.643145 | BV13: 16.806425 | BW13: 16.748701 | BX13: 16.545278 | BY13: 16.902848 | BZ13: 17.388775 | CA13: 16.666717 | CB13: 16.623028 | CC13: 16.240644 | CD13: 15.978906 | CE13: 13.496325 | CF13: 13.172417 | CG13: 12.786693 | CH13: 12.819683 | CI13: 12.474514 | CJ13: 12.801322 | CK13: 13.467993 | CL13: 13.117379 | CM13: 12.204941 | CN13: 11.505256 | CO13: 11.531583 | CP13: 11.272207 | CQ13: 10.60199 | CR13: 9.4157784 | CS13: 9.6696043 | CT13: 9.4125976 | CU13: 9.901989 | CV13: 9.9008377 | CW13: 10.67165 | CX13: 10.869078 | CY13: 10.646554 | CZ13: 10.884059 | DA13: 10.816384 | DB13: 11.314961 | DC13: 10.931885 | DD13: 12.30853 | DE13: 12.791464 | DF13: 11.91693 | DG13: 11.547092 | DH13: 11.268893 | DI13: 11.42549 | DJ13: 11.117948 | DK13: 11.053031 | DL13: 11.162613 | DM13: 11.354907 | DN13: 11.551849 | DO13: 11.912046 | DP13: 11.760808 | DQ13: 11.607745 | DR13: 12.242333 | DS13: 12.147188 | DT13: 12.795171 | DU13: 13.584398 | DV13: 13.853753 | DW13: 13.906172 | DX13: 14.478084 | DY13: 14.227172 | DZ13: 14.940706 | EA13: 13.759757 | EB13: 13.202162 | EC13: 14.097734 | ED13: 14.235747 | EE13: 13.881767 | EF13: 13.736405 | EG13: 13.825648 | EH13: 12.568977 | EI13: 12.690605 | EJ13: 12.180461 | EK13: 11.77924 | EL13: 11.869203 | EM13: 10.938818 | EN13: 10.768379 | EO13: 11.484356 | EP13: 11.093421 | EQ13: 10.746383 | ER13: 9.980829 | ES13: 10.332649 | ET13: 10.596946 | EU13: 11.02313 | EV13: 11.109222 | EW13: 10.918624 | EX13: 11.664973 | EY13: 11.739026 | EZ13: 11.738365 | FA13: 12.09391 | FB13: 11.647892 | FC13: 12.039242 | FD13: 11.877773 | FE13: 12.073433 | FF13: 12.13334 | FG13: 12.574678 | FH13: 13.048284 | FI13: 13.013172 | FJ13: 13.845232 | FL13: 12.816451 | FM13: 14.283681 | FN13: 17.946271 | FO13: 17.697532 | FP13: 16.497003 | FQ13: 16.373914 | FR13: 12.300884 | FS13: 10.385401 | FT13: 11.581269 | FU13: 13.335629 | FV13: 12.885263 | FW13: 10.940195 | FX13: ='EDE''s'!C13 -> 12.400565
B14: Edenorte | C14: 12.573596 | D14: 11.542742 | E14: 1.0308544 | F14: 0.089307583 | H14: 13.412178 | I14: -1.8694363 | J14: -0.13938349 | K14: 0 | L14: 12.160784 | M14: 12.344826 | N14: 12.047705 | O14: 11.789233 | P14: 11.864737 | Q14: 12.264101 | R14: 12.732098 | S14: 14.126224 | T14: 14.962474 | U14: 14.325238 | V14: 16.707444 | W14: 14.516675 | X14: 15.408388 | Y14: 15.95149 | Z14: 15.468403 | AA14: 15.215207 | AB14: 15.263002 | AC14: 15.086485 | AD14: 15.158723 | AE14: 15.280015 | AF14: 14.871939 | AG14: 14.782388 | AH14: 15.474709 | AI14: 15.534366 | AJ14: 16.494716 | AK14: 17.142756 | AL14: 19.10134 | AM14: 19.958689 | AN14: 20.643655 | AO14: 20.074999 | AP14: 20.772462 | AQ14: 21.130048 | AR14: 20.847071 | AS14: 20.796133 | AT14: 20.783142 | AU14: 20.707703 | AV14: 20.576751 | AW14: 21.336453 | AX14: 21.460206 | AY14: 21.929381 | AZ14: 21.346645 | BA14: 20.746947 | BB14: 18.644151 | BC14: 18.67539 | BD14: 19.878309 | BE14: 19.800246 | BF14: 19.489263 | BG14: 19.113141 | BH14: 19.18057 | BI14: 20.177969 | BJ14: 20.459014 | BK14: 19.726214 | BL14: 18.147606 | BM14: 17.089003 | BN14: 16.873337 | BO14: 17.987388 | BP14: 18.029319 | BQ14: 17.479837 | BR14: 17.556536 | BS14: 16.839402 | BT14: 17.902388 | BU14: 18.289791 | BV14: 18.732428 | BW14: 18.635395 | BX14: 18.359418 | BY14: 18.908434 | BZ14: 19.5468 | CA14: 18.605054 | CB14: 18.635843 | CC14: 18.226513 | CD14: 16.813009 | CE14: 14.314767 | CF14: 14.208502 | CG14: 13.914765 | CH14: 14.347637 | CI14: 13.536119 | CJ14: 14.117608 | CK14: 15.030118 | CL14: 14.635231 | CM14: 13.37371 | CN14: 12.573373 | CO14: 12.733777 | CP14: 12.200282 | CQ14: 11.372445 | CR14: 9.6150801 | CS14: 10.134696 | CT14: 9.850465 | CU14: 10.713037 | CV14: 10.440033 | CW14: 11.514165 | CX14: 11.83137 | CY14: 11.175575 | CZ14: 11.609449 | DA14: 11.297542 | DB14: 12.079421 | DC14: 11.305351 | DD14: 12.754349 | DE14: 13.311935 | DF14: 12.535783 | DG14: 12.134161 | DH14: 11.925749 | DI14: 12.04031 | DJ14: 11.745934 | DK14: 11.692137 | DL14: 11.813713 | DM14: 11.957771 | DN14: 12.239367 | DO14: 12.511805 | DP14: 12.322822 | DQ14: 12.352114 | DR14: 12.810949 | DS14: 12.660514 | DT14: 13.233827 | DU14: 13.953989 | DV14: 14.126517 | DW14: 14.137281 | DX14: 14.402484 | DY14: 14.388864 | DZ14: 14.913775 | EA14: 14.039394 | EB14: 13.684776 | EC14: 14.542041 | ED14: 14.365033 | EE14: 14.097901 | EF14: 13.78563 | EG14: 14.038113 | EH14: 12.909856 | EI14: 13.081363 | EJ14: 12.578493 | EK14: 12.401812 | EL14: 12.493966 | EM14: 11.978086 | EN14: 10.638114 | EO14: 12.239732 | EP14: 11.928276 | EQ14: 11.439594 | ER14: 11.227183 | ES14: 11.243166 | ET14: 11.154979 | EU14: 11.592839 | EV14: 11.55817 | EW14: 11.556686 | EX14: 12.515613 | EY14: 12.851019 | EZ14: 11.944614 | FA14: 12.503606 | FB14: 11.973583 | FC14: 12.200059 | FD14: 12.099448 | FE14: 12.220617 | FF14: 12.474227 | FG14: 13.021227 | FH14: 12.833651 | FI14: 13.007401 | FJ14: 13.7712 | FL14: 13.374011 | FM14: 15.27375 | FN14: 19.933406 | FO14: 20.19352 | FP14: 18.236614 | FQ14: 18.108798 | FR14: 13.497026 | FS14: 10.987103 | FT14: 12.188788 | FU14: 13.668423 | FV14: 13.296176 | FW14: 11.648634 | FX14: ='EDE''s'!C14 -> 12.573596
B15: Edesur | C15: 12.575269 | D15: 11.0004 | E15: 1.5748689 | F15: 0.14316469 | H15: 12.486053 | I15: -1.4856521 | J15: -0.11898493 | K15: 0 | L15: 12.106886 | M15: 13.283726 | N15: 11.463497 | O15: 12.117861 | P15: 11.98697 | Q15: 12.541867 | R15: 13.517495 | S15: 14.225323 | T15: 14.579438 | U15: 14.501586 | V15: 16.269042 | W15: 14.650743 | X15: 15.538373 | Y15: 16.002901 | Z15: 15.224377 | AA15: 14.890008 | AB15: 15.150246 | AC15: 14.917067 | AD15: 15.119007 | AE15: 15.170161 | AF15: 14.825411 | AG15: 14.767567 | AH15: 15.515405 | AI15: 15.646349 | AJ15: 16.478773 | AK15: 17.19707 | AL15: 18.649095 | AM15: 19.234332 | AN15: 20.102978 | AO15: 19.658209 | AP15: 20.538482 | AQ15: 20.576449 | AR15: 20.236158 | AS15: 20.243275 | AT15: 19.998974 | AU15: 19.778634 | AV15: 20.193453 | AW15: 20.539444 | AX15: 20.97578 | AY15: 21.10755 | AZ15: 20.744826 | BA15: 20.668901 | BB15: 18.731915 | BC15: 18.169347 | BD15: 19.703651 | BE15: 19.533036 | BF15: 19.274625 | BG15: 19.023938 | BH15: 18.521318 | BI15: 19.387935 | BJ15: 19.714663 | BK15: 18.996531 | BL15: 17.822301 | BM15: 16.879319 | BN15: 16.657502 | BO15: 17.727236 | BP15: 17.837255 | BQ15: 17.785898 | BR15: 17.636899 | BS15: 17.084793 | BT15: 17.721417 | BU15: 18.038988 | BV15: 17.982761 | BW15: 18.262266 | BX15: 18.011401 | BY15: 18.478677 | BZ15: 19.036323 | CA15: 18.251987 | CB15: 18.244312 | CC15: 17.707735 | CD15: 16.308815 | CE15: 14.112271 | CF15: 13.762377 | CG15: 13.370195 | CH15: 13.260409 | CI15: 13.209981 | CJ15: 13.693628 | CK15: 14.442599 | CL15: 14.069334 | CM15: 12.937877 | CN15: 12.127939 | CO15: 12.182018 | CP15: 11.919578 | CQ15: 11.150127 | CR15: 10.113362 | CS15: 10.142982 | CT15: 10.028898 | CU15: 10.507834 | CV15: 10.602892 | CW15: 11.373687 | CX15: 11.520002 | CY15: 11.000539 | CZ15: 10.962818 | DA15: 11.040586 | DB15: 11.598296 | DC15: 11.129413 | DD15: 12.463399 | DE15: 13.093895 | DF15: 12.112798 | DG15: 11.786288 | DH15: 11.491144 | DI15: 11.560155 | DJ15: 11.175312 | DK15: 11.121974 | DL15: 11.201109 | DM15: 11.437708 | DN15: 11.642415 | DO15: 11.941322 | DP15: 11.644934 | DQ15: 11.493651 | DR15: 12.03476 | DS15: 11.92229 | DT15: 12.695786 | DU15: 13.195628 | DV15: 13.311788 | DW15: 13.361275 | DX15: 13.722333 | DY15: 13.54426 | DZ15: 14.006648 | EA15: 13.199029 | EB15: 12.879941 | EC15: 13.46078 | ED15: 13.493876 | EE15: 13.207023 | EF15: 13.041179 | EG15: 13.153607 | EH15: 12.025633 | EI15: 12.062724 | EJ15: 11.764586 | EK15: 11.296049 | EL15: 11.493903 | EM15: 10.692776 | EN15: 11.319962 | EO15: 11.506148 | EP15: 11.143381 | EQ15: 10.878269 | ER15: 10.28372 | ES15: 10.436642 | ET15: 10.656204 | EU15: 10.981345 | EV15: 11.164786 | EW15: 10.983851 | EX15: 11.838861 | EY15: 11.864389 | EZ15: 11.952384 | FA15: 12.283246 | FB15: 11.93325 | FC15: 12.225799 | FD15: 12.01575 | FE15: 12.25296 | FF15: 12.23935 | FG15: 12.817157 | FH15: 13.169159 | FI15: 13.15821 | FJ15: 13.963286 | FL15: 13.479948 | FM15: 15.213365 | FN15: 19.443462 | FO15: 19.862842 | FP15: 17.96703 | FQ15: 17.698239 | FR15: 13.002245 | FS15: 10.855551 | FT15: 11.710473 | FU15: 12.888382 | FV15: 12.33792 | FW15: 11.070817 | FX15: ='EDE''s'!C15 -> 12.575269
B16: Edeeste | C16: 12.07658 | D16: 10.165017 | E16: 1.9115634 | F16: 0.18805314 | H16: 13.350839 | I16: -3.1858222 | J16: -0.23862337 | K16: 0 | L16: 15.663885 | M16: 12.495504 | N16: 10.403245 | O16: 10.742443 | P16: 9.8043494 | Q16: 10.802011 | R16: 10.693491 | S16: 11.206018 | T16: 11.106572 | U16: 10.920827 | V16: 12.050062 | W16: 11.46584 | X16: 12.725363 | Y16: 13.815393 | Z16: 13.060714 | AA16: 12.143578 | AB16: 12.013936 | AC16: 12.491839 | AD16: 11.88658 | AE16: 12.631409 | AF16: 11.898612 | AG16: 11.540344 | AH16: 11.544072 | AI16: 11.790367 | AJ16: 12.652445 | AK16: 13.280894 | AL16: 13.82503 | AM16: 14.366986 | AN16: 15.117235 | AO16: 15.105036 | AP16: 15.274927 | AQ16: 15.372695 | AR16: 14.337682 | AS16: 14.25067 | AT16: 13.679633 | AU16: 13.654439 | AV16: 13.872018 | AW16: 13.540074 | AX16: 12.951848 | AY16: 12.903321 | AZ16: 13.19631 | BA16: 13.128366 | BB16: 12.2071 | BC16: 11.85428 | BD16: 12.469645 | BE16: 12.734052 | BF16: 12.862676 | BG16: 12.966678 | BH16: 13.504473 | BI16: 14.082789 | BJ16: 14.175337 | BK16: 13.929489 | BL16: 13.535324 | BM16: 12.936662 | BN16: 12.672177 | BO16: 12.858096 | BP16: 12.895484 | BQ16: 12.686332 | BR16: 12.717946 | BS16: 12.483284 | BT16: 13.312441 | BU16: 13.532022 | BV16: 13.759678 | BW16: 13.319339 | BX16: 13.272743 | BY16: 13.297719 | BZ16: 13.595755 | CA16: 13.110435 | CB16: 12.988853 | CC16: 12.854854 | CD16: 14.878445 | CE16: 12.112854 | CF16: 11.641909 | CG16: 11.171878 | CH16: 10.98509 | CI16: 10.707697 | CJ16: 10.657129 | CK16: 11.055074 | CL16: 10.751285 | CM16: 10.363925 | CN16: 9.8777267 | CO16: 9.7587601 | CP16: 9.7528649 | CQ16: 9.3512294 | CR16: 8.4933953 | CS16: 8.752483 | CT16: 8.3732875 | CU16: 8.5626077 | CV16: 8.6400958 | CW16: 9.0820415 | CX16: 9.2471535 | CY16: 9.7581589 | CZ16: 10.122373 | DA16: 10.117171 | DB16: 10.316677 | DC16: 10.377206 | DD16: 11.745561 | DE16: 11.990885 | DF16: 11.185927 | DG16: 10.795754 | DH16: 10.479301 | DI16: 10.744061 | DJ16: 10.49515 | DK16: 10.411217 | DL16: 10.535489 | DM16: 10.728421 | DN16: 10.865323 | DO16: 11.377027 | DP16: 11.407244 | DQ16: 11.11741 | DR16: 11.985208 | DS16: 11.947563 | DT16: 12.526222 | DU16: 13.664583 | DV16: 14.168915 | DW16: 14.264077 | DX16: 15.314058 | DY16: 14.788707 | DZ16: 15.872714 | EA16: 14.07077 | EB16: 13.130359 | EC16: 14.360639 | ED16: 14.905784 | EE16: 14.390418 | EF16: 14.410052 | EG16: 14.351732 | EH16: 12.855084 | EI16: 13.019975 | EJ16: 12.277142 | EK16: 11.7681 | EL16: 11.73964 | EM16: 10.321484 | EN16: 10.295944 | EO16: 10.823899 | EP16: 10.354208 | EQ16: 10.03075 | ER16: 8.637485 | ES16: 9.4726312 | ET16: 10.061581 | EU16: 10.566224 | EV16: 10.671651 | EW16: 10.310367 | EX16: 10.756269 | EY16: 10.696978 | EZ16: 11.357894 | FA16: 11.568645 | FB16: 11.089661 | FC16: 11.715543 | FD16: 11.548925 | FE16: 11.762836 | FF16: 11.728489 | FG16: 11.922388 | FH16: 13.111053 | FI16: 12.872809 | FJ16: 13.788705 | FL16: 11.414592 | FM16: 12.270969 | FN16: 14.277494 | FO16: 12.864995 | FP16: 13.179646 | FQ16: 13.330257 | FR16: 10.484609 | FS16: 9.3216325 | FT16: 10.912424 | FU16: 13.505375 | FV16: 13.106714 | FW16: 10.209139 | FX16: ='EDE''s'!C16 -> 12.07658
B18: Factura por Compra de Energía (US$ MM) | C18: 1890.9367 | D18: 1564.5187 | E18: 326.41805 | F18: 0.208638 | H18: 1817.2355 | I18: -252.71682 | J18: -0.13906663 | K18: 0 | L18: 107.23657 | M18: 91.652913 | N18: 88.60107 | O18: 93.337611 | P18: 93.062115 | Q18: 102.80066 | R18: 113.5801 | S18: 121.43083 | T18: 120.04315 | U18: 124.7944 | V18: 129.6381 | W18: 124.40298 | X18: 124.29186 | Y18: 120.74338 | Z18: 132.39679 | AA18: 127.95569 | AB18: 138.28403 | AC18: 132.16921 | AD18: 140.06221 | AE18: 146.63918 | AF18: 132.87483 | AG18: 136.15 | AH18: 124.82904 | AI18: 127.91309 | AJ18: 135.04828 | AK18: 129.55688 | AL18: 156.11413 | AM18: 159.02028 | AN18: 175.61797 | AO18: 175.64391 | AP18: 185.42051 | AQ18: 188.52716 | AR18: 179.57457 | AS18: 183.43707 | AT18: 166.61094 | AU18: 161.5459 | AV18: 157.41573 | AW18: 153.30426 | AX18: 164.78732 | AY18: 168.36575 | AZ18: 191.77571 | BA18: 186.28965 | BB18: 175.25281 | BC18: 166.07395 | BD18: 177.48819 | BE18: 177.07601 | BF18: 164.82869 | BG18: 161.07704 | BH18: 158.19459 | BI18: 153.00763 | BJ18: 172.72042 | BK18: 168.23686 | BL18: 167.91756 | BM18: 156.44255 | BN18: 161.24594 | BO18: 174.66919 | BP18: 171.76925 | BQ18: 172.84266 | BR18: 160.38913 | BS18: 153.95324 | BT18: 157.28972 | BU18: 146.18452 | BV18: 171.72943 | BW18: 169.54553 | BX18: 174.13001 | BY18: 180.63897 | BZ18: 195.21407 | CA18: 183.62843 | CB18: 174.05603 | CC18: 181.73179 | CD18: 163.41694 | CE18: 137.38336 | CF18: 132.50982 | CG18: 117.47995 | CH18: 133.21052 | CI18: 130.83952 | CJ18: 141.73966 | CK18: 150.98492 | CL18: 154.88839 | CM18: 143.85618 | CN18: 132.09495 | CO18: 136.76915 | CP18: 119.24098 | CQ18: 115.05848 | CR18: 98.352684 | CS18: 96.889832 | CT18: 103.31159 | CU18: 110.3781 | CV18: 118.42113 | CW18: 123.5049 | CX18: 131.86521 | CY18: 128.28573 | CZ18: 129.05444 | DA18: 126.47973 | DB18: 120.43201 | DC18: 119.79286 | DD18: 125.18375 | DE18: 123.64574 | DF18: 130.05071 | DG18: 124.09663 | DH18: 133.18031 | DI18: 136.48277 | DJ18: 138.31804 | DK18: 141.74226 | DL18: 132.68235 | DM18: 139.41746 | DN18: 130.98351 | DO18: 136.46925 | DP18: 128.51121 | DQ18: 111.79415 | DR18: 138.77781 | DS18: 142.42704 | DT18: 156.05388 | DU18: 168.97899 | DV18: 180.76341 | DW18: 180.39135 | DX18: 175.35627 | DY18: 175.99949 | DZ18: 181.54666 | EA18: 166.86123 | EB18: 156.42504 | EC18: 154.77529 | ED18: 169.42239 | EE18: 163.76418 | EF18: 176.82448 | EG18: 178.54746 | EH18: 171.93376 | EI18: 176.22644 | EJ18: 163.4069 | EK18: 159.01934 | EL18: 146.89023 | EM18: 134.90313 | EN18: 127.43344 | EO18: 131.80742 | EP18: 129.90328 | EQ18: 128.83396 | ER18: 132.51965 | ES18: 144.59649 | ET18: 155.10869 | EU18: 157.16322 | EV18: 154.73758 | EW18: 155.90282 | EX18: 146.51214 | EY18: 150.61612 | EZ18: 144.55861 | FA18: 140.62991 | FB18: 150.75379 | FC18: 156.23201 | FD18: 170.45232 | FE18: 167.58113 | FF18: 182.0605 | FG18: 188.18662 | FH18: 199.3634 | FI18: 193.98488 | FJ18: 197.13356 | FL18: 1310.5805 | FM18: 1584.3093 | FN18: 1996.1176 | FO18: 2043.7351 | FP18: 1971.389 | FQ18: 2034.9488 | FR18: 1608.6725 | FS18: 1406.7682 | FT18: 1592.2528 | FU18: 1907.4615 | FV18: 1952.1386 | FW18: 1715.1348 | FX18: ='EDE''s'!C18 -> 1890.9367
B19: Edenorte | C19: 576.37967 | D19: 492.28786 | E19: 84.091805 | F19: 0.17081836 | H19: 546.4225 | I19: -54.134641 | J19: -0.099071032 | K19: 0 | L19: 31.042833 | M19: 27.657347 | N19: 29.328933 | O19: 29.972139 | P19: 30.769415 | Q19: 32.927122 | R19: 37.099169 | S19: 40.920705 | T19: 41.457488 | U19: 42.503643 | V19: 44.328178 | W19: 40.375955 | X19: 40.072779 | Y19: 38.548 | Z19: 42.294568 | AA19: 41.315238 | AB19: 44.652039 | AC19: 43.403747 | AD19: 46.916533 | AE19: 47.867014 | AF19: 43.9249 | AG19: 45.375829 | AH19: 40.685061 | AI19: 42.443267 | AJ19: 44.789634 | AK19: 42.749808 | AL19: 52.654016 | AM19: 54.490481 | AN19: 59.116736 | AO19: 59.827867 | AP19: 64.266876 | AQ19: 65.383509 | AR19: 61.827537 | AS19: 63.042102 | AT19: 57.70635 | AU19: 55.686042 | AV19: 53.374917 | AW19: 53.071145 | AX19: 57.942998 | AY19: 59.872049 | AZ19: 67.554311 | BA19: 64.359721 | BB19: 60.771458 | BC19: 59.658244 | BD19: 62.708925 | BE19: 63.385162 | BF19: 57.012458 | BG19: 55.708164 | BH19: 54.796685 | BI19: 53.119929 | BJ19: 59.605515 | BK19: 58.156589 | BL19: 56.553937 | BM19: 52.780994 | BN19: 54.537495 | BO19: 60.603267 | BP19: 58.224505 | BQ19: 58.399604 | BR19: 55.133083 | BS19: 51.492847 | BT19: 52.193506 | BU19: 48.542148 | BV19: 57.885075 | BW19: 57.552712 | BX19: 58.206975 | BY19: 61.513997 | BZ19: 67.954424 | CA19: 64.502848 | CB19: 60.132714 | CC19: 61.736536 | CD19: 52.077948 | CE19: 43.892272 | CF19: 43.221909 | CG19: 38.325383 | CH19: 44.850712 | CI19: 44.208552 | CJ19: 48.180573 | CK19: 50.564611 | CL19: 52.319995 | CM19: 48.136406 | CN19: 43.708756 | CO19: 45.393642 | CP19: 39.176865 | CQ19: 36.969076 | CR19: 30.219214 | CS19: 30.034798 | CT19: 32.296548 | CU19: 35.685125 | CV19: 37.475831 | CW19: 40.347739 | CX19: 43.989811 | CY19: 41.267264 | CZ19: 41.614191 | DA19: 39.919846 | DB19: 37.571685 | DC19: 36.747781 | DD19: 38.550523 | DE19: 38.625006 | DF19: 39.777182 | DG19: 38.626319 | DH19: 41.374336 | DI19: 42.726492 | DJ19: 43.736977 | DK19: 44.517132 | DL19: 41.763115 | DM19: 43.806976 | DN19: 40.995624 | DO19: 42.098042 | DP19: 39.482774 | DQ19: 34.325798 | DR19: 42.114771 | DS19: 43.428112 | DT19: 47.676185 | DU19: 51.579071 | DV19: 55.397223 | DW19: 55.540916 | DX19: 52.974703 | DY19: 52.962412 | DZ19: 53.410261 | EA19: 49.405513 | EB19: 46.045667 | EC19: 44.755511 | ED19: 50.663218 | EE19: 49.678613 | EF19: 52.350699 | EG19: 53.217898 | EH19: 52.765688 | EI19: 53.943619 | EJ19: 48.994052 | EK19: 48.786997 | EL19: 45.220538 | EM19: 42.947724 | EN19: 36.639666 | EO19: 40.719335 | EP19: 40.110743 | EQ19: 40.735219 | ER19: 44.164501 | ES19: 46.101974 | ET19: 48.591245 | EU19: 50.229236 | EV19: 48.132092 | EW19: 49.448958 | EX19: 47.414893 | EY19: 48.268931 | EZ19: 43.762952 | FA19: 42.407127 | FB19: 45.856939 | FC19: 47.762025 | FD19: 52.1589 | FE19: 51.509298 | FF19: 57.083072 | FG19: 60.427183 | FH19: 58.817883 | FI19: 58.194744 | FJ19: 58.399543 | FL19: 428.38293 | FM19: 517.49898 | FN19: 681.54096 | FO19: 715.41955 | FP19: 673.40445 | FQ19: 686.19115 | FR19: 535.05648 | FS19: 447.16983 | FT19: 496.59772 | FU19: 578.29774 | FV19: 589.37023 | FW19: 540.55679 | FX19: ='EDE''s'!C19 -> 576.37967
B20: Edesur | C20: 671.27384 | D20: 560.61335 | E20: 110.6605 | F20: 0.19739183 | H20: 625.00999 | I20: -64.396647 | J20: -0.10303299 | K20: 0 | L20: 38.343524 | M20: 37.395137 | N20: 34.703835 | O20: 37.546343 | P20: 37.890092 | Q20: 41.290706 | R20: 46.720248 | S20: 49.151904 | T20: 49.050477 | U20: 51.274612 | V20: 52.629707 | W20: 49.98101 | X20: 49.354534 | Y20: 47.833631 | Z20: 51.493562 | AA20: 50.669656 | AB20: 55.375966 | AC20: 50.914636 | AD20: 55.434597 | AE20: 56.877335 | AF20: 52.634508 | AG20: 54.287054 | AH20: 51.583136 | AI20: 51.775332 | AJ20: 54.140977 | AK20: 52.93564 | AL20: 63.464307 | AM20: 63.558164 | AN20: 70.146308 | AO20: 69.633551 | AP20: 74.078997 | AQ20: 74.727692 | AR20: 73.17398 | AS20: 75.707799 | AT20: 69.545093 | AU20: 66.921331 | AV20: 65.240616 | AW20: 64.502639 | AX20: 70.164822 | AY20: 70.43349 | AZ20: 79.458619 | BA20: 77.388862 | BB20: 72.66501 | BC20: 67.638739 | BD20: 73.83899 | BE20: 72.542776 | BF20: 67.831921 | BG20: 65.368503 | BH20: 62.580328 | BI20: 60.516 | BJ20: 69.506212 | BK20: 66.977804 | BL20: 66.741605 | BM20: 61.870973 | BN20: 63.693267 | BO20: 69.278135 | BP20: 69.107843 | BQ20: 70.41222 | BR20: 64.245947 | BS20: 62.036199 | BT20: 62.984298 | BU20: 58.832515 | BV20: 67.133247 | BW20: 67.601457 | BX20: 69.613506 | BY20: 72.31222 | BZ20: 76.603815 | CA20: 71.467853 | CB20: 68.844518 | CC20: 71.854322 | CD20: 59.998467 | CE20: 51.745223 | CF20: 49.253616 | CG20: 44.287218 | CH20: 49.841092 | CI20: 49.063536 | CJ20: 53.805643 | CK20: 58.313419 | CL20: 59.591064 | CM20: 54.619167 | CN20: 50.206251 | CO20: 52.387553 | CP20: 45.181965 | CQ20: 43.409503 | CR20: 38.140821 | CS20: 37.153175 | CT20: 39.762493 | CU20: 41.956704 | CV20: 46.555344 | CW20: 49.006799 | CX20: 51.035713 | CY20: 48.440059 | CZ20: 48.276281 | DA20: 47.888337 | DB20: 46.538453 | DC20: 45.294333 | DD20: 46.471636 | DE20: 46.362899 | DF20: 48.278859 | DG20: 45.383983 | DH20: 48.987024 | DI20: 50.146173 | DJ20: 50.783117 | DK20: 52.4757 | DL20: 49.398855 | DM20: 51.415243 | DN20: 47.672877 | DO20: 48.909415 | DP20: 45.556229 | DQ20: 39.445597 | DR20: 48.620632 | DS20: 49.504475 | DT20: 54.73 | DU20: 58.167201 | DV20: 61.283522 | DW20: 61.339307 | DX20: 58.384002 | DY20: 59.586516 | DZ20: 59.227784 | EA20: 55.433756 | EB20: 52.190331 | EC20: 51.527903 | ED20: 57.984458 | EE20: 55.464424 | EF20: 60.023701 | EG20: 61.534966 | EH20: 59.988072 | EI20: 60.825841 | EJ20: 56.711815 | EK20: 56.056475 | EL20: 52.702008 | EM20: 48.194632 | EN20: 48.775786 | EO20: 48.401509 | EP20: 47.48788 | EQ20: 45.728583 | ER20: 47.781964 | ES20: 51.697923 | ET20: 55.077131 | EU20: 54.65996 | EV20: 54.406099 | EW20: 54.672623 | EX20: 51.923888 | EY20: 53.6526 | EZ20: 50.984572 | FA20: 50.481593 | FB20: 54.315143 | FC20: 55.19886 | FD20: 60.382443 | FE20: 59.539643 | FF20: 63.782403 | FG20: 66.788402 | FH20: 70.784634 | FI20: 68.705178 | FJ20: 70.310973 | FL20: 525.9776 | FM20: 628.23395 | FN20: 808.03384 | FO20: 847.07499 | FP20: 786.96653 | FQ20: 798.99144 | FR20: 609.96003 | FS20: 540.04851 | FT20: 586.28578 | FU20: 651.27902 | FV20: 673.20463 | FW20: 614.26595 | FX20: ='EDE''s'!C20 -> 671.27384
B21: Edeeste | C21: 643.28323 | D21: 511.61748 | E21: 131.66575 | F21: 0.25735194 | H21: 645.803 | I21: -134.18553 | J21: -0.2077809 | K21: 0 | L21: 37.850212 | M21: 26.600429 | N21: 24.568302 | O21: 25.81913 | P21: 24.402607 | Q21: 28.582828 | R21: 29.760682 | S21: 31.35822 | T21: 29.535189 | U21: 31.016148 | V21: 32.680217 | W21: 34.046019 | X21: 34.864548 | Y21: 34.361753 | Z21: 38.608659 | AA21: 35.9708 | AB21: 38.256023 | AC21: 37.850827 | AD21: 37.711079 | AE21: 41.894835 | AF21: 36.315426 | AG21: 36.487115 | AH21: 32.560841 | AI21: 33.694491 | AJ21: 36.117672 | AK21: 33.871429 | AL21: 39.995804 | AM21: 40.971635 | AN21: 46.354929 | AO21: 46.182493 | AP21: 47.074637 | AQ21: 48.41596 | AR21: 44.573057 | AS21: 44.687168 | AT21: 39.359495 | AU21: 38.938532 | AV21: 38.800199 | AW21: 35.730475 | AX21: 36.6795 | AY21: 38.060211 | AZ21: 44.762784 | BA21: 44.541066 | BB21: 41.816337 | BC21: 38.776972 | BD21: 40.940278 | BE21: 41.148074 | BF21: 39.984309 | BG21: 40.000374 | BH21: 40.817572 | BI21: 39.371701 | BJ21: 43.608693 | BK21: 43.102467 | BL21: 44.622021 | BM21: 41.790587 | BN21: 43.015177 | BO21: 44.787792 | BP21: 44.436904 | BQ21: 44.030836 | BR21: 41.010103 | BS21: 40.424194 | BT21: 42.111917 | BU21: 38.809856 | BV21: 46.711111 | BW21: 44.39136 | BX21: 46.309526 | BY21: 46.812748 | BZ21: 50.655827 | CA21: 47.657732 | CB21: 45.078803 | CC21: 48.140929 | CD21: 51.340529 | CE21: 41.745863 | CF21: 40.034297 | CG21: 34.867352 | CH21: 38.518715 | CI21: 37.567432 | CJ21: 39.753444 | CK21: 42.106891 | CL21: 42.97733 | CM21: 41.100606 | CN21: 38.179943 | CO21: 38.987952 | CP21: 34.882151 | CQ21: 34.679904 | CR21: 29.992649 | CS21: 29.701859 | CT21: 31.252545 | CU21: 32.736274 | CV21: 34.389955 | CW21: 34.15036 | CX21: 36.839689 | CY21: 38.578407 | CZ21: 39.163964 | DA21: 38.671547 | DB21: 36.321873 | DC21: 37.750745 | DD21: 40.161595 | DE21: 38.65783 | DF21: 41.994674 | DG21: 40.086324 | DH21: 42.818947 | DI21: 43.610109 | DJ21: 43.797947 | DK21: 44.749428 | DL21: 41.520383 | DM21: 44.195236 | DN21: 42.31501 | DO21: 45.461793 | DP21: 43.472208 | DQ21: 38.022752 | DR21: 48.042406 | DS21: 49.49445 | DT21: 53.647694 | DU21: 59.232714 | DV21: 64.082665 | DW21: 63.511123 | DX21: 63.997569 | DY21: 63.45056 | DZ21: 68.908611 | EA21: 62.021965 | EB21: 58.18904 | EC21: 58.491875 | ED21: 60.774713 | EE21: 58.621139 | EF21: 64.450078 | EG21: 63.794595 | EH21: 59.179999 | EI21: 61.456985 | EJ21: 57.701029 | EK21: 54.175864 | EL21: 48.967685 | EM21: 43.760778 | EN21: 42.017984 | EO21: 42.686576 | EP21: 42.304655 | EQ21: 42.370154 | ER21: 40.573184 | ES21: 46.796594 | ET21: 51.440313 | EU21: 52.274028 | EV21: 52.199392 | EW21: 51.781236 | EX21: 47.173361 | EY21: 48.694588 | EZ21: 49.811082 | FA21: 47.741192 | FB21: 50.581704 | FC21: 53.271121 | FD21: 57.910979 | FE21: 56.532189 | FF21: 61.195029 | FG21: 60.971038 | FH21: 69.760884 | FI21: 67.084961 | FJ21: 68.423048 | FL21: 356.21998 | FM21: 438.5764 | FN21: 506.54281 | FO21: 481.24058 | FP21: 511.01805 | FQ21: 549.7662 | FR21: 463.65602 | FS21: 419.54987 | FT21: 509.36928 | FU21: 677.88472 | FV21: 689.56378 | FW21: 560.31206 | FX21: ='EDE''s'!C21 -> 643.28323
... B101: Edeeste | C101: 7.3542871 | D101: 3.6072738 | E101: 3.7470133 | F101: 1.0387383 | H101: 6.6041548 | I101: -2.996881 | J101: -0.45378721 | K101: 0 | L101: 0.42892381 | M101: 0.37323343 | N101: 0.46187774 | O101: 0.43689537 | P101: 0.401262 | Q101: 0.4515293 | R101: 0.45880221 | S101: 0.39870325 | T101: 0.44058291 | U101: 0.53752379 | V101: 0.48232121 | W101: 0.54063087 | X101: 0.43174882 | Y101: 0.455727 | Z101: 0.56429257 | AA101: 0.41729255 | AB101: 0.38586841 | AC101: 0.38383899 | AD101: 0.41756625 | AE101: 0.38024479 | AF101: 0.41255398 | AG101: 0.44771075 | AH101: 0.47124356 | AI101: 0.51140343 | AJ101: 0.41608384 | AK101: 0.41207272 | AL101: 0.49089285 | AM101: 0.45301922 | AN101: 0.42465129 | AO101: 0.41613343 | AP101: 0.4209181 | AQ101: 0.51190378 | AR101: 0.56448468 | AS101: 0.62695647 | AT101: 0.57262482 | AU101: 0.59564231 | AV101: 0.62250271 | AW101: 0.57877969 | AX101: 0.64911217 | AY101: 0.53623652 | AZ101: 0.60898165 | BA101: 0.53652997 | BB101: 0.52220675 | BC101: 0.56654462 | BD101: 0.52183317 | BE101: 0.59379341 | BF101: 0.56396361 | BG101: 0.58664639 | BH101: 0.56848402 | BI101: 0.50774998 | BJ101: 0.56523785 | BK101: 0.5583796 | BL101: 0.53106277 | BM101: 0.50470078 | BN101: 0.57295006 | BO101: 0.64280701 | BP101: 0.53060919 | BQ101: 0.57929144 | BR101: 0.72456097 | BS101: 0.60753374 | BT101: 0.54643585 | BU101: 0.49320292 | BV101: 0.54106993 | BW101: 0.48289622 | BX101: 0.42644601 | BY101: 0.39589287 | BZ101: 0.50023872 | CA101: 0.4581044 | CB101: 0.4841513 | CC101: 0.55298658 | CD101: 0.48531075 | CE101: 0.54285413 | CF101: 0.50266601 | CG101: 0.47191415 | CH101: 0.51476976 | CI101: 0.45774838 | CJ101: 0.46373671 | CK101: 0.47199678 | CL101: 0.4930395 | CM101: 0.49330235 | CN101: 0.54711648 | CO101: 0.63742589 | CP101: 0.54784038 | CQ101: 0.6668826 | CR101: 0.55015632 | CS101: 0.50525553 | CT101: 0.60135246 | CU101: 0.608962 | CV101: 0.55264871 | CW101: 0.55350024 | CX101: 0.54299654 | CY101: 0.61477445 | CZ101: 0.53027932 | DA101: 0.55730452 | DB101: 0.54786424 | DC101: 0.57961452 | DD101: 0.57224122 | DE101: 0.57156774 | DF101: 0.62418428 | DG101: 0.51102469 | DH101: 0.52968406 | DI101: 0.53686984 | DJ101: 0.5289533 | DK101: 0.59587428 | DL101: 0.46600698 | DM101: 0.52577976 | DN101: 0.58448805 | DO101: 0.50548441 | DP101: 0.60412313 | DQ101: 0.47284163 | DR101: 0.54179699 | DS101: 0.51053152 | DT101: 0.51414245 | DU101: 0.50257267 | DV101: 0.57051349 | DW101: 0.57966759 | DX101: 0.68537431 | DY101: 0.65287052 | DZ101: 0.56533149 | EA101: 0.59016188 | EB101: 0.64283877 | EC101: 0.54307286 | ED101: 0.55560705 | EE101: 0.53785089 | EF101: 0.53397435 | EG101: 0.58911371 | EH101: 0.74003826 | EI101: 0.60762492 | EJ101: 0.61448556 | EK101: 0.63320993 | EL101: 0.60633849 | EM101: 0.7016215 | EN101: 0.63880137 | EO101: 0.55771469 | EP101: 0.4504106 | EQ101: 0.21925367 | ER101: 0.24502216 | ES101: 0.1885735 | ET101: 0.1806009 | EU101: 0.18669624 | EV101: 0.21516684 | EW101: 0.31475679 | EX101: 0.41027704 | EY101: 0.5052055 | EZ101: 0.50392689 | FA101: 0.55613431 | FB101: 0.79413548 | FC101: 0.61366059 | FD101: 0.62953179 | FE101: 0.65561624 | FF101: 0.68827575 | FG101: 0.68189463 | FH101: 0.77440704 | FI101: 0.70473574 | FJ101: 0.75196864 | FL101: 5.4122859 | FM101: 5.2794911 | FN101: 5.9053835 | FO101: 6.8871307 | FP101: 6.8933674 | FQ101: 5.9095897 | FR101: 6.268439 | FS101: 6.7447088 | FT101: 6.5521586 | FU101: 6.7899277 | FV101: 7.3057763 | FW101: 4.1124793 | FX101: ='EDE''s'!C101 -> 7.3542871
FX102: ='EDE''s'!C102 -> 0
B103: Otros Ingresos (US$ MM) | C103: 9.3774981 | D103: 6.9584693 | E103: 2.4190288 | F103: 0.34763807 | H103: 7.7720927 | I103: -0.81362338 | J103: -0.10468524 | K103: 0 | L103: 0.09178418 | M103: 0.16109558 | N103: 0.20248871 | O103: 1.039266 | P103: 0.13977764 | Q103: 0.10273805 | R103: 0.81478896 | S103: 0.12711416 | T103: 0.16496626 | U103: 0.22338963 | V103: 0.37213416 | W103: 0.32864391 | X103: 0.31053981 | Y103: 0.15040828 | Z103: 0.19424673 | AA103: 0.10360368 | AB103: 0.82702104 | AC103: 0.23266256 | AD103: 2.1759619 | AE103: 1.1005173 | AF103: 0.86284055 | AG103: 0.31716451 | AH103: 0.11940088 | AI103: 0.1007294 | AJ103: 0.42676072 | AK103: 0.55400606 | AL103: 0.40932143 | AM103: 0.30159634 | AN103: 0.99529705 | AO103: 0.26935797 | AP103: 1.3858054 | AQ103: 0.052813066 | AR103: 0.19869858 | AS103: 0.77888644 | AT103: 0.25068016 | AU103: 1.7388062 | AV103: 1.0619486 | AW103: 0.83801417 | AX103: 0.18949614 | AY103: 0.11594954 | AZ103: 0.15516207 | BA103: 0.99283219 | BB103: 0.27973412 | BC103: 0.088420705 | BD103: 0.43467 | BE103: 0.19470213 | BF103: 0.53346327 | BG103: 0.39661805 | BH103: 0.39763605 | BI103: 0.33100543 | BJ103: 0.27322845 | BK103: 0.019725367 | BL103: 0.42667605 | BM103: 0.44568388 | BN103: 0.77802103 | BO103: 0.93206938 | BP103: 0.2530065 | BQ103: 1.2921396 | BR103: 0.42307974 | BS103: 0.73741264 | BT103: 0.053604774 | BU103: 0.068269964 | BV103: 0.17896167 | BW103: 0.30351916 | BX103: 0.28665694 | BY103: 0.24722181 | BZ103: 0.057686383 | CA103: 0.14582708 | CB103: 0.92606017 | CC103: 0.22294528 | CD103: 0.61642941 | CE103: 0.31210961 | CF103: 1.2408874 | CG103: 0.7958674 | CH103: 0.49732512 | CI103: 0.03484479 | CJ103: 0.40770668 | CK103: 0.28459498 | CL103: 0.2677744 | CM103: 0.23174644 | CN103: 0.15105813 | CO103: 0.11112051 | CP103: 0.3333963 | CQ103: 1.7640185 | CR103: 0.96982071 | CS103: 0.71393769 | CT103: 1.8773259 | CU103: 0.049508042 | CV103: 0.58031414 | CW103: 0.91401175 | CX103: 0.14405074 | CY103: 0.16504567 | CZ103: 0.84175609 | DA103: 1.6460727 | DB103: 0.86715841 | DC103: 0.26261925 | DD103: 0.2767741 | DE103: 0.27356957 | DF103: 1.7757572 | DG103: 0.19450152 | DH103: 1.0323212 | DI103: 0.64714928 | DJ103: 0.46360813 | DK103: 0.22308557 | DL103: 0.18195456 | DM103: 0.21627638 | DN103: 0.06376926 | DO103: 0.19486511 | DP103: 0.33859666 | DQ103: 0.26802185 | DR103: 0.08615076 | DS103: 0.04972958 | DT103: 1.3244113 | DU103: 1.0226026 | DV103: 0.11253567 | DW103: 0.12982036 | DX103: 0.77353917 | DY103: 0.28370798 | DZ103: 0.10895908 | EA103: 0.88002473 | EB103: 0.63997698 | EC103: 0.16863669 | ED103: 0.43324067 | EE103: 0.37104154 | EF103: 0.39821129 | EG103: 0.96100677 | EH103: 0.20760731 | EI103: 0.59033948 | EJ103: 0.2609829 | EK103: 0.18589308 | EL103: 3.555156 | EM103: 0.18978016 | EN103: 0.32946994 | EO103: 0.3344033 | EP103: 0.14377749 | EQ103: 1.6977223 | ER103: 0.90346203 | ES103: 1.5984978 | ET103: 0.30456072 | EU103: 0.87986382 | EV103: 0.10359045 | EW103: 0.25101961 | EX103: 0.4121018 | EY103: 0.94616401 | EZ103: 2.9659146 | FA103: 0.32503237 | FB103: 0.18656655 | FC103: 0.31525859 | FD103: 1.2970927 | FE103: 0.22073751 | FF103: 0.18553297 | FG103: 0.32258283 | FH103: 0.28545099 | FI103: 0.78217669 | FJ103: 2.4911523 | FL103: 3.7681872 | FM103: 6.4950966 | FN103: 7.3620295 | FO103: 5.281011 | FP103: 6.3096841 | FQ103: 3.4192923 | FR103: 6.1203406 | FS103: 9.0316211 | FT103: 5.5436319 | FU103: 5.3780997 | FV103: 7.9618728 | FW103: 7.9046333 | FX103: ='EDE''s'!C103 -> 9.3774981
B104: Edenorte | C104: 7.0574637 | D104: 4.1474513 | E104: 2.9100124 | F104: 0.7016387 | H104: 3.1714777 | I104: 0.97597363 | J104: 0.30773466 | K104: 0 | L104: 0 | M104: 0.0016827038 | N104: 0.033841515 | O104: 0.016430055 | P104: 0.015949767 | Q104: 0.005554059 | R104: 0.085859495 | S104: 0.033217166 | T104: 0.080835596 | U104: 0.039907316 | V104: 0.29805066 | W104: 0.056910707 | X104: 0.044414596 | Y104: 0.077658567 | Z104: 0.018698733 | AA104: 0.014164586 | AB104: 0.055202033 | AC104: 0.10566403 | AD104: 0.073604525 | AE104: 0.025530559 | AF104: 0.063810444 | AG104: 0.18821311 | AH104: 0.010203359 | AI104: 0.017417305 | AJ104: 0.0069253011 | AK104: 0.28681665 | AL104: 0.010281445 | AM104: 0.0064564078 | AN104: 0.0084225952 | AO104: 0.088135575 | AP104: 1.0152929 | AQ104: 0.0034129497 | AR104: 0.0049238734 | AS104: 0.063420969 | AT104: 0.013803058 | AU104: 0.078464263 | AV104: 0.0084611629 | AW104: 0.067913928 | AX104: 0.010848075 | AY104: 0.007233779 | AZ104: 0.021197781 | BA104: 0.022485346 | BB104: 0.020355281 | BC104: 0.015958734 | BD104: 0.014036716 | BE104: 0.02308721 | BF104: 0.17120755 | BG104: 0.073664697 | BH104: 0.085243431 | BI104: 0.011280425 | BJ104: 0.15964698 | BK104: 0.0087493954 | BL104: 0.0037926481 | BM104: 0.022684341 | BN104: 0.067413024 | BO104: 0.058434782 | BP104: 0.072398185 | BQ104: 0.087510749 | BR104: 0.087094815 | BS104: 0.10058071 | BT104: 0.0082020398 | BU104: 0.023101001 | BV104: 0.010999451 | BW104: 0.090421104 | BX104: 0.084641671 | BY104: 0.10483794 | BZ104: 0.021354744 | CA104: 0.10712334 | CB104: 0.013963521 | CC104: 0.070412655 | CD104: 0.20995555 | CE104: 0.078876157 | CF104: 0.42030719 | CG104: 0.028090137 | CH104: 0.11069412 | CI104: 0.025172736 | CJ104: 0.020331988 | CK104: 0.040161236 | CL104: 0.037676476 | CM104: 0.029191853 | CN104: 0.016733206 | CO104: 0.013226953 | CP104: 0.00051768196 | CQ104: 0.063012252 | CR104: 0.39215279 | CS104: 0.013095998 | CT104: 0.87654058 | CU104: 0.0092506217 | CV104: 0.017262464 | CW104: 0.3534624 | CX104: 0.027324503 | CY104: 0.0072014368 | CZ104: 0.012725736 | DA104: 0.016416942 | DB104: 0.019454394 | DC104: 0.012388441 | DD104: 0.23059379 | DE104: 0.04002666 | DF104: 0.85542311 | DG104: 0.013807213 | DH104: 0.83468056 | DI104: 0.43271151 | DJ104: 0.32270149 | DK104: 0.096696424 | DL104: 0.15017624 | DM104: 0.18118581 | DN104: 0.028935976 | DO104: 0.096801269 | DP104: 0.27375387 | DQ104: 0.24028446 | DR104: 0.052427191 | DS104: 0.02386236 | DT104: 1.0003374 | DU104: 0.28716045 | DV104: 0.038925267 | DW104: 0.10572911 | DX104: 0.13691504 | DY104: 0.12115484 | DZ104: 0.073428263 | EA104: 0.17540495 | EB104: 0.093376876 | EC104: 0.099018996 | ED104: 0.05449452 | EE104: 0.057912106 | EF104: 0.11500407 | EG104: 0.89641183 | EH104: 0.11575731 | EI104: 0.045376419 | EJ104: 0.08760463 | EK104: 0.0984495 | EL104: 1.5080715 | EM104: 0.088239522 | EN104: 0.2548949 | EO104: 0.13359364 | EP104: 0.086394971 | EQ104: 1.636742 | ER104: 0.16786842 | ES104: 1.0108124 | ET104: 0.10248324 | EU104: 0.38875412 | EV104: 0.095859384 | EW104: 0.13146959 | EX104: 0.13857867 | EY104: 0.84600564 | EZ104: 2.9539605 | FA104: 0.097667479 | FB104: 0.10398195 | FC104: 0.22790708 | FD104: 0.082969405 | FE104: 0.13277721 | FF104: 0.093250058 | FG104: 0.08141978 | FH104: 0.20027052 | FI104: 0.66584422 | FJ104: 2.4174155 | FL104: 0.66823904 | FM104: 0.69458184 | FN104: 1.5863559 | FO104: 0.45645026 | FP104: 0.76482949 | FQ104: 0.82388918 | FR104: 0.80511583 | FS104: 1.7572763 | FT104: 3.2837401 | FU104: 2.5293832 | FV104: 3.2597172 | FW104: 4.993457 | FX104: ='EDE''s'!C104 -> 7.0574637
B105: Edesur | C105: 1.9991005 | D105: 1.4253517 | E105: 0.5737488 | F105: 0.40253138 | H105: 2.2439193 | I105: -0.81856752 | J105: -0.36479366 | K105: 0 | L105: 0.054729388 | M105: 0.10993257 | N105: 0.1123972 | O105: 0.63236574 | P105: 0.078194183 | Q105: 0.021291528 | R105: 0.69737936 | S105: 0.044233954 | T105: 0.083908335 | U105: 0.17984603 | V105: 0.058479028 | W105: 0.19957381 | X105: 0.19406364 | Y105: 0.041010038 | Z105: 0.10305513 | AA105: 0.053137806 | AB105: 0.73055331 | AC105: 0.066356418 | AD105: 1.7828474 | AE105: 1.0522712 | AF105: 0.71786478 | AG105: 0.05755205 | AH105: 0.067309344 | AI105: 0.055845247 | AJ105: 0.41983542 | AK105: 0.24420796 | AL105: 0.09142227 | AM105: 0.29513994 | AN105: 0.98211202 | AO105: 0.12566832 | AP105: 0.12822613 | AQ105: 0.049400116 | AR105: 0.086778922 | AS105: 0.17780372 | AT105: 0.21723657 | AU105: 1.5391486 | AV105: 1.0440107 | AW105: 0.75036084 | AX105: 0.14683414 | AY105: 0.040657919 | AZ105: 0.13248056 | BA105: 0.9688622 | BB105: 0.031826403 | BC105: 0.069520714 | BD105: 0.39597825 | BE105: 0.11785126 | BF105: 0.22176271 | BG105: 0.21012009 | BH105: 0.22508064 | BI105: 0.31972501 | BJ105: 0.11358147 | BK105: 0.010352824 | BL105: 0.4228834 | BM105: 0.23716392 | BN105: 0.37670604 | BO105: 0.19873654 | BP105: 0.15788112 | BQ105: 1.2046288 | BR105: 0.32216519 | BS105: 0.57646602 | BT105: 0.045402735 | BU105: 0.022451006 | BV105: 0.13339401 | BW105: 0.12945508 | BX105: 0.17756352 | BY105: 0.14196496 | BZ105: 0.036331639 | CA105: 0.03870374 | CB105: 0.91091118 | CC105: 0.15253263 | CD105: 0.38525581 | CE105: 0.10402266 | CF105: 0.81968283 | CG105: 0.76656296 | CH105: 0.386631 | CI105: 0.0095894598 | CJ105: 0.36961941 | CK105: 0.23351945 | CL105: 0.23009792 | CM105: 0.19501637 | CN105: 0.13432492 | CO105: 0.091644372 | CP105: 0.32763895 | CQ105: 1.6965706 | CR105: 0.57215277 | CS105: 0.69191188 | CT105: 0.98058477 | CU105: 0.02519319 | CV105: 0.55840389 | CW105: 0.5532158 | CX105: 0.11293756 | CY105: 0.15352009 | CZ105: 0.82591609 | DA105: 1.618078 | DB105: 0.8469403 | DC105: 0.24766782 | DD105: 0.042018888 | DE105: 0.229721 | DF105: 0.91177618 | DG105: 0.17423809 | DH105: 0.19148656 | DI105: 0.20696007 | DJ105: 0.11323809 | DK105: 0.11021504 | DL105: 0.024406632 | DM105: 0.027955663 | DN105: 0.021137276 | DO105: 0.092697199 | DP105: 0.029736741 | DQ105: 0.020841041 | DR105: 0.021061718 | DS105: 0.014463193 | DT105: 0.27880238 | DU105: 0.70687709 | DV105: 0.040519189 | DW105: 0.009451657 | DX105: 0.61574931 | DY105: 0.10732774 | DZ105: 0.020232881 | EA105: 0.6755419 | EB105: 0.50332561 | EC105: 0.048821374 | ED105: 0.35619119 | EE105: 0.23143203 | EF105: 0.25670652 | EG105: 0.045031215 | EH105: 0.05100265 | EI105: 0.47129515 | EJ105: 0.031488168 | EK105: 0.054419011 | EL105: 0.19420634 | EM105: 0.079049701 | EN105: 0.059511563 | EO105: 0.17364094 | EP105: 0.03903454 | EQ105: 0.031461012 | ER105: 0.18550821 | ES105: 0.059337457 | ET105: 0.047137571 | EU105: 0.45349174 | EV105: 0.0025832483 | EW105: 0.10652122 | EX105: 0.26712423 | EY105: 0.091601447 | EZ105: 0 | FA105: 0.21366362 | FB105: 0.062567823 | FC105: 0.066509607 | FD105: 1.1685414 | FE105: 0.068914606 | FF105: 0.068504859 | FG105: 0.21421561 | FH105: 0.055443287 | FI105: 0.049489613 | FJ105: 0.031250098 | FL105: 2.2723311 | FM105: 4.9218664 | FN105: 4.35698 | FO105: 4.1302658 | FP105: 4.165371 | FQ105: 2.277989 | FR105: 5.2608983 | FS105: 7.1865221 | FT105: 2.1458507 | FU105: 2.5406048 | FV105: 2.322969 | FW105: 1.5169532 | FX105: ='EDE''s'!C105 -> 1.9991005
B106: Edeeste | C106: 0.32093384 | D106: 1.3856662 | E106: -1.0647324 | F106: -0.76839022 | H106: 2.3566957 | I106: -0.97102948 | J106: -0.41203007 | K106: 0 | L106: 0.037054792 | M106: 0.049480308 | N106: 0.056249999 | O106: 0.39047019 | P106: 0.045633687 | Q106: 0.075892466 | R106: 0.031550099 | S106: 0.049663042 | T106: 0.00022232308 | U106: 0.0036362766 | V106: 0.015604469 | W106: 0.072159399 | X106: 0.072061568 | Y106: 0.031739679 | Z106: 0.072492866 | AA106: 0.036301286 | AB106: 0.041265699 | AC106: 0.060642112 | AD106: 0.31950989 | AE106: 0.022715571 | AF106: 0.081165328 | AG106: 0.071399354 | AH106: 0.041888175 | AI106: 0.02746685 | AJ106: 0 | AK106: 0.02298144 | AL106: 0.30761771 | AM106: 0 | AN106: 0.0047624274 | AO106: 0.05555408 | AP106: 0.24228644 | AQ106: 0 | AR106: 0.10699578 | AS106: 0.53766176 | AT106: 0.019640532 | AU106: 0.12119337 | AV106: 0.0094767647 | AW106: 0.0197394 | AX106: 0.031813921 | AY106: 0.068057844 | AZ106: 0.0014837239 | BA106: 0.0014846461 | BB106: 0.22755243 | BC106: 0.002941256 | BD106: 0.024655025 | BE106: 0.053763653 | BF106: 0.14049301 | BG106: 0.11283326 | BH106: 0.087311972 | BI106: 0 | BJ106: 0 | BK106: 0.00062314847 | BL106: 0 | BM106: 0.18583562 | BN106: 0.33390196 | BO106: 0.67489806 | BP106: 0.022727195 | BQ106: 0 | BR106: 0.013819737 | BS106: 0.060365905 | BT106: 0 | BU106: 0.022717957 | BV106: 0.03456821 | BW106: 0.083642972 | BX106: 0.024451745 | BY106: 0.00041891764 | BZ106: 0 | CA106: 0 | CB106: 0.0011854745 | CC106: 0 | CD106: 0.021218049 | CE106: 0.12921079 | CF106: 0.00089735764 | CG106: 0.0012143034 | CH106: 0 | CI106: 8.2594588e-05 | CJ106: 0.017755279 | CK106: 0.010914292 | CL106: 0 | CM106: 0.0075382139 | CN106: 0 | CO106: 0.0062491866 | CP106: 0.0052396689 | CQ106: 0.0044355812 | CR106: 0.0055151493 | CS106: 0.0089298078 | CT106: 0.020200574 | CU106: 0.01506423 | CV106: 0.0046477926 | CW106: 0.0073335513 | CX106: 0.0037886782 | CY106: 0.004324144 | CZ106: 0.0031142663 | DA106: 0.011577799 | DB106: 0.00076371699 | DC106: 0.0025629825 | DD106: 0.0041614219 | DE106: 0.0038219071 | DF106: 0.0085579603 | DG106: 0.0064562259 | DH106: 0.0061540634 | DI106: 0.0074777047 | DJ106: 0.027668549 | DK106: 0.016174107 | DL106: 0.0073716904 | DM106: 0.0071349053 | DN106: 0.013696008 | DO106: 0.0053666414 | DP106: 0.035106051 | DQ106: 0.0068963443 | DR106: 0.012661852 | DS106: 0.011404027 | DT106: 0.045271535 | DU106: 0.028565089 | DV106: 0.033091216 | DW106: 0.014639597 | DX106: 0.020874815 | DY106: 0.055225404 | DZ106: 0.015297931 | EA106: 0.029077873 | EB106: 0.043274489 | EC106: 0.020796321 | ED106: 0.022554963 | EE106: 0.081697407 | EF106: 0.026500701 | EG106: 0.019563725 | EH106: 0.040847347 | EI106: 0.07366792 | EJ106: 0.1418901 | EK106: 0.033024573 | EL106: 1.8528781 | EM106: 0.022490937 | EN106: 0.015063474 | EO106: 0.02716872 | EP106: 0.018347975 | EQ106: 0.02951926 | ER106: 0.55008539 | ES106: 0.528348 | ET106: 0.15493991 | EU106: 0.037617962 | EV106: 0.0051478159 | EW106: 0.013028804 | EX106: 0.0063988941 | EY106: 0.0085569164 | EZ106: 0.01195407 | FA106: 0.013701271 | FB106: 0.020016779 | FC106: 0.020841908 | FD106: 0.045581865 | FE106: 0.019045685 | FF106: 0.023778053 | FG106: 0.026947449 | FH106: 0.029737188 | FI106: 0.066842858 | FJ106: 0.042486719 | FL106: 0.82761705 | FM106: 0.87864838 | FN106: 1.4186935 | FO106: 0.69429494 | FP106: 1.3794836 | FQ106: 0.31741411 | FR106: 0.054326477 | FS106: 0.087822692 | FT106: 0.11404118 | FU106: 0.30811173 | FV106: 2.3791866 | FW106: 1.3942231 | FX106: ='EDE''s'!C106 -> 0.32093384
FX107: ='EDE''s'!C107 -> 0
B108: Gastos Operativos (US$ MM) | C108: 312.47493 | D108: 303.71368 | E108: 8.7612465 | F108: 0.028847059 | H108: 353.53969 | I108: -49.826007 | J108: -0.14093469 | K108: 0 | L108: 22.185317 | M108: 19.238866 | N108: 20.778481 | O108: 18.806081 | P108: 18.786204 | Q108: 18.936068 | R108: 18.281938 | S108: 17.779391 | T108: 19.815662 | U108: 18.865725 | V108: 18.146891 | W108: 22.766096 | X108: 20.188818 | Y108: 16.595545 | Z108: 20.149331 | AA108: 18.087932 | AB108: 19.159697 | AC108: 17.657989 | AD108: 16.524206 | AE108: 19.81923 | AF108: 17.931877 | AG108: 19.728959 | AH108: 24.13785 | AI108: 25.007126 | AJ108: 16.767162 | AK108: 15.47372 | AL108: 23.935219 | AM108: 18.595762 | AN108: 18.341495 | AO108: 20.058472 | AP108: 23.857811 | AQ108: 21.295035 | AR108: 22.15337 | AS108: 25.590379 | AT108: 27.832291 | AU108: 36.273059 | AV108: 25.677819 | AW108: 25.443339 | AX108: 24.191705 | AY108: 28.312901 | AZ108: 31.973194 | BA108: 22.474632 | BB108: 25.239758 | BC108: 22.740222 | BD108: 18.852883 | BE108: 29.922218 | BF108: 25.806705 | BG108: 33.064431 | BH108: 31.393354 | BI108: 24.579119 | BJ108: 22.623103 | BK108: 25.934746 | BL108: 26.198128 | BM108: 22.67151 | BN108: 23.13501 | BO108: 25.431918 | BP108: 24.389186 | BQ108: 22.896145 | BR108: 21.828348 | BS108: 32.749549 | BT108: 27.999294 | BU108: 29.930551 | BV108: 25.391978 | BW108: 31.535476 | BX108: 26.188836 | BY108: 22.768995 | BZ108: 27.069239 | CA108: 25.86918 | CB108: 29.030541 | CC108: 82.695703 | CD108: 27.199619 | CE108: 33.758579 | CF108: 25.735709 | CG108: 26.411497 | CH108: 30.128869 | CI108: 32.632235 | CJ108: 25.841357 | CK108: 27.781771 | CL108: 27.498431 | CM108: 24.848861 | CN108: 27.793276 | CO108: 29.307118 | CP108: 24.745958 | CQ108: 38.293505 | CR108: 34.736253 | CS108: 25.716513 | CT108: 30.25283 | CU108: 27.614957 | CV108: 24.936523 | CW108: 26.166127 | CX108: 25.646841 | CY108: 31.848899 | CZ108: 26.109258 | DA108: 32.297933 | DB108: 31.810123 | DC108: 41.63461 | DD108: 28.447211 | DE108: 26.842796 | DF108: 31.465935 | DG108: 22.474552 | DH108: 28.164967 | DI108: 28.262618 | DJ108: 25.799763 | DK108: 31.674525 | DL108: 26.98673 | DM108: 38.920388 | DN108: 26.548767 | DO108: 36.820915 | DP108: 30.25482 | DQ108: 23.942373 | DR108: 28.391895 | DS108: 35.316208 | DT108: 26.405366 | DU108: 27.511542 | DV108: 32.191667 | DW108: 31.138544 | DX108: 29.472578 | DY108: 32.391713 | DZ108: 29.129928 | EA108: 35.789723 | EB108: 35.824211 | EC108: 28.715035 | ED108: 36.566146 | EE108: 38.604707 | EF108: 31.321773 | EG108: 30.382771 | EH108: 32.776121 | EI108: 30.638599 | EJ108: 28.719445 | EK108: 31.926455 | EL108: 28.064425 | EM108: 37.917519 | EN108: 30.352743 | EO108: 27.961137 | EP108: 29.576093 | EQ108: 22.954558 | ER108: 25.340753 | ES108: 29.279439 | ET108: 28.60134 | EU108: 26.924774 | EV108: 23.162196 | EW108: 30.909786 | EX108: 28.650865 | EY108: 33.58804 | EZ108: 22.850775 | FA108: 30.160339 | FB108: 27.87213 | FC108: 28.486432 | FD108: 26.335388 | FE108: 28.897897 | FF108: 29.840314 | FG108: 29.39214 | FH108: 25.055262 | FI108: 33.404887 | FJ108: 30.179366 | FL108: 234.38672 | FM108: 234.98856 | FN108: 270.17378 | FO108: 313.69981 | FP108: 303.83012 | FQ108: 389.43799 | FR108: 341.01859 | FS108: 358.77087 | FT108: 352.40917 | FU108: 361.93636 | FV108: 391.45721 | FW108: 337.30172 | FX108: ='EDE''s'!C108 -> 312.47493
B109: Edenorte | C109: 106.34175 | D109: 113.69241 | E109: -7.3506667 | F109: -0.064653977 | H109: 133.82138 | I109: -20.12897 | J109: -0.15041669 | K109: 0 | L109: 6.9146452 | M109: 6.6737712 | N109: 6.1306207 | O109: 5.5336873 | P109: 6.0619533 | Q109: 6.2439712 | R109: 5.339697 | S109: 5.7193614 | T109: 6.409599 | U109: 6.2572225 | V109: 5.7800759 | W109: 8.1864772 | X109: 5.4607232 | Y109: 5.173297 | Z109: 6.5494465 | AA109: 6.0070592 | AB109: 6.1183956 | AC109: 6.7982415 | AD109: 5.3196164 | AE109: 5.8340031 | AF109: 5.3503611 | AG109: 5.9854396 | AH109: 5.5678492 | AI109: 7.3200909 | AJ109: 4.6070335 | AK109: 5.801489 | AL109: 5.9608811 | AM109: 6.1306231 | AN109: 6.1805699 | AO109: 5.4172951 | AP109: 6.9366884 | AQ109: 6.9147052 | AR109: 6.4169642 | AS109: 6.3252812 | AT109: 6.1134183 | AU109: 8.2995945 | AV109: 6.016263 | AW109: 6.3348957 | AX109: 6.934838 | AY109: 5.8310646 | AZ109: 5.5685312 | BA109: 5.7260818 | BB109: 6.8918139 | BC109: 6.9425376 | BD109: 6.8252301 | BE109: 8.4952738 | BF109: 8.3293602 | BG109: 8.0419456 | BH109: 8.1988447 | BI109: 8.0406086 | BJ109: 8.0765649 | BK109: 6.2752082 | BL109: 6.8385719 | BM109: 7.0717964 | BN109: 7.14442 | BO109: 7.4382251 | BP109: 7.9610131 | BQ109: 6.7878044 | BR109: 6.47289 | BS109: 9.4994556 | BT109: 7.5808245 | BU109: 9.3896516 | BV109: 8.8798918 | BW109: 14.13541 | BX109: 8.0179952 | BY109: 7.8689617 | BZ109: 9.2145507 | CA109: 8.3377669 | CB109: 9.1235979 | CC109: 9.131619 | CD109: 8.8061817 | CE109: 10.94032 | CF109: 9.2499906 | CG109: 9.2075482 | CH109: 10.208895 | CI109: 14.084999 | CJ109: 9.4120845 | CK109: 9.7324919 | CL109: 10.366749 | CM109: 10.004417 | CN109: 9.7751361 | CO109: 9.01083 | CP109: 9.5764982 | CQ109: 11.979959 | CR109: 8.4877281 | CS109: 8.8744648 | CT109: 12.280012 | CU109: 8.9023795 | CV109: 10.000989 | CW109: 10.841324 | CX109: 9.8193607 | CY109: 10.419666 | CZ109: 9.9491351 | DA109: 11.240372 | DB109: 11.005314 | DC109: 18.258922 | DD109: 10.182736 | DE109: 8.9299197 | DF109: 11.744125 | DG109: 8.1384867 | DH109: 11.041692 | DI109: 9.6767401 | DJ109: 10.572139 | DK109: 11.094159 | DL109: 10.011507 | DM109: 17.252236 | DN109: 10.250846 | DO109: 12.091885 | DP109: 10.247793 | DQ109: 10.300957 | DR109: 9.1003782 | DS109: 18.542763 | DT109: 10.725012 | DU109: 10.957173 | DV109: 12.089661 | DW109: 11.355742 | DX109: 11.258319 | DY109: 10.61743 | DZ109: 10.986344 | EA109: 12.550521 | EB109: 11.475648 | EC109: 11.52065 | ED109: 17.028374 | EE109: 16.651218 | EF109: 10.49569 | EG109: 10.143685 | EH109: 12.16886 | EI109: 10.560749 | EJ109: 11.164729 | EK109: 11.722147 | EL109: 10.889633 | EM109: 13.026189 | EN109: 11.467222 | EO109: 9.7912323 | EP109: 10.23094 | EQ109: 8.8244907 | ER109: 8.4434079 | ES109: 10.256562 | ET109: 11.595027 | EU109: 10.937385 | EV109: 9.7380481 | EW109: 11.454481 | EX109: 10.953617 | EY109: 11.206145 | EZ109: 8.8815313 | FA109: 9.0531305 | FB109: 9.7350392 | FC109: 8.8951606 | FD109: 9.5033132 | FE109: 8.0455514 | FF109: 9.6797995 | FG109: 10.710115 | FH109: 8.4275021 | FI109: 12.075144 | FJ109: 11.33546 | FL109: 75.251082 | FM109: 71.484523 | FN109: 75.104543 | FO109: 81.937836 | FP109: 89.805403 | FQ109: 111.42677 | FR109: 122.6096 | FS109: 130.07967 | FT109: 130.98647 | FU109: 138.73209 | FV109: 146.84757 | FW109: 124.89856 | FX109: ='EDE''s'!C109 -> 106.34175
B110: Edesur | C110: 127.51277 | D110: 117.76871 | E110: 9.7440609 | F110: 0.082738963 | H110: 141.43138 | I110: -23.662676 | J110: -0.16730852 | K110: 0 | L110: 9.3418189 | M110: 7.1138394 | N110: 8.898896 | O110: 6.8277491 | P110: 8.3296856 | Q110: 7.1993575 | R110: 9.5754386 | S110: 7.711106 | T110: 8.6338609 | U110: 7.5878688 | V110: 7.959179 | W110: 8.6321791 | X110: 9.7450236 | Y110: 6.4342633 | Z110: 7.9238034 | AA110: 7.3518801 | AB110: 7.0323402 | AC110: 4.999731 | AD110: 6.3650707 | AE110: 7.4298009 | AF110: 7.214751 | AG110: 7.4064892 | AH110: 8.4984825 | AI110: 9.2577444 | AJ110: 7.2392275 | AK110: 4.1192287 | AL110: 9.932715 | AM110: 7.3162094 | AN110: 7.2220375 | AO110: 7.7613032 | AP110: 7.5654371 | AQ110: 8.8594339 | AR110: 9.9628799 | AS110: 11.709181 | AT110: 12.000482 | AU110: 16.993327 | AV110: 8.9590771 | AW110: 10.092416 | AX110: 9.0692576 | AY110: 13.291815 | AZ110: 17.208484 | BA110: 11.017719 | BB110: 10.839811 | BC110: 9.7425899 | BD110: 5.8984729 | BE110: 11.318753 | BF110: 11.321568 | BG110: 13.550956 | BH110: 12.345722 | BI110: 8.3710276 | BJ110: 7.2363248 | BK110: 13.379416 | BL110: 10.908244 | BM110: 9.6157495 | BN110: 8.6008181 | BO110: 9.9143488 | BP110: 9.2070673 | BQ110: 9.610649 | BR110: 9.1010223 | BS110: 14.335885 | BT110: 11.92552 | BU110: 12.576095 | BV110: 9.2253645 | BW110: 10.451306 | BX110: 10.822586 | BY110: 8.2735712 | BZ110: 11.50151 | CA110: 9.7145459 | CB110: 11.773188 | CC110: 12.819641 | CD110: 11.132801 | CE110: 12.919758 | CF110: 9.9451569 | CG110: 11.306018 | CH110: 13.042524 | CI110: 12.376906 | CJ110: 10.10363 | CK110: 11.405622 | CL110: 9.7560805 | CM110: 8.1884199 | CN110: 10.375344 | CO110: 13.01912 | CP110: 8.4420227 | CQ110: 16.786771 | CR110: 19.801924 | CS110: 9.3876854 | CT110: 11.126974 | CU110: 12.112777 | CV110: 8.6116198 | CW110: 9.2323432 | CX110: 9.2257975 | CY110: 13.8478 | CZ110: 9.0131437 | DA110: 13.96009 | DB110: 14.640056 | DC110: 14.624905 | DD110: 11.167515 | DE110: 12.361575 | DF110: 11.939913 | DG110: 9.89114 | DH110: 10.910647 | DI110: 11.822308 | DJ110: 8.9904883 | DK110: 13.076184 | DL110: 10.326327 | DM110: 15.303642 | DN110: 8.9692126 | DO110: 15.64495 | DP110: 12.652665 | DQ110: 9.0838551 | DR110: 11.862041 | DS110: 9.7017926 | DT110: 8.7023512 | DU110: 9.7750389 | DV110: 12.553286 | DW110: 12.354358 | DX110: 10.833713 | DY110: 14.949632 | DZ110: 10.957578 | EA110: 14.328781 | EB110: 17.445505 | EC110: 10.252625 | ED110: 11.518161 | EE110: 14.980193 | EF110: 13.349272 | EG110: 13.904742 | EH110: 13.140631 | EI110: 12.713523 | EJ110: 10.703103 | EK110: 12.966447 | EL110: 10.457182 | EM110: 14.436666 | EN110: 11.30806 | EO110: 11.122375 | EP110: 13.02035 | EQ110: 8.5762895 | ER110: 9.8383185 | ES110: 11.506418 | ET110: 9.3670973 | EU110: 10.773783 | EV110: 7.3544492 | EW110: 13.229511 | EX110: 11.672058 | EY110: 14.996406 | EZ110: 7.7834707 | FA110: 15.226673 | FB110: 12.190339 | FC110: 12.476633 | FD110: 10.424688 | FE110: 12.801749 | FF110: 11.984372 | FG110: 10.924477 | FH110: 9.9379287 | FI110: 12.562206 | FJ110: 11.200234 | FL110: 97.810979 | FM110: 89.65938 | FN110: 110.68146 | FO110: 132.31092 | FP110: 122.62627 | FQ110: 133.13589 | FR110: 134.74762 | FS110: 145.58512 | FT110: 140.4039 | FU110: 137.75509 | FV110: 155.86805 | FW110: 132.76511 | FX110: ='EDE''s'!C110 -> 127.51277
B111: Edeeste | C111: 78.620414 | D111: 72.252561 | E111: 6.3678524 | F111: 0.088133241 | H111: 78.286922 | I111: -6.0343603 | J111: -0.077080056 | K111: 0 | L111: 5.9288532 | M111: 5.4512557 | N111: 5.7489644 | O111: 6.4446446 | P111: 4.3945655 | Q111: 5.4927393 | R111: 3.3668022 | S111: 4.3489235 | T111: 4.7722024 | U111: 5.0206339 | V111: 4.4076364 | W111: 5.9474392 | X111: 4.9830714 | Y111: 4.9879849 | Z111: 5.6760812 | AA111: 4.7289926 | AB111: 6.0089608 | AC111: 5.8600167 | AD111: 4.8395191 | AE111: 6.5554263 | AF111: 5.3667648 | AG111: 6.33703 | AH111: 10.071519 | AI111: 8.4292909 | AJ111: 4.9209007 | AK111: 5.5530019 | AL111: 8.0416233 | AM111: 5.1489299 | AN111: 4.938888 | AO111: 6.8798738 | AP111: 9.3556858 | AQ111: 5.520896 | AR111: 5.7735259 | AS111: 7.5559172 | AT111: 9.7183905 | AU111: 10.980137 | AV111: 10.702479 | AW111: 9.0160271 | AX111: 8.1876094 | AY111: 9.190022 | AZ111: 9.196179 | BA111: 5.7308315 | BB111: 7.5081327 | BC111: 6.055095 | BD111: 6.1291801 | BE111: 10.108191 | BF111: 6.1557769 | BG111: 11.471529 | BH111: 10.848787 | BI111: 8.167483 | BJ111: 7.3102135 | BK111: 6.2801219 | BL111: 8.4513124 | BM111: 5.9839639 | BN111: 7.3897715 | BO111: 8.0793441 | BP111: 7.2211052 | BQ111: 6.4976919 | BR111: 6.2544361 | BS111: 8.9142085 | BT111: 8.492949 | BU111: 7.9648044 | BV111: 7.2867218 | BW111: 6.9487591 | BX111: 7.348255 | BY111: 6.6264619 | BZ111: 6.353178 | CA111: 7.8168673 | CB111: 8.1337556 | CC111: 60.744443 | CD111: 7.2606356 | CE111: 9.8985006 | CF111: 6.5405615 | CG111: 5.8979303 | CH111: 6.8774504 | CI111: 6.17033 | CJ111: 6.3256421 | CK111: 6.6436578 | CL111: 7.3756019 | CM111: 6.6560239 | CN111: 7.6427957 | CO111: 7.2771678 | CP111: 6.7274368 | CQ111: 9.5267748 | CR111: 6.4466004 | CS111: 7.4543633 | CT111: 6.845844 | CU111: 6.5998005 | CV111: 6.3239147 | CW111: 6.0924596 | CX111: 6.601683 | CY111: 7.5814323 | CZ111: 7.1469795 | DA111: 7.0974714 | DB111: 6.1647529 | DC111: 8.7507826 | DD111: 7.0969596 | DE111: 5.5513009 | DF111: 7.7818972 | DG111: 4.4449254 | DH111: 6.2126277 | DI111: 6.7635702 | DJ111: 6.2371361 | DK111: 7.5041821 | DL111: 6.6488959 | DM111: 6.3645101 | DN111: 7.3287085 | DO111: 9.0840796 | DP111: 7.3543631 | DQ111: 4.5575604 | DR111: 7.4294756 | DS111: 7.0716527 | DT111: 6.9780021 | DU111: 6.7793302 | DV111: 7.5487208 | DW111: 7.4284436 | DX111: 7.3805464 | DY111: 6.824651 | DZ111: 7.1860053 | EA111: 8.9104207 | EB111: 6.9030583 | EC111: 6.9417603 | ED111: 8.0196106 | EE111: 6.9732966 | EF111: 7.476812 | EG111: 6.3343438 | EH111: 7.4666296 | EI111: 7.3643265 | EJ111: 6.8516128 | EK111: 7.237861 | EL111: 6.7176101 | EM111: 10.454664 | EN111: 7.5774605 | EO111: 7.0475295 | EP111: 6.3248038 | EQ111: 5.5537781 | ER111: 7.0590265 | ES111: 7.5164597 | ET111: 7.6392154 | EU111: 5.2136057 | EV111: 6.0696991 | EW111: 6.2257936 | EX111: 6.0251894 | EY111: 7.3854892 | EZ111: 6.1857727 | FA111: 5.880535 | FB111: 5.9467511 | FC111: 7.1146389 | FD111: 6.4073876 | FE111: 8.0505972 | FF111: 8.176143 | FG111: 7.7575485 | FH111: 6.6898311 | FI111: 8.7675372 | FJ111: 7.6436714 | FL111: 61.32466 | FM111: 73.844657 | FN111: 84.387771 | FO111: 99.451053 | FP111: 91.39844 | FQ111: 144.87533 | FR111: 83.661373 | FS111: 83.106084 | FT111: 81.018793 | FU111: 85.449172 | FV111: 88.741585 | FW111: 79.63805 | FX111: ='EDE''s'!C111 -> 78.620414
B112: Gastos de Personal (US$ MM) | C112: 99.829445 | D112: 99.556138 | E112: 0.27330762 | F112: 0.0027452614 | H112: 99.643883 | I112: -0.087745463 | J112: -0.00088059056 | K112: 0 | L112: 5.4080883 | M112: 4.9277348 | N112: 5.4782134 | O112: 6.6023814 | P112: 5.9698069 | Q112: 6.3688192 | R112: 5.6397245 | S112: 6.1019966 | T112: 5.838132 | U112: 5.3555973 | V112: 5.8499992 | W112: 8.9622687 | X112: 5.9869431 | Y112: 5.1719835 | Z112: 5.7359147 | AA112: 6.1965743 | AB112: 5.7938202 | AC112: 5.3399106 | AD112: 6.1526372 | AE112: 6.507203 | AF112: 6.1696356 | AG112: 7.1560328 | AH112: 8.2517906 | AI112: 8.8598702 | AJ112: 5.3186016 | AK112: 5.358688 | AL112: 5.5634194 | AM112: 5.5721528 | AN112: 5.3115192 | AO112: 5.899385 | AP112: 5.980988 | AQ112: 6.2728791 | AR112: 6.004411 | AS112: 6.3194672 | AT112: 7.0050455 | AU112: 10.402913 | AV112: 6.6763537 | AW112: 6.7460667 | AX112: 6.464553 | AY112: 6.5018146 | AZ112: 6.7374795 | BA112: 6.5176007 | BB112: 6.7968692 | BC112: 7.8329191 | BD112: 7.2309572 | BE112: 7.5222177 | BF112: 7.2999068 | BG112: 9.7682389 | BH112: 6.5777441 | BI112: 6.6921152 | BJ112: 6.6967115 | BK112: 6.7444523 | BL112: 6.8519331 | BM112: 6.935406 | BN112: 6.5641897 | BO112: 7.0405939 | BP112: 6.659065 | BQ112: 6.7812385 | BR112: 6.3153182 | BS112: 12.378014 | BT112: 6.974573 | BU112: 7.0304612 | BV112: 7.261445 | BW112: 6.6264551 | BX112: 6.9404096 | BY112: 7.4611026 | BZ112: 6.5784622 | CA112: 7.4129412 | CB112: 7.8755538 | CC112: 6.9049407 | CD112: 7.5328072 | CE112: 12.363534 | CF112: 6.6962147 | CG112: 7.3271846 | CH112: 7.2943747 | CI112: 7.8247662 | CJ112: 6.9015816 | CK112: 7.3416983 | CL112: 8.0008834 | CM112: 7.2137423 | CN112: 7.6873987 | CO112: 7.305189 | CP112: 7.3005277 | CQ112: 12.292287 | CR112: 7.2552959 | CS112: 8.1303391 | CT112: 7.5805472 | CU112: 7.8619278 | CV112: 7.0855615 | CW112: 7.7925925 | CX112: 7.7121984 | CY112: 8.9198242 | CZ112: 7.6030636 | DA112: 7.6941286 | DB112: 7.6831947 | DC112: 13.334553 | DD112: 7.2599032 | DE112: 8.1072485 | DF112: 8.198317 | DG112: 8.0687757 | DH112: 8.029561 | DI112: 7.9646474 | DJ112: 8.6734188 | DK112: 9.1035387 | DL112: 8.2548951 | DM112: 14.791292 | DN112: 8.2611279 | DO112: 13.971761 | DP112: 7.9868011 | DQ112: 8.1766415 | DR112: 8.0517221 | DS112: 8.5424947 | DT112: 8.7880202 | DU112: 7.358684 | DV112: 8.3978274 | DW112: 9.0667169 | DX112: 8.3362481 | DY112: 8.6153595 | DZ112: 8.3482562 | EA112: 14.993263 | EB112: 9.2936522 | EC112: 10.185994 | ED112: 8.5485164 | EE112: 8.9040147 | EF112: 9.0313668 | EG112: 8.3225565 | EH112: 9.7362397 | EI112: 9.2502443 | EJ112: 8.5675575 | EK112: 9.3729372 | EL112: 8.4308039 | EM112: 15.566427 | EN112: 8.2853192 | EO112: 7.8647037 | EP112: 8.0022555 | EQ112: 7.4603479 | ER112: 8.5664417 | ES112: 8.3469353 | ET112: 9.4461004 | EU112: 9.3080542 | EV112: 9.2590637 | EW112: 11.922858 | EX112: 11.094058 | EY112: 14.634019 | EZ112: 7.8814018 | FA112: 9.0891422 | FB112: 9.6845292 | FC112: 8.6135303 | FD112: 8.0789417 | FE112: 11.122164 | FF112: 8.9659689 | FG112: 10.260314 | FH112: 7.9554407 | FI112: 9.2355825 | FJ112: 8.9424302 | FL112: 72.502762 | FM112: 77.322316 | FN112: 75.00947 | FO112: 86.094977 | FP112: 86.236782 | FQ112: 90.962686 | FR112: 93.185848 | FS112: 98.653227 | FT112: 110.68449 | FU112: 106.66203 | FV112: 115.21031 | FW112: 114.19016 | FX112: ='EDE''s'!C112 -> 99.829445
B113: Edenorte | C113: 27.9539 | D113: 27.277316 | E113: 0.6765844 | F113: 0.024803922 | H113: 27.022462 | I113: 0.25485416 | J113: 0.009431197 | K113: 0 | L113: 1.9196274 | M113: 1.6451234 | N113: 1.6307033 | O113: 1.6291582 | P113: 1.9999834 | Q113: 1.6907111 | R113: 1.7136043 | S113: 2.0580398 | T113: 1.9516814 | U113: 1.786208 | V113: 1.8676332 | W113: 3.0967542 | X113: 1.9868665 | Y113: 1.6290154 | Z113: 1.6113951 | AA113: 1.8495809 | AB113: 1.9142165 | AC113: 1.5569941 | AD113: 1.8949734 | AE113: 1.7453138 | AF113: 1.8182598 | AG113: 2.543774 | AH113: 1.8401468 | AI113: 2.9966849 | AJ113: 1.5259908 | AK113: 1.6707754 | AL113: 1.750888 | AM113: 1.8017828 | AN113: 1.6458673 | AO113: 1.6290148 | AP113: 1.8393833 | AQ113: 1.6311759 | AR113: 1.7480642 | AS113: 1.798294 | AT113: 1.9810721 | AU113: 2.9512653 | AV113: 1.7767827 | AW113: 1.8563173 | AX113: 1.8173162 | AY113: 1.85496 | AZ113: 1.9440224 | BA113: 1.7886071 | BB113: 1.9196887 | BC113: 2.4732953 | BD113: 2.2956736 | BE113: 2.158024 | BF113: 2.7816828 | BG113: 2.4519415 | BH113: 2.0091715 | BI113: 1.9511133 | BJ113: 2.0912265 | BK113: 1.9159596 | BL113: 2.0161691 | BM113: 2.2593573 | BN113: 1.8566345 | BO113: 2.2120822 | BP113: 2.1308481 | BQ113: 2.1803915 | BR113: 2.0810994 | BS113: 4.1101088 | BT113: 2.2108859 | BU113: 2.211585 | BV113: 2.3138025 | BW113: 2.1757446 | BX113: 2.1486345 | BY113: 2.2078558 | BZ113: 2.1686797 | CA113: 2.2269825 | CB113: 2.262073 | CC113: 2.3116253 | CD113: 2.1971849 | CE113: 3.93125 | CF113: 2.1296666 | CG113: 2.1946584 | CH113: 2.2233444 | CI113: 2.2322862 | CJ113: 2.2957714 | CK113: 2.248697 | CL113: 2.2969119 | CM113: 2.292699 | CN113: 2.2662852 | CO113: 2.2947138 | CP113: 2.3212921 | CQ113: 3.6959477 | CR113: 2.2032033 | CS113: 2.316221 | CT113: 2.3139356 | CU113: 2.3989445 | CV113: 2.3114965 | CW113: 2.4238149 | CX113: 2.3328876 | CY113: 2.5214048 | CZ113: 2.3930906 | DA113: 2.3903301 | DB113: 2.3562943 | DC113: 3.887595 | DD113: 2.3299161 | DE113: 2.6523229 | DF113: 2.2613341 | DG113: 2.5677212 | DH113: 2.5636955 | DI113: 2.2941941 | DJ113: 2.4149356 | DK113: 2.7054984 | DL113: 2.5251149 | DM113: 9.1350647 | DN113: 2.3367056 | DO113: 3.9409638 | DP113: 2.1579896 | DQ113: 2.3547865 | DR113: 2.2160233 | DS113: 2.4908517 | DT113: 2.4999089 | DU113: 2.2903062 | DV113: 2.5211275 | DW113: 2.3528182 | DX113: 2.3545708 | DY113: 2.5871901 | DZ113: 2.3535278 | EA113: 3.7143995 | EB113: 2.5111114 | EC113: 2.4955585 | ED113: 2.3771388 | EE113: 2.6012613 | EF113: 2.2743139 | EG113: 2.267006 | EH113: 2.6707881 | EI113: 2.3597808 | EJ113: 2.2241709 | EK113: 3.0116344 | EL113: 2.2296975 | EM113: 3.2885909 | EN113: 2.5137191 | EO113: 2.2578143 | EP113: 2.1585853 | EQ113: 2.116162 | ER113: 1.8707863 | ES113: 1.8986697 | ET113: 3.0679473 | EU113: 2.2262994 | EV113: 2.7192781 | EW113: 3.3170445 | EX113: 3.1310097 | EY113: 3.904629 | EZ113: 2.0752403 | FA113: 2.8659066 | FB113: 2.4368253 | FC113: 2.2856042 | FD113: 2.3755164 | FE113: 2.3457002 | FF113: 2.666289 | FG113: 3.4099627 | FH113: 2.158248 | FI113: 2.8311519 | FJ113: 2.5034555 | FL113: 22.989228 | FM113: 23.387221 | FN113: 21.973574 | FO113: 25.118312 | FP113: 26.814162 | FQ113: 28.366304 | FR113: 28.492274 | FS113: 29.849218 | FT113: 37.727467 | FU113: 29.8935 | FV113: 30.311052 | FW113: 31.181945 | FX113: ='EDE''s'!C113 -> 27.9539
B114: Edesur | C114: 43.540089 | D114: 44.949637 | E114: -1.4095485 | F114: -0.031358395 | H114: 45.480518 | I114: -0.53088067 | J114: -0.011672705 | K114: 0 | L114: 2.0827529 | M114: 1.9154763 | N114: 2.1673268 | O114: 2.0726792 | P114: 2.1523365 | Q114: 2.1445787 | R114: 2.1227301 | S114: 2.4227433 | T114: 2.1485262 | U114: 2.0712288 | V114: 2.3928431 | W114: 3.498697 | X114: 2.5411281 | Y114: 2.1500619 | Z114: 2.0711792 | AA114: 2.4332185 | AB114: 2.0823338 | AC114: 2.2522061 | AD114: 2.1016096 | AE114: 2.6371704 | AF114: 2.2409824 | AG114: 2.6895512 | AH114: 4.0373552 | AI114: 3.1569426 | AJ114: 1.8895897 | AK114: 1.8746004 | AL114: 2.152525 | AM114: 1.8709896 | AN114: 1.8214181 | AO114: 1.830002 | AP114: 1.7750121 | AQ114: 2.1928706 | AR114: 1.8171873 | AS114: 1.6595307 | AT114: 2.2808965 | AU114: 3.369348 | AV114: 2.2568504 | AW114: 2.1417384 | AX114: 2.1165071 | AY114: 2.0823742 | AZ114: 2.1432358 | BA114: 2.1071235 | BB114: 2.1843712 | BC114: 2.8308192 | BD114: 1.7095428 | BE114: 2.698082 | BF114: 2.07374 | BG114: 3.4511158 | BH114: 2.2983882 | BI114: 2.3165368 | BJ114: 2.2656859 | BK114: 2.4471599 | BL114: 2.3899762 | BM114: 2.3364877 | BN114: 2.3281808 | BO114: 2.3534085 | BP114: 2.2639641 | BQ114: 2.350764 | BR114: 1.9097506 | BS114: 4.4255056 | BT114: 2.4097606 | BU114: 2.3176591 | BV114: 2.3286115 | BW114: 2.0261978 | BX114: 2.3758524 | BY114: 2.8345412 | BZ114: 1.9883204 | CA114: 2.7971541 | CB114: 3.1540457 | CC114: 2.196362 | CD114: 2.9592867 | CE114: 4.3702918 | CF114: 2.1005904 | CG114: 2.4596464 | CH114: 2.4526006 | CI114: 3.0896395 | CJ114: 2.1603345 | CK114: 2.571616 | CL114: 3.1823818 | CM114: 2.4059786 | CN114: 3.0386522 | CO114: 2.6753156 | CP114: 2.6553997 | CQ114: 4.541267 | CR114: 2.6768022 | CS114: 3.1007391 | CT114: 2.6136557 | CU114: 2.9494665 | CV114: 2.2577826 | CW114: 2.9312525 | CX114: 2.9700923 | CY114: 3.9395313 | CZ114: 2.8738279 | DA114: 3.035396 | DB114: 3.0528984 | DC114: 5.7338407 | DD114: 2.619693 | DE114: 3.0361439 | DF114: 3.6158133 | DG114: 3.2612905 | DH114: 3.2353798 | DI114: 3.2171533 | DJ114: 3.9622649 | DK114: 4.0126708 | DL114: 3.4817839 | DM114: 3.5419877 | DN114: 3.6361697 | DO114: 6.4527341 | DP114: 3.6114745 | DQ114: 3.3858674 | DR114: 3.4436445 | DS114: 3.9280475 | DT114: 4.0693933 | DU114: 2.9235146 | DV114: 3.6779207 | DW114: 4.2938199 | DX114: 3.8626971 | DY114: 3.8383166 | DZ114: 3.8259293 | EA114: 7.0309398 | EB114: 4.4212319 | EC114: 5.3656824 | ED114: 3.684204 | EE114: 3.8095436 | EF114: 3.7612426 | EG114: 3.8427709 | EH114: 4.4114016 | EI114: 4.4781134 | EJ114: 3.8781753 | EK114: 3.9518941 | EL114: 3.8762579 | EM114: 7.8335377 | EN114: 3.3747841 | EO114: 3.1006489 | EP114: 3.3707874 | EQ114: 3.6114053 | ER114: 4.2221173 | ES114: 4.1689608 | ET114: 3.7737079 | EU114: 4.417567 | EV114: 3.7909207 | EW114: 5.797743 | EX114: 5.3209946 | EY114: 6.8615204 | EZ114: 3.5373692 | FA114: 3.8821239 | FB114: 4.6234716 | FC114: 4.1534554 | FD114: 3.4229188 | FE114: 5.3562497 | FF114: 3.3336162 | FG114: 3.3916014 | FH114: 3.4384562 | FI114: 4.2171924 | FJ114: 4.1836338 | FL114: 27.191919 | FM114: 30.393739 | FN114: 24.53397 | FO114: 27.7955 | FP114: 29.685808 | FQ114: 31.758083 | FR114: 33.333422 | FS114: 38.135285 | FT114: 44.073085 | FU114: 47.891565 | FV114: 53.314055 | FW114: 51.811157 | FX114: ='EDE''s'!C114 -> 43.540089
B115: Edeeste | C115: 28.335457 | D115: 27.329185 | E115: 1.0062717 | F115: 0.036820407 | H115: 27.140904 | I115: 0.18828105 | J115: 0.0069371693 | K115: 0 | L115: 1.405708 | M115: 1.3671351 | N115: 1.6801833 | O115: 2.900544 | P115: 1.817487 | Q115: 2.5335294 | R115: 1.8033901 | S115: 1.6212135 | T115: 1.7379244 | U115: 1.4981605 | V115: 1.5895228 | W115: 2.3668176 | X115: 1.4589485 | Y115: 1.3929062 | Z115: 2.0533403 | AA115: 1.913775 | AB115: 1.7972698 | AC115: 1.5307105 | AD115: 2.1560542 | AE115: 2.1247189 | AF115: 2.1103933 | AG115: 1.9227077 | AH115: 2.3742886 | AI115: 2.7062426 | AJ115: 1.903021 | AK115: 1.8133122 | AL115: 1.6600063 | AM115: 1.8993804 | AN115: 1.8442338 | AO115: 2.4403681 | AP115: 2.3665927 | AQ115: 2.4488325 | AR115: 2.4391595 | AS115: 2.8616425 | AT115: 2.7430769 | AU115: 4.0823 | AV115: 2.6427206 | AW115: 2.748011 | AX115: 2.5307297 | AY115: 2.5644804 | AZ115: 2.6502213 | BA115: 2.62187 | BB115: 2.6928093 | BC115: 2.5288046 | BD115: 3.2257408 | BE115: 2.6661116 | BF115: 2.4444839 | BG115: 3.8651816 | BH115: 2.2701845 | BI115: 2.4244651 | BJ115: 2.3397991 | BK115: 2.3813327 | BL115: 2.4457878 | BM115: 2.339561 | BN115: 2.3793744 | BO115: 2.4751032 | BP115: 2.2642528 | BQ115: 2.250083 | BR115: 2.3244682 | BS115: 3.8424001 | BT115: 2.3539265 | BU115: 2.5012171 | BV115: 2.619031 | BW115: 2.4245127 | BX115: 2.4159227 | BY115: 2.4187056 | BZ115: 2.4214621 | CA115: 2.3888046 | CB115: 2.4594351 | CC115: 2.3969534 | CD115: 2.3763356 | CE115: 4.0619927 | CF115: 2.4659577 | CG115: 2.6728798 | CH115: 2.6184296 | CI115: 2.5028405 | CJ115: 2.4454756 | CK115: 2.5213854 | CL115: 2.5215896 | CM115: 2.5150646 | CN115: 2.3824614 | CO115: 2.3351596 | CP115: 2.3238359 | CQ115: 4.0550722 | CR115: 2.3752904 | CS115: 2.7133789 | CT115: 2.6529559 | CU115: 2.5135169 | CV115: 2.5162825 | CW115: 2.4375251 | CX115: 2.4092185 | CY115: 2.4588882 | CZ115: 2.3361451 | DA115: 2.2684025 | DB115: 2.274002 | DC115: 3.7131173 | DD115: 2.3102941 | DE115: 2.4187817 | DF115: 2.3211696 | DG115: 2.239764 | DH115: 2.2304856 | DI115: 2.4533 | DJ115: 2.2962183 | DK115: 2.3853695 | DL115: 2.2479963 | DM115: 2.1142392 | DN115: 2.2882527 | DO115: 3.5780636 | DP115: 2.2173369 | DQ115: 2.4359876 | DR115: 2.3920542 | DS115: 2.1235955 | DT115: 2.2187179 | DU115: 2.1448632 | DV115: 2.1987792 | DW115: 2.4200788 | DX115: 2.1189802 | DY115: 2.1898528 | DZ115: 2.1687991 | EA115: 4.2479233 | EB115: 2.3613089 | EC115: 2.3247531 | ED115: 2.4871737 | EE115: 2.4932098 | EF115: 2.9958104 | EG115: 2.2127796 | EH115: 2.65405 | EI115: 2.41235 | EJ115: 2.4652114 | EK115: 2.4094087 | EL115: 2.3248485 | EM115: 4.4442989 | EN115: 2.396816 | EO115: 2.5062405 | EP115: 2.4728828 | EQ115: 1.7327806 | ER115: 2.473538 | ES115: 2.2793049 | ET115: 2.6044451 | EU115: 2.6641878 | EV115: 2.7488648 | EW115: 2.8080706 | EX115: 2.6420541 | EY115: 3.8678696 | EZ115: 2.2687922 | FA115: 2.3411117 | FB115: 2.6242323 | FC115: 2.1744707 | FD115: 2.2805064 | FE115: 3.4202138 | FF115: 2.9660637 | FG115: 3.4587501 | FH115: 2.3587365 | FI115: 2.1872383 | FJ115: 2.255341 | FL115: 22.321616 | FM115: 23.541356 | FN115: 28.501926 | FO115: 33.181165 | FP115: 29.736812 | FQ115: 30.838299 | FR115: 31.360152 | FS115: 30.668723 | FT115: 28.883934 | FU115: 28.876969 | FV115: 31.585203 | FW115: 31.197055 | FX115: ='EDE''s'!C115 -> 28.335457
B116: Proveedores (US$ MM) | C116: 133.24366 | D116: 119.658 | E116: 13.585665 | F116: 0.11353745 | H116: 155.87948 | I116: -36.221478 | J116: -0.23236849 | K116: 0 | L116: 12.298437 | M116: 9.2206876 | N116: 11.032534 | O116: 7.7145517 | P116: 7.7002411 | Q116: 9.0225094 | R116: 8.2641172 | S116: 7.4798897 | T116: 9.3739282 | U116: 9.1477211 | V116: 7.7878047 | W116: 8.9936239 | X116: 9.8090051 | Y116: 6.3993537 | Z116: 9.0503711 | AA116: 6.9555339 | AB116: 8.501383 | AC116: 7.4237643 | AD116: 6.1522357 | AE116: 8.2137772 | AF116: 6.9698501 | AG116: 8.1433126 | AH116: 11.087276 | AI116: 10.032384 | AJ116: 7.1146258 | AK116: 5.148357 | AL116: 13.157824 | AM116: 8.3821455 | AN116: 8.0053731 | AO116: 8.6577907 | AP116: 11.958641 | AQ116: 9.494186 | AR116: 9.6478478 | AS116: 13.202707 | AT116: 14.412533 | AU116: 18.247089 | AV116: 12.488972 | AW116: 12.020851 | AX116: 10.835715 | AY116: 15.37805 | AZ116: 18.938181 | BA116: 10.253941 | BB116: 11.934855 | BC116: 9.4626473 | BD116: 5.5684764 | BE116: 15.761702 | BF116: 11.970548 | BG116: 13.594608 | BH116: 16.471289 | BI116: 10.491478 | BJ116: 8.8422633 | BK116: 12.53339 | BL116: 13.110468 | BM116: 9.0332812 | BN116: 10.3779 | BO116: 10.164866 | BP116: 11.123494 | BQ116: 9.7080818 | BR116: 9.913993 | BS116: 13.707333 | BT116: 14.162954 | BU116: 13.229817 | BV116: 10.950688 | BW116: 13.022199 | BX116: 11.380909 | BY116: 7.4709753 | BZ116: 12.252957 | CA116: 9.0278388 | CB116: 12.691051 | CC116: 14.622265 | CD116: 12.030356 | CE116: 14.32044 | CF116: 10.881397 | CG116: 11.393311 | CH116: 12.821437 | CI116: 12.530064 | CJ116: 10.576035 | CK116: 11.934396 | CL116: 10.588363 | CM116: 9.5272817 | CN116: 8.9880384 | CO116: 13.751169 | CP116: 8.7249465 | CQ116: 17.34847 | CR116: 18.198175 | CS116: 9.758748 | CT116: 10.716068 | CU116: 9.9268197 | CV116: 8.9555818 | CW116: 10.457041 | CX116: 9.7794037 | CY116: 13.497378 | CZ116: 8.4122685 | DA116: 14.398419 | DB116: 14.061303 | DC116: 12.034251 | DD116: 11.896134 | DE116: 9.6034818 | DF116: 12.013434 | DG116: 6.696027 | DH116: 12.273567 | DI116: 11.730085 | DJ116: 9.3615718 | DK116: 13.936201 | DL116: 10.252453 | DM116: 16.332864 | DN116: 9.1191622 | DO116: 14.286827 | DP116: 13.531479 | DQ116: 8.7116644 | DR116: 12.627237 | DS116: 11.213184 | DT116: 9.7098784 | DU116: 13.122 | DV116: 15.383083 | DW116: 13.305184 | DX116: 12.103209 | DY116: 15.366041 | DZ116: 11.238104 | EA116: 13.115451 | EB116: 17.123038 | EC116: 11.293277 | ED116: 13.952957 | EE116: 21.232287 | EF116: 15.077143 | EG116: 14.034173 | EH116: 14.686218 | EI116: 12.103154 | EJ116: 11.234507 | EK116: 13.619602 | EL116: 11.523122 | EM116: 12.92389 | EN116: 14.059143 | EO116: 9.9931235 | EP116: 13.790177 | EQ116: 9.7238835 | ER116: 10.499751 | ES116: 14.093019 | ET116: 11.338649 | EU116: 8.8156182 | EV116: 7.0591935 | EW116: 11.016703 | EX116: 9.2687399 | EY116: 10.669463 | EZ116: 9.0805633 | FA116: 13.302676 | FB116: 11.127182 | FC116: 10.634076 | FD116: 11.3784 | FE116: 10.757292 | FF116: 13.088981 | FG116: 13.313699 | FH116: 10.641539 | FI116: 15.921048 | FJ116: 13.998208 | FL116: 108.03605 | FM116: 98.738246 | FN116: 127.42912 | FO116: 148.20855 | FP116: 135.47784 | FQ116: 145.16245 | FR116: 139.06491 | FS116: 140.19546 | FT116: 137.50181 | FU116: 149.42652 | FV116: 168.80337 | FW116: 130.32746 | FX116: ='EDE''s'!C116 -> 133.24366
B117: Edenorte | C117: 45.095467 | D117: 48.779157 | E117: -3.6836892 | F117: -0.07551769 | H117: 62.579561 | I117: -13.800404 | J117: -0.22052574 | K117: 0 | L117: 3.4078317 | M117: 3.4594288 | N117: 3.2959963 | O117: 2.6219931 | P117: 2.6532221 | Q117: 3.1535541 | R117: 2.1652483 | S117: 2.2985226 | T117: 2.9821117 | U117: 2.9765598 | V117: 2.343583 | W117: 3.2501542 | X117: 1.945443 | Y117: 1.5732931 | Z117: 2.6418299 | AA117: 2.4062875 | AB117: 2.3508077 | AC117: 3.1252536 | AD117: 1.9541699 | AE117: 1.9981879 | AF117: 1.9375297 | AG117: 1.9332427 | AH117: 2.1136487 | AI117: 2.2177591 | AJ117: 1.8694039 | AK117: 2.1407 | AL117: 2.5894889 | AM117: 2.6714764 | AN117: 2.7365753 | AO117: 2.1140141 | AP117: 2.8592924 | AQ117: 3.1234962 | AR117: 2.4994277 | AS117: 2.4914408 | AT117: 2.3070329 | AU117: 2.7264327 | AV117: 2.5912389 | AW117: 2.6435011 | AX117: 3.0362792 | AY117: 2.2390728 | AZ117: 2.0812303 | BA117: 2.546721 | BB117: 2.873553 | BC117: 2.9370256 | BD117: 2.3669677 | BE117: 3.9639787 | BF117: 2.6669859 | BG117: 3.4027191 | BH117: 3.3835532 | BI117: 3.6523666 | BJ117: 3.3049367 | BK117: 2.5936509 | BL117: 2.7522185 | BM117: 2.6712474 | BN117: 3.3637919 | BO117: 2.7372822 | BP117: 3.6176648 | BQ117: 2.79904 | BR117: 2.8409882 | BS117: 3.4798711 | BT117: 3.4806291 | BU117: 3.5532359 | BV117: 3.7851075 | BW117: 3.8491993 | BX117: 3.2746699 | BY117: 2.7876645 | BZ117: 3.948506 | CA117: 2.9487269 | CB117: 4.1993997 | CC117: 3.9070599 | CD117: 3.5668443 | CE117: 3.961873 | CF117: 4.0742143 | CG117: 3.477227 | CH117: 4.1449342 | CI117: 4.0108171 | CJ117: 3.473583 | CK117: 3.9511531 | CL117: 3.9174458 | CM117: 4.1685469 | CN117: 3.1742217 | CO117: 3.4645892 | CP117: 3.5522748 | CQ117: 4.6594005 | CR117: 2.6558536 | CS117: 2.7633049 | CT117: 3.2515161 | CU117: 2.7513112 | CV117: 3.5888061 | CW117: 4.8651538 | CX117: 3.2462884 | CY117: 3.6308071 | CZ117: 3.3304146 | DA117: 4.6268574 | DB117: 4.3111843 | DC117: 4.2853746 | DD117: 4.1087716 | DE117: 3.062175 | DF117: 3.6511324 | DG117: 2.6711935 | DH117: 5.4692248 | DI117: 3.9264299 | DJ117: 4.7559564 | DK117: 4.6467425 | DL117: 3.8987168 | DM117: 4.6546518 | DN117: 4.1612705 | DO117: 4.8149941 | DP117: 4.8611493 | DQ117: 4.931712 | DR117: 3.8078174 | DS117: 4.0316082 | DT117: 5.1027514 | DU117: 5.8440201 | DV117: 6.140882 | DW117: 5.5408969 | DX117: 5.4666385 | DY117: 4.7632691 | DZ117: 4.8168798 | EA117: 5.3579529 | EB117: 5.2112463 | EC117: 5.7128635 | ED117: 5.4390738 | EE117: 10.195442 | EF117: 5.8010229 | EG117: 4.5452056 | EH117: 6.280823 | EI117: 4.4248417 | EJ117: 4.9916912 | EK117: 5.0785494 | EL117: 4.8988016 | EM117: 5.7443094 | EN117: 5.210802 | EO117: 3.8601747 | EP117: 4.8995421 | EQ117: 3.9210649 | ER117: 3.9388748 | ES117: 5.2209511 | ET117: 4.7953841 | EU117: 4.7124613 | EV117: 3.4585317 | EW117: 4.7290489 | EX117: 4.0323211 | EY117: 3.9889875 | EZ117: 3.983329 | FA117: 3.1676165 | FB117: 4.4275561 | FC117: 3.6177797 | FD117: 4.4138861 | FE117: 2.7022372 | FF117: 3.687614 | FG117: 4.2455246 | FH117: 3.4929778 | FI117: 5.4504386 | FJ117: 5.9065077 | FL117: 34.608206 | FM117: 26.197453 | FN117: 30.128781 | FO117: 33.349273 | FP117: 37.196612 | FQ117: 43.262916 | FR117: 46.068408 | FS117: 43.306872 | FT117: 49.821259 | FU117: 60.665578 | FV117: 68.32387 | FW117: 52.768144 | FX117: ='EDE''s'!C117 -> 45.095467
B118: Edesur | C118: 57.85675 | D118: 47.380241 | E118: 10.476509 | F118: 0.22111557 | H118: 67.146063 | I118: -19.765822 | J118: -0.29437053 | K118: 0 | L118: 5.2262204 | M118: 2.993211 | N118: 4.572496 | O118: 2.7411113 | P118: 4.1972995 | Q118: 3.7181459 | R118: 5.4554767 | S118: 3.2896496 | T118: 4.3598532 | U118: 3.6663225 | V118: 3.6831128 | W118: 3.023856 | X118: 5.3458904 | Y118: 2.2660817 | Z118: 4.0549757 | AA118: 2.861231 | AB118: 3.1556262 | AC118: 0.97919346 | AD118: 2.4306794 | AE118: 2.9864409 | AF118: 3.0905361 | AG118: 2.9501937 | AH118: 2.7006265 | AI118: 3.7523433 | AJ118: 3.4404537 | AK118: 0.45232959 | AL118: 5.5488821 | AM118: 3.9570103 | AN118: 3.1515136 | AO118: 3.9418912 | AP118: 3.7557675 | AQ118: 5.0228447 | AR118: 5.2727228 | AS118: 7.6432238 | AT118: 7.3883449 | AU118: 10.374299 | AV118: 4.1397845 | AW118: 5.4596816 | AX118: 4.0155911 | AY118: 8.1994107 | AZ118: 12.314591 | BA118: 6.241747 | BB118: 5.9740756 | BC118: 4.7666755 | BD118: 1.8445896 | BE118: 6.0234756 | BF118: 6.0776276 | BG118: 6.2052774 | BH118: 6.2998165 | BI118: 3.0167852 | BJ118: 2.5952774 | BK118: 7.6048307 | BL118: 6.094141 | BM118: 4.0953736 | BN118: 3.9707715 | BO118: 3.6539431 | BP118: 4.4850742 | BQ118: 4.3509335 | BR118: 4.7152754 | BS118: 6.8500837 | BT118: 6.3976292 | BU118: 6.2229091 | BV118: 4.4030717 | BW118: 6.1115878 | BX118: 5.222598 | BY118: 2.6794769 | BZ118: 6.6158643 | CA118: 3.6521121 | CB118: 5.7634259 | CC118: 7.2716746 | CD118: 5.4745971 | CE118: 6.1791529 | CF118: 4.3632605 | CG118: 6.0162791 | CH118: 6.2996461 | CI118: 6.4115158 | CJ118: 4.7039279 | CK118: 5.4171825 | CL118: 3.4193298 | CM118: 2.8298444 | CN118: 3.3720963 | CO118: 7.7026779 | CP118: 2.6433802 | CQ118: 9.4473815 | CR118: 13.328124 | CS118: 4.4242052 | CT118: 5.2786109 | CU118: 5.0478653 | CV118: 3.4495851 | CW118: 3.8739241 | CX118: 4.2583459 | CY118: 7.2953768 | CZ118: 2.3679875 | DA118: 7.4998135 | DB118: 7.9266082 | DC118: 5.179991 | DD118: 4.9648303 | DE118: 5.2875318 | DF118: 5.3258573 | DG118: 3.7959308 | DH118: 4.4742227 | DI118: 5.5808014 | DJ118: 2.911159 | DK118: 6.6782896 | DL118: 3.8476046 | DM118: 9.7205726 | DN118: 2.4384035 | DO118: 6.7129067 | DP118: 6.360479 | DQ118: 3.26421 | DR118: 6.8479018 | DS118: 4.6694162 | DT118: 2.1849102 | DU118: 4.6926573 | DV118: 6.8460153 | DW118: 5.5469973 | DX118: 4.1579397 | DY118: 8.2730876 | DZ118: 4.1592954 | EA118: 5.4250688 | EB118: 9.6146844 | EC118: 3.1428988 | ED118: 5.7506966 | EE118: 8.5449795 | EF118: 7.1244918 | EG118: 7.6314712 | EH118: 5.7962652 | EI118: 5.2183999 | EJ118: 3.8538996 | EK118: 6.2477779 | EL118: 4.2204981 | EM118: 4.477547 | EN118: 5.8299014 | EO118: 3.9025299 | EP118: 6.6458924 | EQ118: 3.9049331 | ER118: 3.8122596 | ES118: 6.0614813 | ET118: 3.8157735 | EU118: 3.6202977 | EV118: 1.6913558 | EW118: 4.6603775 | EX118: 3.4354386 | EY118: 5.0481563 | EZ118: 2.6539821 | FA118: 7.99009 | FB118: 5.2593742 | FC118: 4.3156142 | FD118: 4.7467864 | FE118: 5.3093602 | FF118: 5.922058 | FG118: 6.3762805 | FH118: 4.0982496 | FI118: 6.5060212 | FJ118: 4.6789333 | FL118: 46.926755 | FM118: 36.573818 | FN118: 59.949283 | FO118: 71.262527 | FP118: 57.732306 | FQ118: 65.9941 | FR118: 62.626522 | FS118: 69.930438 | FT118: 61.73811 | FU118: 62.427978 | FV118: 71.62361 | FW118: 52.428397 | FX118: ='EDE''s'!C118 -> 57.85675
